Workbook
Name ACTION: #REF!
Name ACTION: #REF!

Sheet Cover
B2: TEST REPORT DOCUMENT
A4: Project Name | B4: EduBus School Bus Management System | E4: Creator | F4: NhiPTK
A5: Project Code | B5: ESBMS | E5: Issue Date | F5: 45912
A6: Document Code | B6: =B5&"_"&"Test Report"&"_"&"v1.0" -> ESBMS_Test Report_v1.0 | E6: Version
A9: Record of change
A10: Effective Date | B10: Version | C10: Change Item | D10: *A,D,M | E10: Change description | F10: Reference
A11: 45912 | B11: 1.0 | C11: Initial Test Requirements | D11: A | E11: - Add initial test requirements - Define overall project scope
A12: 45912 | B12: 1.1 | C12: Project Scope Update | D12: M | E12: - Update project scope based on instructor feedback
A13: 45913 | B13: 1.2 | C13: Functional Requirements Update | D13: M | E13: - Modify and refine functional requirements
A14: 45913 | B14: 1.3 | C14: Test Case Refinement | D14: M | E14: - Improve test cases and test scenarios
A15: 45914 | B15: 1.4 | C15: Final Project Update | D15: M | E15: - Finalize documentation and update project content

Sheet Test Cases
D1: TEST CASE LIST
B3: Project Name | D3: EduBus School Bus Management System
B4: Project Code | D4: ESBMS
B5: Test Environment Setup Description | D5: 1. Server 2. Database 3. Web Browser
B8: No | C8: Function Name | D8: Sheet Name | E8: Description | F8: Pre-Condition
B9: 1 | C9: Login | D9: User Account Management | E9: Allow users to log into the system with valid credentials. | F9: Must connect with server
B10: 2 | C10: Logout | D10: User Account Management | E10: Allow users to securely log out of the system. | F10: Must connect with server
B11: 3 | C11: Change password | D11: User Account Management | E11: Users can change their current password to a new one. | F11: Must connect with server
B12: 4 | C12: Forgot password | D12: User Account Management | E12: Allow users to reset their password via email/OTP. | F12: Must connect with server
B13: 5 | C13: Edit personal profile | D13: User Account Management | E13: Allow users to update their personal information. | F13: Must connect with server
B14: 6 | C14: View personal profile | D14: User Account Management | E14: Display user’s personal information. | F14: Must connect with server
B15: 7 | C15: Create user accounts | D15: User Account Management | E15: Allow admins to create new user accounts. | F15: Must connect with server
B16: 8 | C16: Import driver/parent file | D16: User Account Management | E16: Allow admins to bulk-import users from a file. | F16: Must connect with server
B17: 9 | C17: View user list | D17: User Account Management | E17: Display the list of all system users. | F17: Must connect with server
B18: 10 | C18: Ban/Unban users | D18: User Account Management | E18: Allow admins to restrict or restore user access. | F18: Must connect with server
B19: 11 | C19: Upload user avatar | D19: User Account Management | E19: Allow users to upload or change their profile picture. | F19: Must connect with server
B20: 12 | C20: View driver’s information (Parent) | D20: User Account Management | E20: Display assigned driver details for parents. | F20: Must connect with server
... B90: 85 | C90: Delete unit price | D90: School System Configuration | E90: Allow admins to remove pricing items. | F90: Must connect with server

Sheet Test Statistics
B1: TEST STATISTICS
B3: Project Name | C3: EduBus School Bus Management System | E3: Creator | H3: HuyNLQ, NguyetNTT, TrungNVT, NhiPTK, KhoiVN
B4: Project Code | C4: ESBMS | E4: Reviewer/Approver
B5: Document Code | C5: =C4&"_"&"Test Report"&"_"&"1.0" -> ESBMS_Test Report_1.0 | E5: Issue Date | H5: 45912
B6: Notes
B10: No | C10: Module code | D10: Passed | E10: Failed | F10: Pending | G10: N/A | H10: Number of test cases
B11: 1 | C11: ='User Account Management'!B2 -> User Account Management | D11: ='User Account Management'!B8 -> 109 | E11: ='User Account Management'!C8 -> 1 | F11: ='User Account Management'!D6 -> 0 | G11: ='User Account Management'!E6 -> 1 | H11: ='User Account Management'!B4 -> 112
B12: 2 | C12: ='Service Registration & Payment'!B2 -> Service Registration & Payment | D12: ='Service Registration & Payment'!B8 -> 24 | E12: ='Service Registration & Payment'!C8 -> 0 | F12: ='Service Registration & Payment'!D6 -> 0 | G12: ='Service Registration & Payment'!E6 -> 0 | H12: ='Service Registration & Payment'!B4 -> 26
B13: 3 | C13: ='Student Management'!B2 -> Student management | D13: ='Student Management'!B8 -> 41 | E13: ='Student Management'!C8 -> 0 | F13: ='Student Management'!D8 -> 0 | G13: ='Student Management'!E6 -> 1 | H13: ='Student Management'!B4 -> 44
B14: 4 | C14: ='Vehicle Management'!B2 -> Verifies the complete vehicle management flow—including registering, editing, assigning, monitoring, and deactivating vehicles—covering input validation, operational constraints, assignment consistency, safety parameters, and role-based permissions. | D14: ='Vehicle Management'!B8 -> 22 | E14: ='Vehicle Management'!C8 -> 3 | F14: ='Vehicle Management'!D8 -> 2 | G14: ='Vehicle Management'!E6 -> 0 | H14: ='Vehicle Management'!B4 -> 27
B15: 5 | C15: ='Route Management'!B2 -> Route Management | D15: ='Route Management'!B8 -> 54 | E15: ='Route Management'!C8 -> 0 | F15: ='Route Management'!D8 -> 0 | G15: ='Route Management'!E6 -> 0 | H15: ='Route Management'!B4 -> 54
B16: 6 | C16: ='Schedule Management'!B2 -> Schedule Management | D16: ='Schedule Management'!B8 -> 122 | E16: ='Schedule Management'!C8 -> 3 | F16: ='Schedule Management'!D7 -> 0 | G16: ='Schedule Management'!E7 -> 0 | H16: ='Schedule Management'!B4 -> 125
B17: 7 | C17: ='Trip Management'!B2 -> Trip Management | D17: ='Trip Management'!B8 -> 52 | E17: ='Trip Management'!C8 -> 0 | F17: ='Trip Management'!D6 -> 0 | G17: ='Trip Management'!E6 -> 0 | H17: ='Trip Management'!B4 -> 52
B18: 8 | C18: ='Atendance Management'!B2 -> Attendance Management | D18: ='Atendance Management'!B8 -> 38 | E18: ='Atendance Management'!C8 -> 0 | F18: ='Atendance Management'!D6 -> 0 | G18: ='Atendance Management'!E6 -> 0 | H18: ='Atendance Management'!B4 -> 38
B19: 9 | C19: ='Vehicle Status Monitoring'!B2 -> Vehicle Status Monitoring | D19: ='Vehicle Status Monitoring'!B8 -> 9 | E19: ='Vehicle Status Monitoring'!C8 -> 0 | F19: ='Vehicle Status Monitoring'!D6 -> 0 | G19: ='Vehicle Status Monitoring'!E6 -> 0 | H19: ='Vehicle Status Monitoring'!B4 -> 12
B20: 10 | C20: =Notifications!B2 -> Notifications | D20: =Notifications!B8 -> 10 | E20: =Notifications!C8 -> 2 | F20: =Notifications!D6 -> 0 | G20: =Notifications!E6 -> 0 | H20: =Notifications!B4 -> 12
B21: 11 | C21: ='PickupDrop-off Address Manageme'!B2 -> Pickup/Drop-off Address Management | D21: ='PickupDrop-off Address Manageme'!B8 -> 8 | E21: ='PickupDrop-off Address Manageme'!C8 -> 0 | F21: ='PickupDrop-off Address Manageme'!D6 -> 0 | G21: ='PickupDrop-off Address Manageme'!E6 -> 0 | H21: ='PickupDrop-off Address Manageme'!B4 -> 10
B22: 12 | C22: =Reporting!B2 -> Reporting | D22: =Reporting!B8 -> 16 | E22: =Reporting!C8 -> 3 | F22: =Reporting!D6 -> 0 | G22: =Reporting!E6 -> 1 | H22: =Reporting!B4 -> 20
B23: 13 | C23: ='Audit Logs'!B2 -> Audit Logs | D23: ='Audit Logs'!B8 -> 6 | E23: ='Audit Logs'!C8 -> 2 | F23: ='Audit Logs'!D6 -> 0 | G23: ='Audit Logs'!E6 -> 0 | H23: ='Audit Logs'!B4 -> 8
B24: 14 | C24: ='School System Configuration'!B2 -> School System Configuration | D24: ='School System Configuration'!B8 -> 23 | E24: ='School System Configuration'!C8 -> 0 | F24: ='School System Configuration'!D6 -> 1 | G24: ='School System Configuration'!E6 -> 0 | H24: ='School System Configuration'!B4 -> 26
C25: Sub total | D25: =SUM(D11:D24) -> 534 | E25: =SUM(E11:E24) -> 14 | F25: =SUM(F11:F24) -> 3 | G25: =SUM(G11:G24) -> 3 | H25: =SUM(H11:H24) -> 566
C27: Test coverage | E27: =(D25+E25)*100/(H25-G25) -> 97.335702 | F27: %
C28: Test successful coverage | E28: =D25*100/(H25-G25) -> 94.849023 | F28: %

Sheet User Account Management
A2: Feature | B2: User Account Management | R2: Passed
A3: Test requirement | B3: Verifies the full auth flow—register, email/Google login, password reset, and logout—covering input validation, account status checks, security (rate-limit, token/redirect safety), session handling, and graceful error responses. | R3: Failed
A4: Number of TCs | B4: =COUNTA(A12:A1008)-7 -> 112 | R4: Pending
A5: Testing Round | B5: Passed | C5: Failed | D5: Pending | E5: N/A | R5: N/A
A6: Round 1 | B6: =COUNTIF($F10:$F1026,B5) -> 95 | C6: =COUNTIF($F10:$F981,C5) -> 16 | D6: =COUNTIF($F10:$F981,D5) -> 0 | E6: =COUNTIF($F10:$F981,E5) -> 1
A7: Round 2 | B7: =COUNTIF($I10:$I1007,B5) -> 107 | C7: =COUNTIF($I10:$I1007,C5) -> 4 | D7: =COUNTIF($F10:$F981,D5) -> 0 | E7: =COUNTIF($F10:$F981,E5) -> 1
A8: Round 3 | B8: =COUNTIF($L10:$L1007,B5) -> 109 | C8: =COUNTIF($L10:$L1007,C5) -> 1 | D8: =COUNTIF($L10:$L1007,D5) -> 0 | E8: =COUNTIF($F10:$F981,E5) -> 1
A10: Test Case ID | B10: Test Case Description | C10: Test Case Procedure | D10: Expected Results | E10: Pre-conditions | F10: Round 1 | G10: Test date | H10: Tester | I10: Round 2 | J10: Test date | K10: Tester | L10: Round 3 | M10: Test date | N10: Tester | O10: Note
A11: View user lists
A12: VIEW-USERS-001 | B12: View user list with default settings | C12: 1. Login as admin successfully. 2. Navigate to "/admin/users" page. 3. Check user list display. | D12: 1. User list loads successfully. 2. Default 20 users per page are displayed. 3. Users are sorted by first name in ascending order. 4. Pagination controls are visible. 5. Search box and filter options are available. | E12: 1. Admin is logged in. 2. System has users in database. | F12: Passed | G12: 45914 | H12: TrungNVT | I12: Passed | J12: 45954 | K12: HuyNLQ | L12: Passed | M12: 45974 | N12: TrungNVT
A13: VIEW-USERS-002 | B13: View user list with pagination | C13: 1. Login as admin successfully. 2. Navigate to "/admin/users" page. 3. Click "Next" button to go to page 2. 4. Click "Previous" button to go back to page 1. 5. Change items per page to 50. | D13: 1. Page 2 loads with different users. 2. Previous button works correctly. 3. Items per page changes to 50. 4. Pagination controls update correctly. 5. Total page count adjusts properly. | E13: 1. Admin is logged in. 2. System has more than 20 users. | F13: Passed | G13: 45914 | H13: TrungNVT | I13: Passed | J13: 45954 | K13: HuyNLQ | L13: Passed | M13: 45974 | N13: TrungNVT
A14: VIEW-USERS-003 | B14: Search users by name | C14: 1. Login as admin successfully. 2. Navigate to "/admin/users" page. 3. Enter "John" in search box. 4. Press Enter key. 5. Check search results. | D14: 1. Search results show only users with "John" in name. 2. Search is case-insensitive. 3. Results include first name and last name matches. 4. Pagination resets to page 1. 5. Search term is preserved in search box. | E14: 1. Admin is logged in. 2. System has users with name "John". | F14: Passed | G14: 45914 | H14: TrungNVT | I14: Passed | J14: 45954 | K14: HuyNLQ | L14: Passed | M14: 45974 | N14: TrungNVT
A15: VIEW-USERS-004 | B15: Filter users by status - Active | C15: 1. Login as admin successfully. 2. Navigate to "/admin/users" page. 3. Select "Active" from status filter dropdown. 4. Check filtered results. | D15: 1. Only active users are displayed. 2. Locked and deleted users are hidden. 3. User count updates correctly. 4. Pagination adjusts to filtered results. 5. Filter selection is preserved. | E15: 1. Admin is logged in. 2. System has active users. | F15: Passed | G15: 45914 | H15: TrungNVT | I15: Passed | J15: 45954 | K15: HuyNLQ | L15: Passed | M15: 45974 | N15: TrungNVT
A16: VIEW-USERS-005 | B16: Filter users by status - Locked | C16: 1. Login as admin successfully. 2. Navigate to "/admin/users" page. 3. Select "Locked" from status filter dropdown. 4. Check filtered results. | D16: 1. Only locked users are displayed. 2. Active and deleted users are hidden. 3. Lock status is clearly indicated. 4. Lock reason and expiry date are shown. 5. Filter works correctly. | E16: 1. Admin is logged in. 2. System has locked users. | F16: Passed | G16: 45914 | H16: TrungNVT | I16: Passed | J16: 45954 | K16: HuyNLQ | L16: Passed | M16: 45974 | N16: TrungNVT
A17: VIEW-USERS-006 | B17: View user list with no results | C17: 1. Login as admin successfully. 2. Navigate to "/admin/users" page. 3. Enter "NonExistentUser" in search box. 4. Press Enter key. 5. Check empty state. | D17: 1. "No users found" message is displayed. 2. Empty state is user-friendly. 3. Search box retains search term. 4. Pagination controls are hidden. 5. Clear search option is available. | E17: 1. Admin is logged in. | F17: Passed | G17: 45914 | H17: TrungNVT | I17: Passed | J17: 45954 | K17: HuyNLQ | L17: Passed | M17: 45974 | N17: TrungNVT
A18: VIEW-USERS-007 | B18: View user list with network error | C18: 1. Login as admin successfully. 2. Navigate to "/admin/users" page. 3. Disconnect network connection. 4. Try to refresh page or navigate. 5. Check error handling. | D18: 1. Error message "Network error" is displayed. 2. User list shows empty state. 3. Error message is user-friendly. 4. Retry option is available. 5. System handles error gracefully. | E18: 1. Admin is logged in. 2. Network can be disconnected. | F18: Passed | G18: 45914 | H18: TrungNVT | I18: Passed | J18: 45954 | K18: HuyNLQ | L18: Passed | M18: 45974 | N18: TrungNVT
A19: VIEW-USERS-08 | B19: View user list with backend unavailable | C19: 1. Login as admin successfully. 2. Navigate to "/admin/users" page. 3. Stop backend server. 4. Try to refresh page. 5. Check error handling. | D19: 1. Error message "Server unavailable" is displayed. 2. User list shows empty state. 3. Error message is clear and helpful. 4. Retry option is available. 5. System handles server error gracefully. | E19: 1. Admin is logged in. 2. Backend server can be stopped. | F19: Failed | G19: 45914 | H19: TrungNVT | I19: Passed | J19: 45954 | K19: HuyNLQ | L19: Passed | M19: 45974 | N19: TrungNVT | O19: Round 1: Wrong message displayed: "Failed to fetch users"
A20: VIEW-USERS-09 | B20: View user list with expired session | C20: 1. Login as admin successfully. 2. Wait for session to expire. 3. Navigate to "/admin/users" page. 4. Try to view user list. 5. Check system behavior. | D20: 1. User is redirected to login page. 2. Session expired message is displayed. 3. User list is not accessible. 4. User must login again. 5. Security is properly enforced. | E20: 1. Admin is logged in. 2. Session can expire. | F20: Passed | G20: 45914 | H20: TrungNVT | I20: Passed | J20: 45954 | K20: HuyNLQ | L20: Passed | M20: 45974 | N20: TrungNVT
A21: VIEW-USERS-010 | B21: View user list with non-admin user | C21: 1. Login with driver or parent account. 2. Try to navigate to "/admin/users" page. 3. Check system behavior. | D21: 1. Access is denied. 2. User is redirected to unauthorized page. 3. Error message "Access denied" is displayed. 4. Only admin can access user list. 5. Security is properly enforced. | E21: 1. Driver or Parent account exists. | F21: Passed | G21: 45914 | H21: TrungNVT | I21: Passed | J21: 45954 | K21: HuyNLQ | L21: Passed | M21: 45974 | N21: TrungNVT
A22: VIEW-USERS-0011 | B22: Sort users by name ascending | C22: 1. Login as admin successfully. 2. Navigate to "/admin/users" page. 3. Click "Name" sort. 4. Check sort order. | D22: 1. Users are sorted by first name A-Z. 2. Sort indicator shows ascending arrow. 3. All users on current page are sorted. 4. Sort persists across page changes. 5. Sort functionality works correctly. | E22: 1. Admin is logged in. 2. System has users with different first names. | F22: Passed | G22: 45914 | H22: TrungNVT | I22: Passed | J22: 45954 | K22: HuyNLQ | L22: Passed | M22: 45974 | N22: TrungNVT
A23: VIEW-USERS-012 | B23: Sort users by name descending | C23: 1. Login as admin successfully. 2. Navigate to "/admin/users" page. 3. Click "Name" sort. 4. Check sort order. | D23: 1. Users are sorted by first name Z-A. 2. Sort indicator shows descending arrow. 3. Sort order is reversed correctly. 4. All users are properly sorted. 5. Sort functionality works as expected. | E23: 1. Admin is logged in. 2. System has users with different first names. | F23: Passed | G23: 45914 | H23: TrungNVT | I23: Passed | J23: 45954 | K23: HuyNLQ | L23: Passed | M23: 45974 | N23: TrungNVT
A24: WEB-VIEW-USERS-015 | B24: Sort users by creation date ascending | C24: 1. Login as admin successfully. 2. Navigate to "/admin/users" page. 3. Click "Created At" sort. 4. Check sort order. | D24: 1. Users are sorted by creation date (oldest first). 2. Sort indicator shows ascending arrow. 3. All users on current page are sorted. 4. Sort persists across page changes. 5. Sort functionality works correctly. | E24: 1. Admin is logged in. 2. System has users created on different dates. | F24: Passed | G24: 45914 | H24: TrungNVT | I24: Passed | J24: 45954 | K24: HuyNLQ | L24: Passed | M24: 45974 | N24: TrungNVT
A25: WEB-VIEW-USERS-016 | B25: Sort users by creation date descending | C25: 1. Login as admin successfully. 2. Navigate to "/admin/users" page. 3. Click "Created At" sort. 4. Check sort order. | D25: 1. Users are sorted by creation date (newest first). 2. Sort indicator shows descending arrow. 3. Sort order is reversed correctly. 4. All users are properly sorted. 5. Sort functionality works as expected. | E25: 1. Admin is logged in. 2. System has users created on different dates. | F25: Passed | G25: 45914 | H25: TrungNVT | I25: Passed | J25: 45954 | K25: HuyNLQ | L25: Passed | M25: 45974 | N25: TrungNVT
A26: Create parent account
A27: CR-PR-001 | B27: Create parent with valid data. | C27: 1. Login as admin successfully. 2. Navigate to "/create-account" page. 3. Select "Parent Account" tab. 4. Fill all required fields. 5. Click "Create New Account" button. | D27: 1. Parent account is created successfully. 2. Success message is displayed. 3. Form is reset for next entry. | E27: Email is not already in use. | F27: Passed | G27: 45915 | H27: TrungNVT | I27: Passed | J27: 45954 | K27: HuyNLQ | L27: Passed | M27: 45974 | N27: TrungNVT
A28: CR-PR-002 | B28: Create parent with duplicate email | C28: 1. Login as admin successfully. 2. Navigate to "/create-account" page. 3. Select ""Parent Account"" tab. 4. Fill form with email that already exists in system. 5. Fill other required fields with valid data. 6. Click "Create New Account" button. | D28: 1. Error message "Email already exists" is displayed. 2. Account creation fails. 3. Form data is preserved for correction. 4. User can modify email and retry. | E28: Email already exists in system. | F28: N/A | G28: 45915 | H28: TrungNVT | I28: N/A | J28: 45954 | K28: HuyNLQ | L28: N/A | M28: 45974 | N28: TrungNVT
A29: CR-PR-002 | B29: Create parent with empty required fields | C29: 1. Login as admin successfully. 2. Navigate to "/create-account" page. 3. Select "Parent Account" tab. 4. Leave required fields empty. 5. Click "Create New Account" button. | D29: 1. Validation errors are displayed for empty fields: - "Email is required" - "First name is required" - "Last name is required" - "Phone number is required" - "Address is required" - "Gender is required" - "Date of birth is required" 2. Form submission is blocked. 3. User must fill required fields. | E29: 1. Admin is logged in | F29: Passed | G29: 45915 | H29: TrungNVT | I29: Passed | J29: 45954 | K29: HuyNLQ | L29: Passed | M29: 45974 | N29: TrungNVT
A30: CR-PR-003 | B30: Create parent with invalid email format | C30: 1. Login as admin successfully. 2. Navigate to "/create-account" page. 3. Select "Parent Account" tab. 4. Enter invalid email format (e.g., "invalid-email"). 5. Fill other required fields with valid data. 6. Click "Create New Account" button. | D30: 1. Validation error "Invalid email format" is displayed. 2. Account creation fails. 3. Form submission is blocked. 4. User must correct email format. | E30: 1. Admin is logged in. | F30: Passed | G30: 45915 | H30: TrungNVT | I30: Passed | J30: 45954 | K30: HuyNLQ | L30: Passed | M30: 45974 | N30: TrungNVT
A31: CR-PR-004 | B31: Create parent with invalid phone number | C31: 1. Login as admin successfully. 2. Navigate to "/create-account" page. 3. Select "Parent Account" tab. 4. Enter invalid phone number (e.g., "abc123"). 5. Fill other required fields with valid data. 6. Click "Create New Account" button. | D31: 1. Validation error "Invalid phone number format" is displayed. 2. Account creation fails. 3. Form submission is blocked. 4. User must correct phone number format. | E31: 1. Admin is logged in. | F31: Passed | G31: 45915 | H31: TrungNVT | I31: Passed | J31: 45954 | K31: HuyNLQ | L31: Passed | M31: 45974 | N31: TrungNVT
A32: CR-PR-005 | B32: Create parent with future date of birth | C32: 1. Login as admin successfully. 2. Navigate to "/create-account" page. 3. Select "Parent Account" tab. 4. Enter future date for date of birth. 5. Fill other required fields with valid data. 6. Click "Create New Account" button. | D32: 1. Validation error is displayed for invalid date. 2. Account creation fails. 3. Form submission is blocked. 4. User must enter valid past date. | E32: 1. Admin is logged in. | F32: Failed | G32: 45915 | H32: TrungNVT | I32: Passed | J32: 45954 | K32: HuyNLQ | L32: Passed | M32: 45974 | N32: TrungNVT | O32: Round 1: Select the date of birth in the future
A33: CR-PR-006 | B33: Create parent with very old date of birth | C33: 1. Login as admin successfully. 2. Navigate to "/create-account" page. 3. Select "Parent Account" tab. 4. Enter very old date (e.g., 1900-01-01). 5. Fill other required fields with valid data. 6. Click "Create New Account" button. | D33: 1. Validation error for invalid age is displayed. 2. Account creation fails. 3. Form submission is blocked. 4. User must enter reasonable birth date. | E33: 1. Admin is logged in. | F33: Failed | G33: 45915 | H33: TrungNVT | I33: Passed | J33: 45954 | K33: HuyNLQ | L33: Passed | M33: 45974 | N33: TrungNVT | O33: Round 1: Select very old date of birth
A34: CR-PR-007 | B34: Create parent with special characters in name | C34: 1. Login as admin successfully. 2. Navigate to "/create-account" page. 3. Select "Parent Account" tab. 4. Enter names with special characters (e.g., "JosÃ© MarÃ­a"). 5. Fill other required fields with valid data. 6. Click "Create New Account" button. | D34: 1. Parent account is created successfully. 2. Special characters are handled properly. 3. Success message is displayed. 4. Data is stored correctly in database. | E34: 1. Admin is logged in. 2. Email is not already in use. | F34: Failed | G34: 45915 | H34: TrungNVT | I34: Passed | J34: 45954 | K34: HuyNLQ | L34: Passed | M34: 45974 | N34: TrungNVT | O34: Round 1: Special characters can be entered for first name and last name.
A35: CR-PR-008 | B35: Create parent with long address | C35: 1. Login as admin successfully. 2. Navigate to "/create-account" page. 3. Select "Parent Account" tab. 4. Enter very long address (500+ characters). 5. Fill other required fields with valid data. 6. Click "Create New Account" button. | D35: 1. Parent account is created successfully. 2. Long address is handled properly. 3. Success message is displayed. 4. Data is stored correctly in database. | E35: 1. Admin is logged in. 2. Email is not already in use. | F35: Failed | G35: 45915 | H35: TrungNVT | I35: Passed | J35: 45954 | K35: HuyNLQ | L35: Passed | M35: 45974 | N35: TrungNVT | O35: Round 1: No character limit for addresses
A36: CR-PR-009 | B36: Create parent with backend unavailable | C36: 1. Login as admin successfully. 2. Navigate to "/create-account" page. 3. Select "Parent Account" tab. 4. Fill form with valid data. 5. Stop backend server. 6. Click "Create New Account" button. | D36: 1. Error message "Server unavailable" is displayed. 2. Account creation fails. 3. Form data is preserved. 4. User can retry when backend is restored. | E36: 1. Admin is logged in. 2. Backend server can be stopped. | F36: Failed | G36: 45915 | H36: TrungNVT | I36: Passed | J36: 45954 | K36: HuyNLQ | L36: Passed | M36: 45974 | N36: TrungNVT | O36: Round 1: Wrong message displayed: "Parent creation failed. Data was not saved to the database."
A37: CR-PR-010 | B37: Create parent with expired session | C37: 1. Login as admin successfully. 2. Wait for session to expire. 3. Navigate to "/create-account" page. 4. Select "Parent Account" tab. 5. Fill form with valid data. 6. Click "Create New Account" button. | D37: 1. User is redirected to login page. 2. Account creation fails. 3. Session expired message is displayed. 4. User must login again. | E37: 1. Admin is logged in. 2. Session can expire. | F37: Passed | G37: 45915 | H37: TrungNVT | I37: Passed | J37: 45954 | K37: HuyNLQ | L37: Passed | M37: 45974 | N37: TrungNVT
A38: CR-PR-011 | B38: Create parent with browser refresh during submission | C38: 1. Login as admin successfully. 2. Navigate to "/create-account" page. 3. Select "Parent Account" tab. 4. Fill form with valid data. 5. Click "Create New Account" button. 6. Refresh browser immediately after clicking. | D38: 1. Account creation may succeed or fail. 2. No duplicate accounts are created. 3. System handles refresh gracefully. 4. User can verify account status. | E38: 1. Admin is logged in. | F38: Passed | G38: 45915 | H38: TrungNVT | I38: Passed | J38: 45954 | K38: HuyNLQ | L38: Passed | M38: 45974 | N38: TrungNVT
A39: CR-PR-012 | B39: Create parent with multiple rapid submissions | C39: 1. Login as admin successfully. 2. Navigate to "/create-account" page. 3. Select "Parent Account" tab. 4. Fill form with valid data. 5. Click "Create New Account" button multiple times rapidly. | D39: 1. Only one account is created. 2. Duplicate submissions are prevented. 3. Success message is displayed once. 4. Button is disabled during processing. | E39: 1. Admin is logged in. | F39: Passed | G39: 45915 | H39: TrungNVT | I39: Passed | J39: 45954 | K39: HuyNLQ | L39: Passed | M39: 45974 | N39: TrungNVT
A40: CR-PR-013 | B40: Create parent with different gender options | C40: 1. Login as admin successfully. 2. Navigate to "/create-account" page. 3. Select "Parent Account" tab. 4. Test each gender option: - Male - Female - Other 5. Fill other required fields with valid data. 6. Click "Create New Account" button for each. | D40: 1. All gender options work correctly. 2. Accounts are created successfully for each gender. 3. Gender data is stored correctly in database. 4. Success messages are displayed. | E40: 1. Admin is logged in. 2. Different emails for each test. | F40: Passed | G40: 45915 | H40: TrungNVT | I40: Passed | J40: 45954 | K40: HuyNLQ | L40: N/A | M40: 45974 | N40: TrungNVT
A41: CR-PR-014 | B41: Create parent with minimum age validation | C41: 1. Login as admin successfully. 2. Navigate to "/create-account" page. 3. Select "Parent Account" tab. 4. Enter date of birth making parent exactly 18 years old. 5. Fill other required fields with valid data. 6. Click "Create New Account" button. | D41: 1. Parent account is created successfully. 2. Age validation passes for 18-year-old. 3. Success message is displayed. 4. Account is created without issues. | E41: 1. Admin is logged in. 2. Email is not already in use. | F41: Passed | G41: 45915 | H41: TrungNVT | I41: Passed | J41: 45954 | K41: HuyNLQ | L41: Passed | M41: 45974 | N41: TrungNVT
A42: CR-PR-015 | B42: Create parent with maximum age validation | C42: 1. Login as admin successfully. 2. Navigate to "/create-account" page. 3. Select "Parent Account" tab. 4. Enter date of birth making parent 100 years old. 5. Fill other required fields with valid data. 6. Click "Create New Account" button. | D42: 1. Validation error for maximum age is displayed. 2. Account creation fails. 3. Form submission is blocked. 4. User must enter reasonable age. | E42: 1. Admin is logged in. | F42: Failed | G42: 45915 | H42: TrungNVT | I42: Passed | J42: 45954 | K42: HuyNLQ | L42: Passed | M42: 45974 | N42: TrungNVT | O42: Round 1: No maximum age limit
A43: CR-PR-016 | B43: Create parent with non-admin user access | C43: 1. Login with driver or parent account. 2. Try to navigate to "/create-account" page. 3. Check system behavior. | D43: 1. Access is denied. 2. User is redirected to unauthorized page. 3. Error message "Access denied" is displayed. 4. Only admin can access create account page. | E43: 1. Driver or Parent account exists. | F43: Passed | G43: 45915 | H43: TrungNVT | I43: Passed | J43: 45954 | K43: HuyNLQ | L43: Passed | M43: 45974 | N43: TrungNVT
A44: CR-PR-017 | B44: Create parent with form field limits | C44: 1. Login as admin successfully. 2. Navigate to "/create-account" page. 3. Select "Parent Account" tab. 4. Test field character limits: - Very long names (100+ characters) - Very long email (100+ characters) 5. Fill other required fields with valid data. 6. Click "Create New Account" button. | D44: 1. Field limits are enforced properly. 2. Validation errors are displayed for excessive length. 3. Account creation fails for invalid lengths. 4. User must enter reasonable field lengths. | E44: 1. Admin is logged in. | F44: Failed | G44: 45915 | H44: TrungNVT | I44: Passed | J44: 45954 | K44: HuyNLQ | L44: Passed | M44: 45974 | N44: TrungNVT | O44: Round 1: No character length limit for input fields
A45: CR-PR-01̣8 | B45: Import parents from valid Excel file | C45: 1. Login as admin successfully. 2. Navigate to "/create-account" page. 3. Select "Parent Account" tab. 4. Click "Upload" button. 5. Select valid Excel file with parent data. 6. Click "Import" button. | D45: 1. Excel file is processed successfully. 2. Import results are displayed showing: - Total processed count - Successfully imported parents - Failed imports with reasons 3. Successfully imported parents can login. 4. Failed records show specific error messages. | E45: 1. Admin is logged in. 2. Valid Excel file with correct format exists. | F45: Passed | G45: 45915 | H45: TrungNVT | I45: Passed | J45: 45954 | K45: HuyNLQ | L45: Passed | M45: 45974 | N45: TrungNVT
A46: CR-PR-019 | B46: Import parents from invalid file format | C46: 1. Login as admin successfully. 2. Navigate to "/create-account" page. 3. Select "Parent Account" tab. 4. Click "Upload" button. 5. Select invalid file format (e.g., .txt, .pdf, .docx). 6. Click "Import" button. | D46: 1. Error message "Invalid file format. Only .xlsx files are supported" is displayed. 2. Import process is blocked. 3. User must select correct file format. 4. No data is processed. | E46: 1. Admin is logged in. 2. Invalid file format exists. | F46: Passed | G46: 45915 | H46: TrungNVT | I46: Passed | J46: 45954 | K46: HuyNLQ | L46: Passed | M46: 45974 | N46: TrungNVT
A47: CR-PR-020 | B47: Import parents from empty Excel file | C47: 1. Login as admin successfully. 2. Navigate to "/create-account" page. 3. Select "Parent Account" tab. 4. Click "Upload" button. 5. Select empty Excel file. 6. Click "Import" button. | D47: 1. Error message "No data to import" is displayed. 2. Import process fails gracefully. 3. User is informed about empty file. 4. No accounts are created. | E47: 1. Admin is logged in. 2. Empty Excel file exists. | F47: Passed | G47: 45915 | H47: TrungNVT | I47: Passed | J47: 45954 | K47: HuyNLQ | L47: Passed | M47: 45974 | N47: TrungNVT
A48: CR-PR-021 | B48: Import parents with duplicate emails | C48: 1. Login as admin successfully. 2. Navigate to "/create-account" page. 3. Select "Parent Account" tab. 4. Click "Upload" button. 5. Select Excel file with duplicate email addresses. 6. Click "Import" button. | D48: 1. Import process completes with mixed results. 2. First occurrence of email is imported successfully. 3. Duplicate emails are marked as failed with "Email already exists" error. 4. Import results show both success and failure counts. | E48: 1. Admin is logged in. 2. Excel file with duplicate emails exists. | F48: Passed | G48: 45915 | H48: TrungNVT | I48: Passed | J48: 45954 | K48: HuyNLQ | L48: Passed | M48: 45974 | N48: TrungNVT
A49: CR-PR-022 | B49: Import parents with missing required fields | C49: 1. Login as admin successfully. 2. Navigate to "/create-account" page. 3. Select "Parent Account" tab. 4. Click "Upload" button. 5. Select Excel file with missing required fields. 6. Click "Import" button. | D49: 1. Import process completes with validation errors. 2. Records with missing fields are marked as failed. 3. Specific error messages are shown for each missing field. 4. Valid records are imported successfully. 5. Import results show detailed failure reasons. | E49: 1. Admin is logged in. 2. Excel file with missing fields exists. | F49: Passed | G49: 45915 | H49: TrungNVT | I49: Passed | J49: 45954 | K49: HuyNLQ | L49: Passed | M49: 45974 | N49: TrungNVT
A50: CR-PR-023 | B50: Import parents with invalid data formats | C50: 1. Login as admin successfully. 2. Navigate to "/create-account" page. 3. Select "Parent Account" tab. 4. Click "Upload" button. 5. Select Excel file with invalid data formats (invalid email, phone, date). 6. Click "Import" button. | D50: 1. Import process completes with validation errors. 2. Records with invalid formats are marked as failed. 3. Specific validation error messages are displayed. 4. Valid records are imported successfully. 5. User can see which records failed and why. | E50: 1. Admin is logged in. 2. Excel file with invalid formats exists. | F50: Passed | G50: 45915 | H50: TrungNVT | I50: Passed | J50: 45954 | K50: HuyNLQ | L50: Passed | M50: 45974 | N50: TrungNVT
A51: CR-PR-024 | B51: Import parents with large Excel file | C51: 1. Login as admin successfully. 2. Navigate to "/create-account" page. 3. Select "Parent Account" tab. 4. Click "Upload" button. 5. Select Excel file with 1000+ parent records. 6. Click "Import" button. | D51: 1. Import process handles large file successfully. 2. Progress indicator is displayed during import. 3. All valid records are imported. 4. Import results show accurate counts. 5. System performance remains stable. | E51: 1. Admin is logged in. 2. Large Excel file (1000+ records) exists. | F51: Passed | I51: Passed | J51: 45954 | K51: HuyNLQ | L51: Passed | M51: 45974 | N51: TrungNVT
A52: CR-PR-025 | B52: Import parents with network interruption | C52: 1. Login as admin successfully. 2. Navigate to "/create-account" page. 3. Select "Parent Account" tab. 4. Click "Upload" button. 5. Select Excel file and start import. 6. Disconnect network during import process. | D52: 1. Import process fails with network error. 2. Error message "Network error" is displayed. 3. No partial data is imported. 4. User can retry when network is restored. 5. File selection is preserved. | E52: 1. Admin is logged in. 2. Network can be disconnected. | F52: Passed | I52: Passed | J52: 45954 | K52: HuyNLQ | L52: Passed | M52: 45974 | N52: TrungNVT
A53: CR-PR-026 | B53: Import parents with backend unavailable | C53: 1. Login as admin successfully. 2. Navigate to "/create-account" page. 3. Select "Parent Account" tab. 4. Click "Upload" button. 5. Select Excel file and start import. 6. Stop backend server during import. | D53: 1. Import process fails with server error. 2. Error message "Server unavailable" is displayed. 3. No partial data is imported. 4. User can retry when backend is restored. 5. File selection is preserved. | E53: 1. Admin is logged in. 2. Backend server can be stopped. | F53: Passed | G53: 45915 | H53: TrungNVT | I53: Passed | J53: 45954 | K53: HuyNLQ | L53: Passed | M53: 45974 | N53: TrungNVT
A54: CR-PR-027 | B54: Download parent import template | C54: 1. Login as admin successfully. 2. Navigate to "/create-account" page. 3. Select "Parent Account" tab. 4. Click "Download Template" button. 5. Check downloaded file. | D54: 1. Excel template file is downloaded successfully. 2. Template contains correct column headers: - Email - First Name - Last Name - Phone Number - Gender - Date of Birth - Address 3. Template includes sample data and instructions. 4. File can be opened and edited. | E54: 1. Admin is logged in. | F54: Failed | G54: 45915 | H54: TrungNVT | I54: Passed | J54: 45954 | K54: HuyNLQ | L54: Passed | M54: 45974 | N54: TrungNVT
A55: CR-PR-028 | B55: Import parents with template format | C55: 1. Login as admin successfully. 2. Navigate to "/create-account" page. 3. Select "Parent Account" tab. 4. Download template and fill with valid data. 5. Upload filled template file. 6. Click "Import" button. | D55: 1. Import process completes successfully. 2. All records from template are imported. 3. Data matches template format exactly. 4. Success message is displayed. 5. Imported parents can login. | E55: 1. Admin is logged in. 2. Template is downloaded and filled correctly. | F55: Failed | G55: 45915 | H55: TrungNVT | I55: Passed | J55: 45954 | K55: HuyNLQ | L55: Passed | M55: 45974 | N55: TrungNVT
A56: CR-PR-029 | B56: Import parents with wrong column order | C56: 1. Login as admin successfully. 2. Navigate to "/create-account" page. 3. Select "Parent Account" tab. 4. Click "Upload" button. 5. Select Excel file with columns in wrong order. 6. Click "Import" button. | D56: 1. Import process fails or produces incorrect results. 2. Error message about column format is displayed. 3. Data mapping is incorrect. 4. User must use correct template format. 5. No accounts are created with wrong data. | E56: 1. Admin is logged in. 2. Excel file with wrong column order exists. | F56: Passed | G56: 45915 | H56: TrungNVT | I56: Passed | J56: 45954 | K56: HuyNLQ | L56: Passed | M56: 45974 | N56: TrungNVT
A57: CR-PR-030 | B57: Import parents with non-admin user | C57: 1. Login with driver or parent account. 2. Try to navigate to "/create-account" page. 3. Check if import functionality is accessible. | D57: 1. Access is denied. 2. User is redirected to unauthorized page. 3. Error message "Access denied" is displayed. 4. Only admin can access import functionality. 5. Import button is not visible. | E57: 1. Driver or Parent account exists. | F57: Passed | G57: 45915 | H57: TrungNVT | I57: Passed | J57: 45954 | K57: HuyNLQ | L57: Passed | M57: 45974 | N57: TrungNVT
A58: CR-PR-031 | B58: Import parents with expired session | C58: 1. Login as admin successfully. 2. Wait for session to expire. 3. Navigate to "/create-account" page. 4. Select "Parent Account" tab. 5. Click "Upload" button. 6. Select Excel file and try to import. | D58: 1. User is redirected to login page. 2. Import process fails. 3. Session expired message is displayed. 4. User must login again to continue. 5. File selection is lost. | E58: 1. Admin is logged in. 2. Session can expire. | F58: Passed | G58: 45915 | H58: TrungNVT | I58: Passed | J58: 45954 | K58: HuyNLQ | L58: Passed | M58: 45974 | N58: TrungNVT
A59: CR-PR-032 | B59: Import parents with mixed valid/invalid data | C59: 1. Login as admin successfully. 2. Navigate to "/create-account" page. 3. Select "Parent Account" tab. 4. Click "Upload" button. 5. Select Excel file with mixed valid and invalid data. 6. Click "Import" button. | D59: 1. Import process completes with mixed results. 2. Valid records are imported successfully. 3. Invalid records are marked as failed with specific reasons. 4. Import results show detailed breakdown. 5. User can see which records succeeded and failed. | E59: 1. Admin is logged in. 2. Excel file with mixed data exists. | F59: Failed | G59: 45915 | H59: TrungNVT | I59: Passed | J59: 45954 | K59: HuyNLQ | L59: Passed | M59: 45974 | N59: TrungNVT
A60: Create driver account
A61: DRIVER-033 | B61: Create driver account with valid basic data | C61: 1. Navigate to Create Account page 2. Select "Driver" account type 3. Fill email: "driver@example.com" 4. Fill firstName: "John" 5. Fill lastName: "Doe" 6. Fill phoneNumber: "0123456789" 7. Select gender: "Male" 8. Set dateOfBirth: "1985-01-01" 9. Fill address: "123 Main St" 10. Click "Create New Account" | D61: 1. Success message displayed 2. Temporary password shown in alert 3. Form reset after creation 4. Driver account created in database 5. No welcome email sent (unlike parent) | E61: Admin logged in | F61: Passed | G61: 45915 | H61: TrungNVT | I61: Passed | J61: 45954 | K61: HuyNLQ | L61: Passed | M61: 45974 | N61: TrungNVT
A62: DRIVER-034 | B62: Create driver account with duplicate email | C62: 1. Navigate to Create Account page 2. Select "Driver" account type 3. Fill email: "existing@example.com" (already exists) 4. Fill other required fields 5. Click "Create New Account" | D62: 1. Error message "Email already exists in the system" 2. Form submission blocked 3. Account not created | E62: Admin logged in, email already exists | F62: Passed | G62: 45915 | H62: TrungNVT | I62: Passed | J62: 45954 | K62: HuyNLQ | L62: Passed | M62: 45974 | N62: TrungNVT
A63: DRIVER-035 | B63: Create driver account with duplicate phone number | C63: 1. Navigate to Create Account page 2. Select "Driver" account type 3. Fill phoneNumber: "0987654321" (already exists) 4. Fill other required fields 5. Click "Create New Account" | D63: 1. Error message "Phone number already exists in the system" 2. Form submission blocked 3. Account not created | E63: Admin logged in, phone already exists | F63: Passed | G63: 45915 | H63: TrungNVT | I63: Passed | J63: 45954 | K63: HuyNLQ | L63: Passed | M63: 45974 | N63: TrungNVT
A64: DRIVER-036 | B64: Create driver account with invalid email format | C64: 1. Navigate to Create Account page 2. Select "Driver" account type 3. Fill email: "invalid-email" 4. Fill other required fields 5. Click "Create New Account" | D64: 1. Validation error "Invalid email format" 2. Form submission blocked 3. Account not created | E64: Admin logged in | F64: Passed | G64: 45915 | H64: TrungNVT | I64: Passed | J64: 45954 | K64: HuyNLQ | L64: Passed | M64: 45974 | N64: TrungNVT
A65: DRIVER-037 | B65: Create driver account with missing required fields | C65: 1. Navigate to Create Account page 2. Select "Driver" account type 3. Leave firstName empty 4. Fill other required fields 5. Click "Create New Account" | D65: 1. Validation error "First Name is required" 2. Form submission blocked 3. Account not created | E65: Admin logged in | F65: Passed | G65: 45915 | H65: TrungNVT | I65: Passed | J65: 45954 | K65: HuyNLQ | L65: Passed | M65: 45974 | N65: TrungNVT
A66: DRIVER-038 | B66: Create driver account with future date of birth | C66: 1. Navigate to Create Account page 2. Select "Driver" account type 3. Set dateOfBirth: "2030-01-01" 4. Fill other required fields 5. Click "Create New Account" | D66: 1. Validation error "Date of birth cannot be in the future" 2. Form submission blocked 3. Account not created | E66: Admin logged in | F66: Passed | G66: 45915 | H66: TrungNVT | I66: Passed | J66: 45954 | K66: HuyNLQ | L66: Passed | M66: 45974 | N66: TrungNVT
A67: DRIVER-039 | B67: Create driver account with empty phone number | C67: 1. Navigate to Create Account page 2. Select "Driver" account type 3. Leave phoneNumber empty 4. Fill other required fields 5. Click "Create New Account" | D67: 1. Validation error "Phone Number is required" 2. Form submission blocked 3. Account not created | E67: Admin logged in | F67: Passed | G67: 45915 | H67: TrungNVT | I67: Passed | J67: 45954 | K67: HuyNLQ | L67: Passed | M67: 45974 | N67: TrungNVT
A68: DRIVER-040 | B68: Create driver account with empty address | C68: 1. Navigate to Create Account page 2. Select "Driver" account type 3. Leave address empty 4. Fill other required fields 5. Click "Create New Account" | D68: 1. Validation error "Address is required" 2. Form submission blocked 3. Account not created | E68: Admin logged in | F68: Passed | G68: 45915 | H68: TrungNVT | I68: Passed | J68: 45954 | K68: HuyNLQ | L68: Passed | M68: 45974 | N68: TrungNVT
A69: DRIVER-041 | B69: Create driver account with empty gender | C69: 1. Navigate to Create Account page 2. Select "Driver" account type 3. Leave gender unselected 4. Fill other required fields 5. Click "Create New Account" | D69: 1. Validation error "Gender is required" 2. Form submission blocked 3. Account not created | E69: Admin logged in | F69: Passed | G69: 45915 | H69: TrungNVT | I69: Passed | J69: 45954 | K69: HuyNLQ | L69: Passed | M69: 45974 | N69: TrungNVT
A70: DRIVER-042 | B70: Create driver account with empty date of birth | C70: 1. Navigate to Create Account page 2. Select "Driver" account type 3. Fill all required fields 4. Upload driver photo (image file) 5. Click "Create New Account" | D70: 1. Validation error "Date of Birth is required" 2. Form submission blocked 3. Account not created | E70: Admin logged in | F70: Passed | G70: 45915 | H70: TrungNVT | I70: Passed | J70: 45954 | K70: HuyNLQ | L70: Passed | M70: 45974 | N70: TrungNVT
A71: DRIVER-043 | B71: Create driver account with driver photo upload | C71: 1. Navigate to Create Account page 2. Select "Driver" account type 3. Fill all required fields 4. Upload driver photo (image file) 5. Click "Create New Account" | D71: 1. Driver account created successfully 2. Driver photo uploaded 3. Photo file saved to server 4. Success message displayed | E71: Admin logged in, valid image file | F71: Passed | G71: 45915 | H71: TrungNVT | I71: Passed | J71: 45954 | K71: HuyNLQ | L71: Passed | M71: 45974 | N71: TrungNVT
A72: DRIVER-044 | B72: Create driver account with health certificate upload | C72: 1. Navigate to Create Account page 2. Select "Driver" account type 3. Fill all required fields 4. Upload health certificate (image file) 5. Click "Create New Account" | D72: 1. Driver account created successfully 2. Health certificate uploaded 3. Certificate file saved to server 4. Success message displayed | E72: Admin logged in, valid image file | F72: Passed | G72: 45915 | H72: TrungNVT | I72: Passed | J72: 45954 | K72: HuyNLQ | L72: Passed | M72: 45974 | N72: TrungNVT
... A85: DRIVER-057 | B85: Create driver account with special characters in name | C85: 1. Navigate to Create Account page 2. Select "Driver" account type 3. Fill firstName: "José" 4. Fill lastName: "García-López" 5. Fill other required fields 6. Click "Create New Account" | D85: 1. Driver account created successfully 2. Special characters handled properly 3. Name displayed correctly in system 4. Success message displayed | E85: Admin logged in | F85: Passed | G85: 45915 | H85: TrungNVT | I85: Passed | J85: 45954 | K85: HuyNLQ | L85: Passed | M85: 45974 | N85: TrungNVT
A86: Ban/unban users
A87: BAN-USER-001 | B87: Ban single user with reason and expiry date | C87: 1. Login as admin successfully. 2. Navigate to "/admin/users" page. 3. Find an active user in the list. 4. Click "Lock" button for that user. 5. Fill in lock reason: "Policy violation". 6. Set lock expiry date to tomorrow. 7. Click "Confirm Lock" button. | D87: 1. Lock modal opens successfully. 2. Form validation works correctly. 3. User is locked successfully. 4. Success message "User locked successfully" is displayed. 5. User status changes to "Locked" in the list. 6. Lock reason and expiry date are shown. | E87: 1. Admin is logged in. 2. System has active users. | F87: Passed | G87: 45916 | H87: TrungNVT | I87: Passed | J87: 45954 | K87: HuyNLQ | L87: Passed | M87: 45974 | N87: TrungNVT
A88: BAN-USER-002 | B88: Ban single user without expiry date | C88: 1. Login as admin successfully. 2. Navigate to "/admin/users" page. 3. Find an active user in the list. 4. Click "Lock" button for that user. 5. Fill in lock reason: "Suspicious activity". 6. Leave expiry date empty (permanent lock). 7. Click "Confirm Lock" button. | D88: 1. Lock modal opens successfully. 2. User is locked permanently. 3. Success message "User locked successfully" is displayed. 4. User status changes to "Locked" in the list. 5. No expiry date is shown (permanent lock). 6. Lock reason is displayed. | E88: 1. Admin is logged in. 2. System has active users. | F88: Failed | G88: 45916 | H88: TrungNVT | I88: Passed | J88: 45954 | K88: HuyNLQ | L88: Passed | M88: 45974 | N88: TrungNVT | O88: Round 1: the account was only locked for 1 day
A89: BAN-USER-003 | B89: Ban single user without reason | C89: 1. Login as admin successfully. 2. Navigate to "/admin/users" page. 3. Find an active user in the list. 4. Click "Lock" button for that user. 5. Leave reason field empty. 6. Set expiry date to next week. 7. Click "Confirm Lock" button. | D89: 1. Lock modal opens successfully. 2. Default reason "Locked by admin" is used. 3. User is locked successfully. 4. Success message "User locked successfully" is displayed. 5. User status changes to "Locked" in the list. 6. Default reason is shown. | E89: 1. Admin is logged in. 2. System has active users. | F89: Passed | G89: 45916 | H89: TrungNVT | I89: Passed | J89: 45954 | K89: HuyNLQ | L89: Passed | M89: 45974 | N89: TrungNVT
A90: BAN-USER-004 | B90: Ban multiple users at once | C90: 1. Login as admin successfully. 2. Navigate to "/admin/users" page. 3. Select multiple active users using checkboxes. 4. Click "Lock Selected" button. 5. Fill in lock reason: "Bulk violation". 6. Set expiry date to next month. 7. Click "Confirm Lock" button. | D90: 1. Multiple users are selected successfully. 2. Bulk lock modal opens. 3. All selected users are locked successfully. 4. Success message shows count of locked users. 5. All selected users status changes to "Locked". 6. Lock reason and expiry are applied to all users. | E90: 1. Admin is logged in. 2. System has multiple active users. | F90: Passed | G90: 45916 | H90: TrungNVT | I90: Passed | J90: 45954 | K90: HuyNLQ | L90: Passed | M90: 45974 | N90: TrungNVT
A91: BAN-USER-005 | B91: Unban single locked user | C91: 1. Login as admin successfully. 2. Navigate to "/admin/users" page. 3. Filter users by "Locked" status. 4. Find a locked user in the list. 5. Click "Unlock" button for that user. 6. Confirm unlock action. | D91: 1. Locked users are displayed in filter. 2. Unlock confirmation dialog appears. 3. User is unlocked successfully. 4. Success message "User unlocked successfully" is displayed. 5. User status changes to "Active" in the list. 6. Lock information is removed. | E91: 1. Admin is logged in. 2. System has locked users. | F91: Passed | G91: 45916 | H91: TrungNVT | I91: Passed | J91: 45954 | K91: HuyNLQ | L91: Passed | M91: 45974 | N91: TrungNVT
A92: BAN-USER-006 | B92: Unban multiple locked users | C92: 1. Login as admin successfully. 2. Navigate to "/admin/users" page. 3. Filter users by "Locked" status. 4. Select multiple locked users using checkboxes. 5. Click "Unlock Selected" button. 6. Confirm bulk unlock action. | D92: 1. Locked users are displayed in filter. 2. Multiple users are selected successfully. 3. Bulk unlock confirmation dialog appears. 4. All selected users are unlocked successfully. 5. Success message shows count of unlocked users. 6. All selected users status changes to "Active". | E92: 1. Admin is logged in. 2. System has multiple locked users. | F92: Passed | G92: 45916 | H92: TrungNVT | I92: Passed | J92: 45954 | K92: HuyNLQ | L92: Passed | M92: 45974 | N92: TrungNVT
A93: BAN-USER-007 | B93: Ban user with past expiry date | C93: 1. Login as admin successfully. 2. Navigate to "/admin/users" page. 3. Find an active user in the list. 4. Click "Lock" button for that user. 5. Set expiry date to yesterday (past date). 6. Click "Confirm Lock" button. | D93: 1. Lock modal opens successfully. 2. Validation error "Expiry date cannot be in the past" is displayed. 3. Lock action is blocked. 4. User remains active. 5. Form validation prevents invalid date. 6. User can correct the date. | E93: 1. Admin is logged in. 2. System has active users. | F93: Passed | G93: 45916 | H93: TrungNVT | I93: Passed | J93: 45954 | K93: HuyNLQ | L93: Passed | M93: 45974 | N93: TrungNVT
A94: BAN-USER-008 | B94: Ban user with very long reason | C94: 1. Login as admin successfully. 2. Navigate to "/admin/users" page. 3. Find an active user in the list. 4. Click "Lock" button for that user. 5. Enter very long reason (500+ characters). 6. Set expiry date to next week. 7. Click "Confirm Lock" button. | D94: 1. Lock modal opens successfully. 2. Long reason is handled properly. 3. User is locked successfully. 4. Success message is displayed. 5. Long reason is stored and displayed correctly. 6. No truncation occurs. | E94: 1. Admin is logged in. 2. System has active users. | F94: Passed | G94: 45916 | H94: TrungNVT | I94: Passed | J94: 45954 | K94: HuyNLQ | L94: Passed | M94: 45974 | N94: TrungNVT
A95: BAN-USER-009 | B95: Ban user with special characters in reason | C95: 1. Login as admin successfully. 2. Navigate to "/admin/users" page. 3. Find an active user in the list. 4. Click "Lock" button for that user. 5. Enter reason with special characters: "Violation @#$%^&*()". 6. Set expiry date to next week. 7. Click "Confirm Lock" button. | D95: 1. Lock modal opens successfully. 2. Special characters are handled properly. 3. User is locked successfully. 4. Success message is displayed. 5. Special characters are preserved in reason. 6. No encoding issues occur. | E95: 1. Admin is logged in. 2. System has active users. | F95: Passed | G95: 45916 | H95: TrungNVT | I95: Passed | J95: 45954 | K95: HuyNLQ | L95: Passed | M95: 45974 | N95: TrungNVT
A96: BAN-USER-010 | B96: Ban user with network interruption | C96: 1. Login as admin successfully. 2. Navigate to "/admin/users" page. 3. Find an active user in the list. 4. Click "Lock" button for that user. 5. Fill in lock details. 6. Disconnect network connection. 7. Click "Confirm Lock" button. | D96: 1. Lock modal opens successfully. 2. Error message "Network error" is displayed. 3. Lock action fails. 4. User remains active. 5. Form data is preserved. 6. User can retry when network is restored. | E96: 1. Admin is logged in. 2. Network can be disconnected. | F96: Passed | G96: 45916 | H96: TrungNVT | I96: Passed | J96: 45954 | K96: HuyNLQ | L96: Passed | M96: 45974 | N96: TrungNVT
A97: BAN-USER-011 | B97: Ban user with backend unavailable | C97: 1. Login as admin successfully. 2. Navigate to "/admin/users" page. 3. Find an active user in the list. 4. Click "Lock" button for that user. 5. Fill in lock details. 6. Stop backend server. 7. Click "Confirm Lock" button. | D97: 1. Lock modal opens successfully. 2. Error message "Server unavailable" is displayed. 3. Lock action fails. 4. User remains active. 5. Form data is preserved. 6. User can retry when backend is restored. | E97: 1. Admin is logged in. 2. Backend server can be stopped. | F97: Passed | G97: 45916 | H97: TrungNVT | I97: Passed | J97: 45954 | K97: HuyNLQ | L97: Passed | M97: 45974 | N97: TrungNVT
A98: BAN-USER-012 | B98: Ban user with expired session | C98: 1. Login as admin successfully. 2. Wait for session to expire. 3. Navigate to "/admin/users" page. 4. Try to ban a user. 5. Check system behavior. | D98: 1. User is redirected to login page. 2. Session expired message is displayed. 3. Ban action cannot be performed. 4. User must login again. 5. Security is properly enforced. | E98: 1. Admin is logged in. 2. Session can expire. | F98: Passed | G98: 45916 | H98: TrungNVT | I98: Passed | J98: 45954 | K98: HuyNLQ | L98: Passed | M98: 45974 | N98: TrungNVT
A99: BAN-USER-013 | B99: Ban user with non-admin user | C99: 1. Login with driver or parent account. 2. Try to navigate to "/admin/users" page. 3. Check if ban functionality is accessible. | D99: 1. Access is denied. 2. User is redirected to unauthorized page. 3. Error message "Access denied" is displayed. 4. Only admin can access ban functionality. 5. Ban buttons are not visible. | E99: 1. Driver or Parent account exists. | F99: Passed | G99: 45916 | H99: TrungNVT | I99: Passed | J99: 45954 | K99: HuyNLQ | L99: Passed | M99: 45974 | N99: TrungNVT
A100: BAN-USER-014 | B100: Ban already locked user | C100: 1. Login as admin successfully. 2. Navigate to "/admin/users" page. 3. Find a locked user in the list. 4. Try to click "Lock" button again. 5. Check system behavior. | D100: 1. Lock button is disabled or shows different state. 2. User cannot be locked again. 3. Appropriate message is displayed. 4. No duplicate lock occurs. 5. System handles already locked user gracefully. | E100: 1. Admin is logged in. 2. System has locked users. | F100: Passed | G100: 45916 | H100: TrungNVT | I100: Passed | J100: 45954 | K100: HuyNLQ | L100: Passed | M100: 45974 | N100: TrungNVT
... A105: BAN-USER-019 | B105: Ban user with slow network | C105: 1. Login as admin successfully. 2. Navigate to "/admin/users" page. 3. Find an active user in the list. 4. Simulate slow network connection. 5. Try to ban the user. 6. Check loading behavior. | D105: 1. Lock modal opens successfully. 2. Loading indicator is displayed during ban. 3. Ban operation eventually completes. 4. Success message is displayed. 5. User experience is smooth despite slow network. | E105: 1. Admin is logged in. 2. Network speed can be controlled. | F105: Passed | G105: 45916 | H105: TrungNVT | I105: Passed | J105: 45954 | K105: HuyNLQ | L105: Passed | M105: 45974 | N105: TrungNVT
A106: Login with admin account
A107: WEB-AUTH-001 | B107: Admin login with valid credentials | C107: 1. Navigate to login page. 2. Enter admin email in email field. 3. Enter correct password in password field. 4. Click "Login" button. 5. Verify redirect to admin dashboard page. | D107: 1. Login request sent successfully. 2. Response contains success: true. 3. Access token stored in localStorage. 4. Redirect to admin dashboard. | E107: 1. Admin account exists. 2. Admin account is active | F107: Passed | G107: 45916 | H107: TrungNVT | I107: Passed | J107: 45954 | K107: HuyNLQ | L107: Passed | M107: 45974 | N107: TrungNVT
A108: WEB-AUTH-002 | B108: Admin login with invalid password | C108: 1. Navigate to login page. 2. Enter admin email in email field. 3. Enter incorrect password in password field. 4. Click "Login" button. 5. Check error handling. | D108: 1. Error message "Wrong username or password" displayed. 2. User is not authenticated. 3. Login form remains visible. | E108: Admin account exists in system | F108: Passed | G108: 45916 | H108: TrungNVT | I108: Passed | J108: 45954 | K108: HuyNLQ | L108: Passed | M108: 45974 | N108: TrungNVT
A109: WEB-LOGIN-003 | B109: Admin login with non-existent email | C109: 1. Navigate to login page. 2. Enter unregistered email in email field. 3. Enter any password in password field. 4. Click ""Login"" button. 5. Check error handling." | D109: 1. Error message "Wrong email or password" displayed. 2. User is not authenticated. 3. Login form remains visible. | E109: None | F109: Passed | G109: 45916 | H109: TrungNVT | I109: Passed | J109: 45954 | K109: HuyNLQ | L109: Passed | M109: 45974 | N109: TrungNVT
A110: WEB-LOGIN-004 | B110: Admin login with empty email field | C110: 1. Navigate to login page. 2. Leave email field blank. 3. Enter password in password field. 4. Click Login button. 5. Check validation. | D110: 1. Validation message "Email is required" displayed. 2. Login button is disabled or form submission blocked. 3. No API call is made. | E110: None | F110: Passed | G110: 45916 | H110: TrungNVT | I110: Failed | J110: 45954 | K110: HuyNLQ | L110: Passed | M110: 45974 | N110: TrungNVT
A111: WEB-LOGIN-005 | B111: Admin login with empty password field | C111: 1. Navigate to login page. 2. Enter admin email in email field. 3. Leave password field blank. 4. Click Login button. 5. Check validation. | D111: 1. Validation message "Password is required" displayed. 2. Login button is disabled or form submission blocked. 3. No API call is made. | E111: None | F111: Passed | G111: 45916 | H111: TrungNVT | I111: Failed | J111: 45954 | K111: HuyNLQ | L111: Passed | M111: 45974 | N111: TrungNVT
A112: WEB-LOGIN-006 | B112: Admin login with invalid email format | C112: 1. Navigate to login page. 2. Enter invalid email format (e.g., ""admin@""). 3. Enter password in password field. 4. Click "Login" button. 5. Check validation. | D112: 1. Client-side validation message "Invalid email format" displayed. 2. Login button is disabled or form submission blocked. 3. No API call is made. | E112: None | F112: Passed | G112: 45916 | H112: TrungNVT | I112: Passed | J112: 45954 | K112: HuyNLQ | L112: Passed | M112: 45974 | N112: TrungNVT
A113: WEB-LOGIN-007 | B113: Driver login attempt on web platform | C113: 1. Navigate to login page. 2. Enter driver email in email field. 3. Enter correct password in password field. 4. Click "Login" button. 5. Check authorization response. | D113: 1. Error message "You don't have permissions to access the system" displayed. 2. User is not authenticated. 3. Login form remains visible. | E113: 1. Driver account exists. 2. Driver account is active. | F113: Passed | G113: 45916 | H113: TrungNVT | I113: Passed | J113: 45954 | K113: HuyNLQ | L113: Passed | M113: 45974 | N113: TrungNVT
A114: WEB-LOGIN-008 | B114: Parent login attempt on web platform | C114: 1. Navigate to login page. 2. Enter parent email in email field. 3. Enter correct password in password field. 4. Click "Login" button. 5. Check authorization response. | D114: 1. Error message "You don't have permissions to access the system" displayed. 2. User is not authenticated. 3. Login form remains visible. | E114: 1. Parent account exists. 2. Parent account is active. | F114: Passed | G114: 45916 | H114: TrungNVT | I114: Failed | J114: 45954 | K114: HuyNLQ | L114: Passed | M114: 45974 | N114: TrungNVT
A115: Logout
A116: WEB-LOGOUT-001 | B116: Admin logout from web dashboard | C116: 1. Login as admin successfully. 2. Navigate to admin dashboard. 3. Click "Log out" button in header. 4. Verify logout process. | D116: 1. User is logged out successfully. 2. Access token and refresh token removed from localStorage. 3. Redirected to login page. 4. User session is cleared. | E116: 1. Admin is logged in. 2. User is on dashboard page. | F116: Passed | G116: 45916 | H116: TrungNVT | I116: Passed | J116: 45954 | K116: HuyNLQ | L116: Passed | M116: 45974 | N116: TrungNVT | O116: Round1: Should redirect to login page instead of home page.
A117: WEB-LOGOUT-002 | B117: Logout with expired token | C117: 1. Login as admin successfully. 2. Wait for token to expire or manually expire token. 3. Click "Log out" button. 4. Check logout behavior. | D117: 1. Logout still works successfully. 2. Tokens are removed from localStorage. 3. Redirected to login page. 4. No error messages displayed. | E117: 1. Admin is logged in. 2. Token is expired. | F117: Passed | G117: 45916 | H117: TrungNVT | I117: Passed | J117: 45954 | K117: HuyNLQ | L117: Passed | M117: 45974 | N117: TrungNVT | O117: Round 1:Should redirect to login page instead of home page.
A118: WEB-LOGOUT-003 | B118: Access protected page after logout | C118: 1. Login as admin successfully. 2. Navigate to admin dashboard. 3. Click ""Log out"" button. 4. Manually navigate to protected URL (e.g., /dashboard). 5. Check system response. | D118: User is redirected to login page. | E118: 1. Admin is logged in. 2. User knows protected URL. | F118: Passed | G118: 45916 | H118: TrungNVT | I118: Passed | J118: 45954 | K118: HuyNLQ | L118: Passed | M118: 45974 | N118: TrungNVT | O118: Round 1:Should redirect to login page instead of home page.
...

Sheet Student Management
A2: Feature | B2: Student management | R2: Passed
A3: Test requirement | B3: Verifies the complete student management flow—including creating, viewing, editing, and deactivating student records—covering input validation, relationship consistency (class, parent, bus assignments), permission checks, data integrity, and graceful error handling. | R3: Failed
A4: Number of TCs | B4: =COUNTA(A12:A916)-8 -> 44 | R4: Pending
A5: Testing Round | B5: Passed | C5: Failed | D5: Pending | E5: N/A | R5: N/A
A6: Round 1 | B6: =COUNTIF($F10:$F914,B5) -> 39 | C6: =COUNTIF($F10:$F914,C5) -> 4 | D6: =COUNTIF($F10:$F914,D5) -> 0 | E6: =COUNTIF($F10:$F914,E5) -> 1
A7: Round 2 | B7: =COUNTIF($I10:$I914,B5) -> 39 | C7: =COUNTIF($I10:$I914,C5) -> 3 | D7: =COUNTIF($F10:$F914,D5) -> 0 | E7: =COUNTIF($F10:$F914,E5) -> 1
A8: Round 3 | B8: =COUNTIF($L10:$L914,B5) -> 41 | C8: =COUNTIF($L10:$L914,C5) -> 0 | D8: =COUNTIF($F10:$F914,D5) -> 0 | E8: =COUNTIF($F10:$F914,E5) -> 1
A10: Test Case ID | B10: Test Case Description | C10: Test Case Procedure | D10: Expected Results | E10: Pre-conditions | F10: Round 1 | G10: Test date | H10: Tester | I10: Round 2 | J10: Test date | K10: Tester | L10: Round 3 | M10: Test date | N10: Tester | O10: Note
A11: Add Student
A12: STU-001 | B12: Verify that a student can be successfully created with valid data by an admin user. | C12: 1.Send POST request to /api/Student with valid student data 2.Include admin authorization token in headers 3.Verify response status and data | D12: 1.Status Code: 201 Created 2.Response contains student data with generated ID 3.Student status is set to "Available" 4.Student is created in database | E12: 1. Admin user is authenticated 2. Database is accessible | F12: Passed | G12: 45914 | H12: KhoiVN | I12: Passed | J12: 45954 | K12: NguyetNTT | L12: Passed | M12: 45974 | N12: KhoiVN
A13: STU-002 | B13: Verify that creating a student fails when required fields are missing. | C13: 1. Send POST request to /api/Student with missing firstName 2. Include admin authorization token in headers 3. Verify error response | D13: 1. Status Code: 400 Bad Request 2. Error message indicates missing required field 3. No student is created in database | E13: 1. Admin user is authenticated 2. Database is accessible | F13: Failed | G13: 45914 | H13: KhoiVN | I13: Failed | J13: 45954 | K13: NguyetNTT | L13: Passed | M13: 45974 | N13: KhoiVN | O13: When both parentId and parentEmail are provided, The new parentEmail override the existing email in user table. Need to be clarified here.
A14: STU-003 | B14: Verify that non-admin users cannot create students. | C14: 1.Send POST request to /api/Student with valid data 2.Include parent authorization token in headers 3.Verify access denied response | D14: 1. Status Code: 403 Forbidden 2. Access denied error 3. No student is created in database | E14: 1. Parent user is authenticated (non-admin) 2. Database is accessible | F14: Passed | G14: 45914 | H14: KhoiVN | I14: Passed | J14: 45954 | K14: NguyetNTT | L14: Passed | M14: 45974 | N14: KhoiVN
A15: STU-004 | B15: Verify that students can be imported from a valid Excel file. | C15: 1. Send POST request to /api/Student/import with Excel file 2. Include admin authorization token in headers 3. Verify response status and import results | D15: 1. Status Code: 200 OK 2. Response contains import statistics 3. Successful students are created in database 4. Failed students are reported with reasons | E15: 1. Admin user is authenticated 2. Valid Excel file with student data exists 3. Database is accessible | F15: Passed | G15: 45914 | H15: KhoiVN | I15: Failed | J15: 45954 | K15: NguyetNTT | L15: Passed | M15: 45974 | N15: KhoiVN
A16: STU-005 | B16: Verify that importing fails with invalid file format. | C16: 1. Send POST request to /api/Student/import with .csv file 2. Include admin authorization token in headers 3. Verify error response | D16: 1. Status Code: 400 Bad Request 2. Error message indicates only .xlsx files are supported 3. No students are imported | E16: 1. Admin user is authenticated 2. Invalid file format exists 3. Database is accessible | F16: Passed | G16: 45914 | H16: KhoiVN | I16: Passed | J16: 45954 | K16: NguyetNTT | L16: Passed | M16: 45974 | N16: KhoiVN
A17: STU-006 | B17: Verify that creating a student fails when ParentEmail format is invalid. | C17: 1. Send POST request to /api/Student with invalid email format 2. Include admin authorization token in headers 3.Verify error response | D17: 1. Status Code: 400 Bad Request 2. Error message indicates invalid email format 3. No student is created in database | E17: 1. Admin user is authenticated 2. Database is accessible | F17: Passed | G17: 45914 | H17: KhoiVN | I17: Passed | J17: 45954 | K17: NguyetNTT | L17: Passed | M17: 45974 | N17: KhoiVN
A18: STU-007 | B18: Verify that creating a student fails when firstName exceeds 50 characters. | C18: 1. Send POST request to /api/Student with firstName longer than 50 characters 2. Include admin authorization token in headers 3. Verify error response | D18: 1. Status Code: 400 Bad Request 2. Error message indicates firstName cannot exceed 50 characters 3. No student is created in database | E18: 1. Admin user is authenticated 2. Database is accessible | F18: Failed | G18: 45914 | H18: KhoiVN | I18: Passed | J18: 45954 | K18: NguyetNTT | L18: Passed | M18: 45974 | N18: KhoiVN | O18: API passed but No validation in UI
A19: View Student
A20: STU-008 | B20: Verify that parent can retrieve their own child's data but not other children. | C20: 1. Send GET request to /api/Student/{own-child-id} 2. Include parent authorization token in headers 3. Verify successful access 4. Send GET request to /api/Student/{other-child-id} 5. Verify access denied | D20: 1. Own child: Status Code 200 OK with student data 2. Other child: Status Code 403 Forbidden with access denied | E20: 1. Parent user is authenticated 2. Student belongs to the authenticated parent 3. Another student belongs to different parent 4. Database is accessible | F20: N/A | G20: 45914 | H20: KhoiVN | I20: N/A | J20: 45954 | K20: NguyetNTT | L20: N/A | M20: 45974 | N20: KhoiVN
A21: STU-009 | B21: Verify that admin can retrieve list of students with filters applied | C21: 1. Send GET request to /api/Student 2. Provide proper filters in the url params 3. Verify returned data | D21: 1. Correct list of students is returned | E21: 1. Admin user is authenticated 2. Database is accessible | F21: Passed | G21: 45914 | H21: KhoiVN | I21: Passed | J21: 45954 | K21: NguyetNTT | L21: Passed | M21: 45974 | N21: KhoiVN
A22: STU-010 | B22: Verify that students can be exported to Excel by an admin user. | C22: 1. Send GET request to /api/Student/export 2. Include admin authorization token in headers 3. Verify response status and file content | D22: 1. Status Code: 200 OK 2. Response contains Excel file with proper content type 3. File includes all student data with correct headers 4. File is downloadable as "Students.xlsx" | E22: 1. Admin user is authenticated 2. Database is accessible | F22: Passed | G22: 45914 | H22: KhoiVN | I22: Passed | J22: 45954 | K22: NguyetNTT | L22: Passed | M22: 45974 | N22: KhoiVN
A23: STU-011 | B23: Verify that getting students by invalid status fails. | C23: 1. Send GET request to /api/Student/status/99 (invalid status) 2. Include admin authorization token in headers 3. Verify error response | D23: 1. Status Code: 400 Bad Request 2. Error message indicates invalid status value with valid options 3. No data is returned | E23: 1. Admin user is authenticated 2. Database is accessible | F23: Passed | G23: 45914 | H23: KhoiVN | I23: Failed | J23: 45954 | K23: NguyetNTT | L23: N/A | M23: 45974 | N23: KhoiVN
A24: STU-012 | B24: Verify that a parent cannot access a student who has no parent assigned (ParentId is null). | C24: 1. Create a student with ParentId = null (no parent assigned) 2. Send GET request to /api/Student/{student-id} with parent authorization token 3. Verify access denied response | D24: 1. Status Code: 403 Forbidden 2. Access denied error 3. Student data is not returned | E24: 1. Driver user is authenticated 2. Students and parents exist, students are not linked to parents 3. Database is accessible | F24: Passed | G24: 45914 | H24: KhoiVN | I24: Passed | J24: 45954 | K24: NguyetNTT | L24: Passed | M24: 45974 | N24: KhoiVN
A25: STU-013 | B25: Verify that a driver cannot access any student data. | C25: 1. Send GET request to /api/Student/{student-id} with driver authorization token 2. Verify access denied response 3. Send GET request to /api/Student/parent/{parent-id} with driver authorization token 4. Verify access denied response | D25: 1. Both requests return Status Code: 403 Forbidden 2. Access denied error for both endpoints 3. No student data is returned | E25: 1. Driver user is authenticated 2. Students exist 3. Database is accessible | F25: Passed | G25: 45914 | H25: KhoiVN | I25: N/A | J25: 45954 | K25: NguyetNTT | L25: N/A | M25: 45974 | N25: KhoiVN
A26: Update
A27: STU-014 | B27: Verify that a student can be successfully updated with valid data by an admin user. | C27: 1. Send PUT request to /api/Student/{id} with updated data 2. Include admin authorization token in headers 3. Verify response status and updated data | D27: 1. Status Code: 200 OK 2. Response contains updated student data 3. Student data is updated in database | E27: 1. Admin user is authenticated 2. Student exists in the system 3. Database is accessible | F27: Failed | G27: 45914 | H27: KhoiVN | I27: Passed | J27: 45954 | K27: NguyetNTT | L27: Passed | M27: 45974 | N27: KhoiVN | O27: In UI: display phone number instead of email Required email, while email is optional when creating, needs to be clarified
A28: STU-015 | B28: Verify that a student can be successfully activated by an admin. | C28: 1. Send POST request to /api/Student/{id}/activate 2. Include admin authorization token in headers 3. Verify response status and updated student data | D28: 1. Status Code: 200 OK 2. Response contains updated student data 3. Student status is changed to Active 4. ActivatedAt timestamp is set | E28: 1. Admin user is authenticated 2. Student exists in the system with Available status 3. Database is accessible | F28: Passed | G28: 45914 | H28: KhoiVN | I28: Passed | J28: 45954 | K28: NguyetNTT | L28: Passed | M28: 45974 | N28: KhoiVN
A29: STU-016 | B29: Verify that a student can be successfully deactivated with reason by an admin. | C29: 1. Send POST request to /api/Student/{id}/deactivate with reason 2. Include admin authorization token in headers 3. Verify response status and updated student data | D29: 1. Status Code: 200 OK 2. Response contains updated student data 3. Student status is changed to Inactive 4. DeactivatedAt timestamp is set 5. DeactivationReason is stored | E29: 1. Admin user is authenticated 2. Student exists in the system with Active status 3. Database is accessible | F29: Passed | G29: 45914 | H29: KhoiVN | I29: Passed | J29: 45954 | K29: NguyetNTT | L29: Passed | M29: 45974 | N29: KhoiVN
A30: STU-017 | B30: Verify that students can be filtered by status. | C30: 1. Send GET request to /api/Student/status/{status} 2. Include admin authorization token in headers 3. Verify response status and filtered student list | D30: 1. Status Code: 200 OK 2. Response contains array of students with Active status only 3. All returned students have status = Active | E30: 1. Admin user is authenticated 2. Students with different statuses exist in the system 3. Database is accessible | F30: Passed | G30: 45914 | H30: KhoiVN | I30: Passed | J30: 45954 | K30: NguyetNTT | L30: Passed | M30: 45974 | N30: KhoiVN
A31: STU-018 | B31: Verify that deactivating a student fails when reason is missing. | C31: 1. Send POST request to /api/Student/{id}/deactivate with empty request body 2. Include admin authorization token in headers 3. Verify error response | D31: 1. Status Code: 400 Bad Request 2. Error message indicates deactivation reason is required 3. Student status remains unchanged | E31: 1. Admin user is authenticated 2. Students with active statuses exist in the system 3. Database is accessible | F31: Passed | G31: 45914 | H31: KhoiVN | I31: Passed | J31: 45954 | K31: NguyetNTT | L31: Passed | M31: 45974 | N31: KhoiVN | O31: Only alert in UI, better have a modal
A32: STU-019 | B32: Verify that activating a non-existent student fails. | C32: 1. Send POST request to /api/Student/{non-existent-id}/activate 2. Include admin authorization token in headers 3. Verify error response | D32: 1. Status Code: 404 Not Found 2. Error message indicates student not found 3. No changes are made to database | E32: 1. Admin user is authenticated 2. Students with such id does not exist in the system 3. Database is accessible | F32: Passed | G32: 45914 | H32: KhoiVN | I32: Passed | J32: 45954 | K32: NguyetNTT | L32: Passed | M32: 45974 | N32: KhoiVN
A33: Update
A34: STU-020 | B34: Verify that a student can be successfully updated with valid data by an admin user. | C34: 1. Send PUT request to /api/Student/{id} with updated data 2. Include admin authorization token in headers 3. Verify response status and updated data | D34: 1. Status Code: 200 OK 2. Response contains updated student data 3. Student data is updated in database | E34: 1. Admin user is authenticated 2. Student exists in the system 3. Database is accessible | F34: Failed | G34: 45914 | H34: KhoiVN | I34: Passed | J34: 45954 | K34: NguyetNTT | L34: Passed | M34: 45974 | N34: KhoiVN | O34: In UI: display phone number instead of email Required email, while email is optional when creating, needs to be clarified
A35: STU-021 | B35: Verify that a student can be successfully activated by an admin. | C35: 1. Send POST request to /api/Student/{id}/activate 2. Include admin authorization token in headers 3. Verify response status and updated student data | D35: 1. Status Code: 200 OK 2. Response contains updated student data 3. Student status is changed to Active 4. ActivatedAt timestamp is set | E35: 1. Admin user is authenticated 2. Student exists in the system with Available status 3. Database is accessible | F35: Passed | G35: 45914 | H35: KhoiVN | I35: Passed | J35: 45954 | K35: NguyetNTT | L35: Passed | M35: 45974 | N35: KhoiVN
A36: STU-022 | B36: Verify that a student can be successfully deactivated with reason by an admin. | C36: 1. Send POST request to /api/Student/{id}/deactivate with reason 2. Include admin authorization token in headers 3. Verify response status and updated student data | D36: 1. Status Code: 200 OK 2. Response contains updated student data 3. Student status is changed to Inactive 4. DeactivatedAt timestamp is set 5. DeactivationReason is stored | E36: 1. Admin user is authenticated 2. Student exists in the system with Active status 3. Database is accessible | F36: Passed | G36: 45914 | H36: KhoiVN | I36: Passed | J36: 45954 | K36: NguyetNTT | L36: Passed | M36: 45974 | N36: KhoiVN
A37: STU-023 | B37: Verify that students can be filtered by status. | C37: 1. Send GET request to /api/Student/status/{status} 2. Include admin authorization token in headers 3. Verify response status and filtered student list | D37: 1. Status Code: 200 OK 2. Response contains array of students with Active status only 3. All returned students have status = Active | E37: 1. Admin user is authenticated 2. Students with different statuses exist in the system 3. Database is accessible | F37: Passed | G37: 45914 | H37: KhoiVN | I37: Passed | J37: 45954 | K37: NguyetNTT | L37: Passed | M37: 45974 | N37: KhoiVN
A38: STU-024 | B38: Verify that deactivating a student fails when reason is missing. | C38: 1. Send POST request to /api/Student/{id}/deactivate with empty request body 2. Include admin authorization token in headers 3. Verify error response | D38: 1. Status Code: 400 Bad Request 2. Error message indicates deactivation reason is required 3. Student status remains unchanged | E38: 1. Admin user is authenticated 2. Students with active statuses exist in the system 3. Database is accessible | F38: Passed | G38: 45914 | H38: KhoiVN | I38: Passed | J38: 45954 | K38: NguyetNTT | L38: Passed | M38: 45974 | N38: KhoiVN | O38: Only alert in UI, better have a modal
A39: STU-025 | B39: Verify that activating a non-existent student fails. | C39: 1. Send POST request to /api/Student/{non-existent-id}/activate 2. Include admin authorization token in headers 3. Verify error response | D39: 1. Status Code: 404 Not Found 2. Error message indicates student not found 3. No changes are made to database | E39: 1. Admin user is authenticated 2. Students with such id does not exist in the system 3. Database is accessible | F39: Passed | G39: 45914 | H39: KhoiVN | I39: Passed | J39: 45954 | K39: NguyetNTT | L39: Passed | M39: 45974 | N39: KhoiVN
A40: STUDENT_CRUD
A41: STU-026 | B41: Test deleting student (Soft Delete) | C41: 1. Login as Admin 2. Call DELETE /api/student/{id} 3. Submit | D41: 1. Returns 200 OK 2. Student IsDeleted = true 3. Student removed from active lists 4. Historical data preserved | E41: 1. Active student exists | F41: Passed | G41: 45914 | H41: KhoiVN | I41: Passed | J41: 45954 | K41: NguyetNTT | L41: Passed | M41: 45974 | N41: KhoiVN | O41: In UI: display phone number instead of email Required email, while email is optional when creating, needs to be clarified
A42: STU-027 | B42: Test importing students from Excel | C42: 1. Login as Admin 2. Call POST /api/student/import 3. Upload valid .xlsx file 4. Submit | D42: 1. Returns 200 OK 2. Returns count of successful/failed imports 3. Students created in database 4. Duplicate emails handled gracefully | E42: 1. Valid Excel file | F42: Passed | G42: 45914 | H42: KhoiVN | I42: Passed | J42: 45954 | K42: NguyetNTT | L42: Passed | M42: 45974 | N42: KhoiVN
A43: STU-028 | B43: Test importing students with invalid data | C43: 1. Upload .xlsx with missing required fields (Name, Email) 2. Submit | D43: 1. Returns 200 OK (Partial Success) 2. FailedStudents list contains error details 3. Valid rows still processed | E43: 1. Invalid Excel file | F43: Passed | G43: 45914 | H43: KhoiVN | I43: Passed | J43: 45954 | K43: NguyetNTT | L43: Passed | M43: 45974 | N43: KhoiVN
A44: STU-029 | B44: Test allocating students to vehicles (Indirect) | C44: 1. Create Route with PickupPoints 2. Assign Student to PickupPoint (Enrollment) 3. Assign Route to Vehicle (Trip Generation) 4. Check Trip details | D44: 1. Student appears in Trip Stops 2. Student allocated to correct Vehicle for the trip | E44: 1. Route, Vehicle, Student exist | F44: Passed | G44: 45914 | H44: KhoiVN | I44: Passed | J44: 45954 | K44: NguyetNTT | L44: Passed | M44: 45974 | N44: KhoiVN
A45: PARENT_VIEW
A46: STU-030 | B46: Test viewing my students' information | C46: 1. Login as Parent 2. Call GET /api/student/parent/{myParentId} 3. Check list | D46: 1. Returns 200 OK 2. List of students linked to parent 3. Includes status, class, pickup point info | E46: 1. Parent has students | F46: Passed | G46: 45914 | H46: KhoiVN | I46: Passed | J46: 45954 | K46: NguyetNTT | L46: Passed | M46: 45974 | N46: KhoiVN | O46: In UI: display phone number instead of email Required email, while email is optional when creating, needs to be clarified
A47: STU-031 | B47: Test viewing other parent's students (Security) | C47: 1. Login as Parent A 2. Call GET /api/student/parent/{parentB_Id} 3. Submit | D47: 1. Returns 403 Forbidden 2. Access denied | E47: 1. Parent B exists | F47: Passed | G47: 45914 | H47: KhoiVN | I47: Passed | J47: 45954 | K47: NguyetNTT | L47: Passed | M47: 45974 | N47: KhoiVN
A48: STU-032 | B48: Test updating student information (Parent) | C48: 1. Login as Parent 2. Try to call PUT /api/student/{id} 3. Submit | D48: 1. Returns 403 Forbidden (Currently Admin only) 2. Parent cannot modify core student data directly | E48: 1. Student exists | F48: Passed | G48: 45914 | H48: KhoiVN | I48: Passed | J48: 45954 | K48: NguyetNTT | L48: Passed | M48: 45974 | N48: KhoiVN
A49: STU-033 | B49: Test updating student face profile | C49: 1. Login as Parent/Admin 2. Call API to upload face image (Endpoint TBD/Missing) 3. Submit | D49: 1. Feature Not Implemented 2. Should update face recognition data | E49: 1. Image file ready | F49: Passed | G49: 45914 | H49: KhoiVN | I49: Passed | J49: 45954 | K49: NguyetNTT | L49: Passed | M49: 45974 | N49: KhoiVN
A50: BUS_LISTS
A51: STU-034 | B51: Test viewing student list on specific trip | C51: 1. Login as Driver 2. Call GET /api/trip/{id}/detail-for-driver 3. Check response | D51: 1. Returns 200 OK 2. TripDto contains Stops 3. Each Stop contains Attendance list with Student Names | E51: 1. Assigned trip exists | F51: Passed | G51: 45914 | H51: KhoiVN | I51: Passed | J51: 45954 | K51: NguyetNTT | L51: Passed | M51: 45974 | N51: KhoiVN | O51: In UI: display phone number instead of email Required email, while email is optional when creating, needs to be clarified
A52: STU-035 | B52: Test viewing bus-specific attendance list | C52: 1. Login as Supervisor/Admin 2. Call GET /api/trip/{id}/attendance 3. Check response | D52: 1. Returns 200 OK 2. Summary of attendance (Boarded, Absent, etc.) 3. Matches student list for that bus | E52: 1. Trip exists | F52: Passed | G52: 45914 | H52: KhoiVN | I52: Passed | J52: 45954 | K52: NguyetNTT | L52: Passed | M52: 45974 | N52: KhoiVN
A53: STU-036 | B53: Test driver viewing unassigned trip | C53: 1. Login as Driver A 2. Try GET /api/trip/{tripId_of_DriverB}/detail-for-driver 3. Submit | D53: 1. Returns 403/404 2. Driver can only view their own assigned trips | E53: 1. Trip belongs to Driver B | F53: Passed | G53: 45914 | H53: KhoiVN | I53: Passed | J53: 45954 | K53: NguyetNTT | L53: Passed | M53: 45974 | N53: KhoiVN
A54: ABSENCE_REPORT
A55: ABS-001 | B55: Test sending absence report (Parent) | C55: 1. Login as Parent 2. Call POST /api/student-absence-requests/parent 3. Body: {studentId, date, reason} 4. Submit | D55: 1. Returns 201 Created 2. Request saved with status "Pending" 3. Notification sent to Admin/Supervisor | E55: 1. Valid student | F55: Passed | G55: 45914 | H55: KhoiVN | I55: Passed | J55: 45954 | K55: NguyetNTT | L55: Passed | M55: 45974 | N55: KhoiVN | O55: In UI: display phone number instead of email Required email, while email is optional when creating, needs to be clarified
A56: ABS-002 | B56: Test handling absent student (Approve) | C56: 1. Login as Admin 2. Call PATCH /api/student-absence-requests/{id}/approve 3. Submit | D56: 1. Returns 200 OK 2. Status = "Approved" 3. Student marked as "Excused" in daily attendance (if integrated) | E56: 1. Pending request | F56: Passed | G56: 45914 | H56: KhoiVN | I56: Passed | J56: 45954 | K56: NguyetNTT | L56: Passed | M56: 45974 | N56: KhoiVN
A57: ABS-003 | B57: Test handling absent student (Reject) | C57: 1. Login as Admin 2. Call PATCH /api/student-absence-requests/{id}/reject 3. Body: {reason} 4. Submit | D57: 1. Returns 200 OK 2. Status = "Rejected" 3. Parent notified | E57: 1. Pending request | F57: Passed | G57: 45914 | H57: KhoiVN | I57: Passed | J57: 45954 | K57: NguyetNTT | L57: Passed | M57: 45974 | N57: KhoiVN
A58: ABS-004 | B58: Test sending absence for past date | C58: 1. Create request for date < Today 2. Submit | D58: 1. Returns 400 Bad Request (if policy exists) 2. Or allows with warning | E58: None | F58: Passed | G58: 45914 | H58: KhoiVN | I58: Passed | J58: 45954 | K58: NguyetNTT | L58: Passed | M58: 45974 | N58: KhoiVN
A59: DRIVER_LEAVE
A60: DRV-001 | B60: Test sending leave/sick request (Driver) | C60: 1. Login as Driver 2. Call POST /api/driver/send-leave-request 3. Body: {startDate, endDate, reason, type} 4. Submit | D60: 1. Returns 201 Created 2. Request saved as "Pending" 3. Admin notified | E60: 1. Driver account | F60: Passed | G60: 45914 | H60: KhoiVN | I60: Passed | J60: 45954 | K60: NguyetNTT | L60: Passed | M60: 45974 | N60: KhoiVN | O60: In UI: display phone number instead of email Required email, while email is optional when creating, needs to be clarified
A61: DRV-002 | B61: Test approving leave request with replacement | C61: 1. Login as Admin 2. Call PATCH /api/driver/leaves/{id}/approve 3. Body: {replacementDriverId} 4. Submit | D61: 1. Returns 200 OK 2. Status = "Approved" 3. Replacement driver assigned to vehicle for duration | E61: 1. Pending request 2. Available replacement | F61: Passed | G61: 45914 | H61: KhoiVN | I61: Passed | J61: 45954 | K61: NguyetNTT | L61: Passed | M61: 45974 | N61: KhoiVN
A62: DRV-003 | B62: Test rejecting leave request | C62: 1. Login as Admin 2. Call PATCH /api/driver/leaves/{id}/reject 3. Body: {reason} 4. Submit | D62: 1. Returns 200 OK 2. Status = "Rejected" 3. Driver notified | E62: 1. Pending request | F62: Passed | G62: 45914 | H62: KhoiVN | I62: Passed | J62: 45954 | K62: NguyetNTT | L62: Passed | M62: 45974 | N62: KhoiVN
A63: DRV-004 | B63: Test overlapping leave requests | C63: 1. Driver has approved leave Jan 1-5 2. Driver submits new request Jan 3-7 3. Submit | D63: 1. Returns 409 Conflict 2. Error "Overlapping leave request" | E63: 1. Existing leave | F63: Passed | G63: 45914 | H63: KhoiVN | I63: Passed | J63: 45954 | K63: NguyetNTT | L63: Passed | M63: 45974 | N63: KhoiVN

Sheet School System Configuration
A2: Feature | B2: School System Configuration | R2: Passed
A3: Test requirement | B3: Verifies the full configuration flow for school-wide system settings—including updating school information, location, branding, pricing, operational rules, and system parameters—covering input validation, permission control, dependency checks, and consistent system-wide impact. | R3: Failed
A4: Number of TCs | B4: =COUNTA(A12:A896)-6 -> 26 | R4: Pending
A5: Testing Round | B5: Passed | C5: Failed | D5: Pending | E5: N/A | R5: N/A
A6: Round 1 | B6: =COUNTIF($F10:$F894,B5) -> 23 | C6: =COUNTIF($F10:$F894,C5) -> 2 | D6: =COUNTIF($F10:$F894,D5) -> 1 | E6: =COUNTIF($F10:$F894,E5) -> 0
A7: Round 2 | B7: =COUNTIF($I10:$I894,B5) -> 23 | C7: =COUNTIF($I10:$I894,C5) -> 2 | D7: =COUNTIF($F10:$F894,D5) -> 1 | E7: =COUNTIF($F10:$F894,E5) -> 0
A8: Round 3 | B8: =COUNTIF($L10:$L894,B5) -> 23 | C8: =COUNTIF($L10:$L894,C5) -> 0 | D8: =COUNTIF($F10:$F894,D5) -> 1 | E8: =COUNTIF($F10:$F894,E5) -> 0
A10: Test Case ID | B10: Test Case Description | C10: Test Case Procedure | D10: Expected Results | E10: Pre-conditions | F10: Round 1 | G10: Test date | H10: Tester | I10: Round 2 | J10: Test date | K10: Tester | L10: Round 3 | M10: Test date | N10: Tester | O10: Note
A11: PARENT_NOTIFICATIONS
A12: CONF-001 | B12: Test creating initial school information | C12: 1. Login as Admin 2. Call POST /api/school 3. Body: {name, address, email, phone} 4. Submit | D12: 1. Returns 201 Created 2. School info saved 3. IsActive = true by default | E12: 1. No school info exists | F12: Passed | G12: 45914 | H12: HuyNLQ | I12: Passed | J12: 45954 | K12: HuyNLQ | L12: Passed | M12: 45974 | N12: KhoiVN
A13: CONF-002 | B13: Test preventing duplicate school creation | C13: 1. School info already exists 2. Call POST /api/school again 3. Submit | D13: 1. Returns 409 Conflict 2. Error "School already exists" 3. System enforces singleton school record | E13: 1. School info exists | F13: Passed | G13: 45914 | H13: HuyNLQ | I13: Passed | J13: 45954 | K13: HuyNLQ | L13: Pending | M13: 45974 | N13: KhoiVN
A14: CONF-003 | B14: Test updating school information | C14: 1. Login as Admin 2. Call PUT /api/school/{id} 3. Update name and contact info 4. Submit | D14: 1. Returns 200 OK 2. Data updated in database 3. UpdatedAt timestamp refreshed | E14: 1. School info exists | F14: Passed | G14: 45914 | H14: HuyNLQ | I14: Passed | J14: 45954 | K14: HuyNLQ | L14: Passed | M14: 45974 | N14: KhoiVN
A15: CONF-004 | B15: Test public access to school info | C15: 1. No login (Anonymous) 2. Call GET /api/school 3. Check response | D15: 1. Returns 200 OK 2. Public info (name, address, contact) returned 3. Internal notes NOT returned | E15: 1. School info exists | F15: Passed | G15: 45914 | H15: HuyNLQ | I15: Passed | J15: 45954 | K15: HuyNLQ | L15: Passed | M15: 45974 | N15: KhoiVN
A16: CONF-005 | B16: Test admin access to full school info | C16: 1. Login as Admin 2. Call GET /api/school/admin 3. Check response | D16: 1. Returns 200 OK 2. Includes InternalNotes, IsPublished status 3. Full details available | E16: 1. Admin account | F16: Failed | G16: 45914 | H16: HuyNLQ | I16: Passed | J16: 45954 | K16: HuyNLQ | L16: Passed | M16: 45974 | N16: KhoiVN
A17: LOCATION_IMAGES
A18: CONF-006 | B18: Test updating school location (Map Picker) | C18: 1. Login as Admin 2. Call PUT /api/school/{id}/location 3. Body: {lat, long, fullAddress, displayAddress} 4. Submit | D18: 1. Returns 200 OK 2. Coordinates updated 3. Spatial data (Geog point) updated correctly for map queries | E18: 1. Valid coordinates | F18: Passed | G18: 45914 | H18: HuyNLQ | I18: Failed | J18: 45954 | K18: HuyNLQ | L18: Passed | M18: 45974 | N18: KhoiVN
A19: CONF-007 | B19: Test retrieving school images | C19: 1. Login as Admin 2. Call GET /api/school/images 3. Check response | D19: 1. Returns list of active images 2. Filtered by types: Logo, Banner, Gallery, etc. 3. Includes file URLs and metadata | E19: 1. Images uploaded | F19: Failed | G19: 45914 | H19: HuyNLQ | I19: Passed | J19: 45954 | K19: HuyNLQ | L19: Passed | M19: 45974 | N19: KhoiVN
A20: CONF-008 | B20: Test updating location with invalid coordinates | C20: 1. Call PUT /api/school/{id}/location 2. Body: {lat: 95.0, long: 200.0} 3. Submit | D20: 1. Returns 400 Bad Request 2. Validation error for coordinate range | E20: None | F20: Passed | G20: 45914 | H20: HuyNLQ | I20: Passed | J20: 45954 | K20: HuyNLQ | L20: Pending | M20: 45974 | N20: KhoiVN
A21: UNIT_PRICE_CRUD
A22: CONF-009 | B22: Test creating new unit price | C22: 1. Login as Admin 2. Call POST /api/unitprice 3. Body: {name, pricePerKm: 10000, effectiveFrom: tomorrow} 4. Submit | D22: 1. Returns 201 Created 2. Unit price saved 3. CreatedByAdmin info recorded | E22: 1. No overlapping prices | F22: Passed | G22: 45914 | H22: HuyNLQ | I22: Passed | J22: 45954 | K22: HuyNLQ | L22: Passed | M22: 45974 | N22: KhoiVN
A23: CONF-010 | B23: Test updating unit price details | C23: 1. Call PUT /api/unitprice/{id} 2. Update price and description 3. Submit | D23: 1. Returns 200 OK 2. Price updated 3. Effective dates updated if changed | E23: 1. Unit price exists | F23: Passed | G23: 45914 | H23: HuyNLQ | I23: Failed | J23: 45954 | K23: HuyNLQ | L23: Passed | M23: 45974 | N23: KhoiVN
A24: CONF-011 | B24: Test soft deleting unit price | C24: 1. Call DELETE /api/unitprice/{id} 2. Submi | D24: 1. Returns 204 No Content 2. IsDeleted = true 3. IsActive = false 4. EffectiveTo set to now | E24: 1. Active unit price | F24: Passed | G24: 45914 | H24: HuyNLQ | I24: Passed | J24: 45954 | K24: HuyNLQ | L24: Passed | M24: 45974 | N24: KhoiVN
A25: CONF-012 | B25: Test retrieving current effective price | C25: 1. Call GET /api/unitprice/current-effective 2. Check response | D25: 1. Returns single price config 2. Price is active AND (EffectiveFrom <= Now <= EffectiveTo) 3. Used for fee calculation | E25: 1. Active effective price exists | F25: Passed | G25: 45914 | H25: HuyNLQ | I25: Passed | J25: 45954 | K25: HuyNLQ | L25: Passed | M25: 45974 | N25: KhoiVN
A26: CONF-013 | B26: Test retrieving all unit prices (including deleted) | C26: 1. Call GET /api/unitprice/all-including-deleted 2. Check list | D26: 1. Returns active, inactive, and deleted prices 2. Useful for audit trail | E26: 1. Deleted prices exist | F26: Passed | G26: 45914 | H26: HuyNLQ | I26: Passed | J26: 45954 | K26: HuyNLQ | L26: Passed | M26: 45974 | N26: KhoiVN
A27: PRICE_VALIDATION
A28: CONF-014 | B28: Test preventing overlapping price ranges (Create) | C28: 1. Existing price: Jan 1 - Jan 31 2. Create new price: Jan 15 - Feb 15 3. Submit | D28: 1. Returns 400 Bad Request or 500 (InvalidOperation) 2. Error "Cannot create new UnitPrice in this time range" 3. Overlap | E28: 1. Active price exists | F28: Passed | G28: 45914 | H28: HuyNLQ | I28: Passed | J28: 45954 | K28: HuyNLQ | L28: Passed | M28: 45974 | N28: KhoiVN
A29: CONF-015 | B29: Test preventing overlapping price ranges (Update) | C29: 1. Price A: Jan 1 - Jan 31 2. Price B: Feb 1 - Feb 28 3. Update Price B to start Jan 20 4. Submit | D29: 1. Returns 400/500 2. Error "Cannot update UnitPrice in this time range" 3. Overlap detected | E29: 1. Two active prices | F29: Passed | G29: 45914 | H29: HuyNLQ | I29: Passed | J29: 45954 | K29: HuyNLQ | L29: Passed | M29: 45974 | N29: KhoiVN
A30: CONF-016 | B30: Test creating price with open-ended EffectiveTo | C30: 1. Create price: EffectiveFrom = Tomorrow, EffectiveTo = null 2. Submit | D30: 1. Returns 201 Created 2. Price valid indefinitely from start date | E30: 1. No future prices exist | F30: Passed | G30: 45914 | H30: HuyNLQ | I30: Passed | J30: 45954 | K30: HuyNLQ | L30: Passed | M30: 45974 | N30: KhoiVN
A31: CONF-017 | B31: Test overlap with open-ended price | C31: 1. Existing price: Jan 1 - null (forever) 2. Create new price: Feb 1 - Feb 28 3. Submit | D31: 1. Returns Error 2. Overlap detected with open-ended existing price | E31: 1. Open-ended price exists | F31: Passed | G31: 45914 | H31: HuyNLQ | I31: Passed | J31: 45954 | K31: HuyNLQ | L31: Passed | M31: 45974 | N31: KhoiVN
A32: CONF-018 | B32: Test creating price in gap period | C32: 1. Price A: Jan 1 - Jan 15 2. Price B: Feb 1 - Feb 15 3. Create Price C: Jan 16 - Jan 31 4. Submit | D32: 1. Returns 201 Created 2. No overlap detected 3. Gap filled successfully | E32: 1. Gap exists between prices | F32: Passed | G32: 45914 | H32: HuyNLQ | I32: Passed | J32: 45954 | K32: HuyNLQ | L32: Passed | M32: 45974 | N32: KhoiVN
A33: Update school's location
A34: CONF-019 | B34: Test prevent update with invalid location | C34: 1. Existing location: long 111.2 lat 122.3 2. New location: long 222.3 lat 333.4 3. Submit | D34: 1. Returns 400 Bad Request or 500 (InvalidOperation) 2. Error "Cannot update with invalid location" 3. rejected | E34: 1. Location exist | F34: Passed | G34: 45914 | H34: HuyNLQ | I34: Passed | J34: 45954 | K34: HuyNLQ | L34: Passed | M34: 45974 | N34: KhoiVN
A35: CONF-020 | B35: Test prevent other user except admin can update | C35: 1. Login as parent 2. attempt to access the endpoint school/location/update | D35: 1. Returns 400/500 2. Error "You're not allowed to access this" 3. Rejected | E35: 1. login as parent | F35: Passed | G35: 45914 | H35: HuyNLQ | I35: Passed | J35: 45954 | K35: HuyNLQ | L35: Passed | M35: 45974 | N35: KhoiVN
A36: CONF-021 | B36: Test prevent updating during active trip | C36: 1. Login as admin 2. Attempt to update the locaiton during active trip | D36: 1. Returns badrequest 400 2. Location not updated during trip | E36: 1. Trip and location exist | F36: Passed | G36: 45914 | H36: HuyNLQ | I36: Passed | J36: 45954 | K36: HuyNLQ | L36: Passed | M36: 45974 | N36: KhoiVN
A37: Update school's information
A38: CONF-022 | B38: Test prevent update with invalid information | C38: 1. Schoolname: name with unallowed chars 2. SchoolImage: unsupported file type 3. Submit | D38: 1. Returns 400 Bad Request 2. Error "Please try again with valid information" 3. rejected | E38: 1. School exist | F38: Passed | G38: 45914 | H38: HuyNLQ | I38: Passed | J38: 45954 | K38: HuyNLQ | L38: Passed | M38: 45974 | N38: KhoiVN
A39: CONF-023 | B39: Test prevent other user except admin can update | C39: 1. Login as parent 2. attempt to access the endpoint school/information/update | D39: 1. Returns 400/500 2. Error "You're not allowed to access this" 3. Rejected | E39: 1. login as parent | F39: Passed | G39: 45914 | H39: HuyNLQ | I39: Passed | J39: 45954 | K39: HuyNLQ | L39: Passed | M39: 45974 | N39: KhoiVN
A40: CONF-024 | B40: Test updating with valid data | C40: 1. Login as admin 2. Valid image: png 3. Valid name: "FPT School" | D40: 1. Returns 203 updated 2. School info updated successfully | E40: 1. School exist | F40: Passed | G40: 45914 | H40: HuyNLQ | I40: Passed | J40: 45954 | K40: HuyNLQ | L40: Passed | M40: 45974 | N40: KhoiVN
A41: View school's information
A42: CONF-025 | B42: Login to view school information | C42: 1. Login as admin 2. Navigate about school page 3. Waiting for data to retrieve | D42: 1. Returns 200 success 2. School information is displayed correctly | E42: 1. School exist | F42: Passed | G42: 45914 | H42: HuyNLQ | I42: Passed | J42: 45954 | K42: HuyNLQ | L42: Passed | M42: 45974 | N42: KhoiVN
A43: CONF-026 | B43: Navigate to school information as guest | C43: 1. attempt to access the endpoint school/information/update as guest | D43: 1. Returns 401 2. Error "You're not allowed to access this" | E43: 1. Access as guest | F43: Pending | G43: 45914 | H43: HuyNLQ | I43: Pending | J43: 45954 | K43: HuyNLQ | L43: Pending | M43: 45974 | N43: KhoiVN

Sheet Schedule Management
A2: Feature | B2: Schedule Management | R2: Passed
A3: Test requirement | B3: Verifies the complete schedule management flow—including creating, editing, assigning, and updating daily bus schedules—covering input validation, time/route consistency, conflict detection, role-based permissions, and reliable system updates. | R3: Failed
A4: Number of TCs | B4: =COUNTA(A12:A979)-6 -> 125 | R4: Pending
A5: Testing Round | B5: Passed | C5: Failed | D5: Pending | E5: N/A | R5: N/A
A6: Round 1 | B6: =COUNTIF($F10:$F1026,B5) -> 97 | C6: =COUNTIF($F10:$F1026,C5) -> 28 | D6: =COUNTIF($F9:$F976,D4) -> 0 | E6: =COUNTIF($F9:$F976,E4) -> 0
A7: Round 2 | B7: =COUNTIF($I10:$I977,B5) -> 121 | C7: =COUNTIF($I10:$I977,C5) -> 4 | D7: =COUNTIF($F10:$F977,D5) -> 0 | E7: =COUNTIF($F10:$F977,E5) -> 0
A8: Round 3 | B8: =COUNTIF($L10:$L977,B5) -> 122 | C8: =COUNTIF($L10:$L977,C5) -> 3 | D8: =COUNTIF($F10:$F977,D5) -> 0 | E8: =COUNTIF($F10:$F977,E5) -> 0
A10: Test Case ID | B10: Test Case Description | C10: Test Case Procedure | D10: Expected Results | E10: Pre-conditions | F10: Round 1 | G10: Test date | H10: Tester | I10: Round 2 | J10: Test date | K10: Tester | L10: Round 3 | M10: Test date | N10: Tester | O10: Note
A11: Create Schedule
A12: SCHED-001 | B12: Create schedule with valid data | C12: 1. Click "Create Schedule" button 2. Fill all required fields (name, type, start/end time, academic year, effective dates) 3. Select RRule pattern 4. Click "Save" | D12: 1. Success message "Schedule created successfully" 2. Schedule appears in list 3. Modal closes | E12: 1. User logged in as admin 2. Academic years available | F12: Passed | G12: 45928 | H12: HuyNLQ | I12: Passed | J12: 45960 | K12: TrungNVT | L12: Failed | M12: 45986 | N12: HuyNLQ
A13: SCHED-002 | B13: Create schedule with missing required field | C13: 1. Click "Create Schedule" 2. Leave "Schedule Name" field empty 3. Fill other required fields 4. Click "Save" | D13: 1. Validation message "Schedule name is required" 2. Form submission blocked | E13: None | F13: Passed | G13: 45928 | H13: HuyNLQ | I13: Passed | J13: 45960 | K13: TrungNVT | L13: Passed | M13: 45986 | N13: HuyNLQ
A14: SCHED-003 | B14: Create schedule with invalid time range | C14: 1. Click "Create Schedule" 2. Set start time: 14:00 3. Set end time: 12:00 4. Fill other fields 5. Click "Save" | D14: 1. Validation message "End time must be after start time" 2. Form submission blocked | E14: None | F14: Passed | G14: 45928 | H14: HuyNLQ | I14: Passed | J14: 45960 | K14: TrungNVT | L14: Passed | M14: 45986 | N14: HuyNLQ
A15: SCHED-004 | B15: Create schedule with past effective date | C15: 1. Click "Create Schedule" 2. Set "Effective From" to yesterday's date 3. Fill other required fields 4. Click "Save" | D15: 1. Validation message "Effective date cannot be in the past" 2. Form submission blocked | E15: None | F15: Passed | G15: 45928 | H15: HuyNLQ | I15: Passed | J15: 45960 | K15: TrungNVT | L15: Passed | M15: 45986 | N15: HuyNLQ
A16: SCHED-005 | B16: Create schedule with duplicate name | C16: 1. Click "Create Schedule" 2. Enter name that already exists 3. Fill other required fields 4. Click "Save" | D16: 1. API responds 409 (Conflict) 2. Error message "Schedule name already exists" | E16: 1. Another schedule with same name exists | F16: Passed | G16: 45928 | H16: HuyNLQ | I16: Passed | J16: 45960 | K16: TrungNVT | L16: Passed | M16: 45986 | N16: HuyNLQ
A17: SCHED-006 | B17: Create schedule with invalid RRule | C17: 1. Click "Create Schedule" 2. Select custom RRule mode 3. Create invalid RRule pattern 4. Fill other fields 5. Click "Save" | D17: 1. RRule validation error appears 2. Form submission blocked | E17: None | F17: Passed | G17: 45928 | H17: HuyNLQ | I17: Passed | J17: 45960 | K17: TrungNVT | L17: Failed | M17: 45986 | N17: HuyNLQ
A18: SCHED-007 | B18: Create schedule with backend unavailable | C18: 1. Click "Create Schedule" 2. Fill all required fields 3. Mock API to return 503 4. Click "Save" | D18: 1. Error toast "Service unavailable, try later" 2. Form remains open | E18: 1. Backend offline / 503 | F18: Passed | G18: 45928 | H18: HuyNLQ | I18: Passed | J18: 45960 | K18: TrungNVT | L18: Passed | M18: 45986 | N18: HuyNLQ
A19: SCHED-008 | B19: Create schedule with special characters in name | C19: 1. Click "Create Schedule" 2. Enter name with special chars: "Test@#$%" 3. Fill other required fields 4. Click "Save" | D19: 1. Success message "Schedule created successfully 2. Name displayed correctly | E19: None | F19: Passed | G19: 45928 | H19: HuyNLQ | I19: Passed | J19: 45960 | K19: TrungNVT | L19: Passed | M19: 45986 | N19: HuyNLQ
A20: SCHED-009 | B20: Create schedule with very long name | C20: 1. Click "Create Schedule 2. Enter name with 200+ characters 3. Fill other required fields 4. Click "Save" | D20: 1. Validation message "Name too long (max 100 characters)" 2. Form submission blocked | E20: None | F20: Passed | G20: 45928 | H20: HuyNLQ | I20: Passed | J20: 45960 | K20: TrungNVT | L20: Passed | M20: 45986 | N20: HuyNLQ
A21: SCHED-010 | B21: Create schedule with same start and end time | C21: 1. Click "Create Schedule" 2. Set start time: 08:00 3. Set end time: 08:00 4. Fill other fields 5. Click "Save" | D21: 1. Validation message "End time must be after start time" 2. Form submission blocked | E21: None | F21: Passed | G21: 45928 | H21: HuyNLQ | I21: Passed | J21: 45960 | K21: TrungNVT | L21: Passed | M21: 45986 | N21: HuyNLQ
A22: SCHED-011 | B22: Create schedule with effective to before effective from | C22: 1. Click "Create Schedule" 2. Set "Effective From": 2024-12-01 3. Set "Effective To": 2024-11-01 4. Fill other fields 5. Click "Save" | D22: 1. Validation message "Effective To must be after Effective From" 2. Form submission blocked | E22: None | F22: Passed | G22: 45928 | H22: HuyNLQ | I22: Passed | J22: 45960 | K22: TrungNVT | L22: Failed | M22: 45986 | N22: HuyNLQ
A23: SCHED-012 | B23: Create schedule with network timeout | C23: 1. Click "Create Schedule" 2. Fill all required fields 3. Simulate network timeout 4. Click "Save" | D23: 1. Error message "Request timeout. Please check your connection" 2. Form remains open | E23: 1. Network timeout simulated | F23: Passed | G23: 45928 | H23: HuyNLQ | I23: Passed | J23: 45960 | K23: TrungNVT | L23: Passed | M23: 45986 | N23: HuyNLQ
... A26: SCHED-015 | B26: Create schedule with unsaved changes navigation | C26: 1. Click "Create Schedule" 2. Fill some fields 3. Try to navigate away 4. Confirm unsaved changes dialog | D26: 1. Warning dialog "You have unsaved changes" 2. Options: Save, Discard, Cancel 3. Navigation blocked until choice made | E26: None | F26: Failed | G26: 45928 | H26: HuyNLQ | I26: Passed | J26: 45960 | K26: TrungNVT | L26: Passed | M26: 45986 | N26: HuyNLQ
A27: Update Schedule
A28: SCHED-016 | B28: Update schedule with valid data | C28: 1. Click "Edit" button on existing schedule 2. Modify schedule name and time 3. Click "Save Changes" | D28: 1. Success message "Schedule updated successfully" 2. Changes reflected in list 3. Edit form closes | E28: 1. Existing schedule available 2. User logged in as admin | F28: Passed | G28: 45928 | H28: HuyNLQ | I28: Passed | J28: 45960 | K28: TrungNVT | L28: Passed | M28: 45986 | N28: HuyNLQ
A29: SCHED-017 | B29: Update schedule with empty name | C29: 1. Click "Edit" on existing schedule 2. Clear the "Schedule Name" field 3. Click "Save Changes" | D29: 1. Validation message "Schedule name is required" 2. Update blocked | E29: 1. Existing schedule available | F29: Passed | G29: 45928 | H29: HuyNLQ | I29: Passed | J29: 45960 | K29: TrungNVT | L29: Passed | M29: 45986 | N29: HuyNLQ
A30: SCHED-018 | B30: Update schedule with invalid time | C30: 1. Click "Edit" on existing schedule 2. Set end time before start time 3. Click "Save Changes" | D30: 1. Validation message "End time must be after start time" 2. Update blocked | E30: 1. Existing schedule available | F30: Passed | G30: 45928 | H30: HuyNLQ | I30: Passed | J30: 45960 | K30: TrungNVT | L30: Passed | M30: 45986 | N30: HuyNLQ
A31: SCHED-019 | B31: Update schedule with duplicate name | C31: 1. Click "Edit" on Schedule A 2. Change name to match Schedule B 3. Click "Save Changes" | D31: 1. API responds 409 (Conflict) 2. Error message "Schedule name already exists" | E31: 1. Two different schedules exist | F31: Passed | G31: 45928 | H31: HuyNLQ | I31: Passed | J31: 45960 | K31: TrungNVT | L31: Passed | M31: 45986 | N31: HuyNLQ
A32: SCHED-020 | B32: Update schedule with expired session | C32: 1. Click "Edit" on schedule 2. Manually clear authentication token 3. Click "Save Changes" | D32: 1. User redirected to login page 2. Message "Session expired" | E32: 1. Token removed/expired | F32: Passed | G32: 45928 | H32: HuyNLQ | I32: Passed | J32: 45960 | K32: TrungNVT | L32: Passed | M32: 45986 | N32: HuyNLQ
A33: SCHED-021 | B33: Update schedule with backend error | C33: 1. Click "Edit" on schedule 2. Make changes 3. Mock API to return 500 4. Click "Save Changes" | D33: 1. Error message "Failed to update schedule. Please try again" 2. Edit form remains open | E33: 1. Backend returns 500 error | F33: Passed | G33: 45928 | H33: HuyNLQ | I33: Passed | J33: 45960 | K33: TrungNVT | L33: Passed | M33: 45986 | N33: HuyNLQ
A34: SCHED-022 | B34: Update schedule preserving exceptions | C34: 1. Click "Edit" on schedule with exceptions 2. Change schedule name only 3. Click "Save Changes" | D34: 1. Schedule name updated 2. Existing exceptions preserved 3. No data loss | E34: 1. Schedule with existing exceptions | F34: Passed | G34: 45928 | H34: HuyNLQ | I34: Passed | J34: 45960 | K34: TrungNVT | L34: Passed | M34: 45986 | N34: HuyNLQ
A35: SCHED-023 | B35: Update schedule preserving time overrides | C35: 1. Click "Edit" on schedule with time overrides 2. Change effective dates only 3. Click "Save Changes" | D35: 1. Effective dates updated 2. Existing time overrides preserved 3. No data loss | E35: 1. Schedule with existing time overrides | F35: Passed | G35: 45928 | H35: HuyNLQ | I35: Passed | J35: 45960 | K35: TrungNVT | L35: Passed | M35: 45986 | N35: HuyNLQ
A36: SCHED-024 | B36: Update schedule with RRule change | C36: 1. Click "Edit" on schedule 2. Change RRule pattern 3. Click "Save Changes" | D36: 1. Success message "Schedule updated successfully" 2. New RRule applied 3. Schedule regenerated | E36: 1. Existing schedule available | F36: Passed | G36: 45928 | H36: HuyNLQ | I36: Passed | J36: 45960 | K36: TrungNVT | L36: Passed | M36: 45986 | N36: HuyNLQ
A37: SCHED-025 | B37: Update schedule with invalid effective dates | C37: 1. Click "Edit" on schedule 2. Set effective to before effective from 3. Click "Save Changes" | D37: 1. Validation message "Effective To must be after Effective From" 2. Update blocked | E37: 1. Existing schedule available | F37: Passed | G37: 45928 | H37: HuyNLQ | I37: Passed | J37: 45960 | K37: TrungNVT | L37: Passed | M37: 45986 | N37: HuyNLQ
A38: SCHED-026 | B38: Update schedule with concurrent modification | C38: 1. User A opens schedule for editing 2. User B opens same schedule for editing 3. User A saves changes 4. User B tries to save | D38: 1. User B gets conflict warning 2. Option to refresh and re-edit 3. Data integrity maintained | E38: 1. Two admin users logged in | F38: Failed | G38: 45928 | H38: HuyNLQ | I38: Passed | J38: 45960 | K38: TrungNVT | L38: Passed | M38: 45986 | N38: HuyNLQ
A39: SCHED-027 | B39: Update schedule with network interruption | C39: 1. Click "Edit" on schedule 2. Make changes 3. Simulate network interruption 4. Click "Save Changes" | D39: 1. Error message "Network error. Please try again" 2. Changes not lost 3. Retry option available | E39: 1. Network interruption simulated | F39: Passed | G39: 45928 | H39: HuyNLQ | I39: Passed | J39: 45960 | K39: TrungNVT | L39: Passed | M39: 45986 | N39: HuyNLQ
... A42: SCHED-030 | B42: Update schedule with invalid characters | C42: 1. Click "Edit" on schedule 2. Enter name with SQL injection chars 3. Click "Save Changes" | D42: 1. Validation message "Invalid characters detected" 2. Update blocked 3. Security maintained | E42: 1. Existing schedule available | F42: Failed | G42: 45928 | H42: HuyNLQ | I42: Passed | J42: 45960 | K42: TrungNVT | L42: Passed | M42: 45986 | N42: HuyNLQ
A43: View Schedule Detail
A44: SCHED-031 | B44: View schedule details successfully | C44: 1. Click "View Details" button on any schedule | D44: 1. Modal opens with complete schedule information 2. Shows name, type, times, RRule, effective dates 3. Displays exception dates and time overrides | E44: 1. Existing schedule available | F44: Passed | G44: 45928 | H44: HuyNLQ | I44: Passed | J44: 45960 | K44: TrungNVT | L44: Passed | M44: 45986 | N44: HuyNLQ
A45: SCHED-032 | B45: View schedule with no exceptions | C45: 1. Click "View Details" on schedule with no exceptions | D45: 1. Modal opens 2. Exception section shows "No exceptions" 3. All other details displayed correctly | E45: 1. Schedule with no exceptions exists | F45: Passed | G45: 45928 | H45: HuyNLQ | I45: Passed | J45: 45960 | K45: TrungNVT | L45: Passed | M45: 45986 | N45: HuyNLQ
A46: SCHED-033 | B46: View schedule with multiple exceptions | C46: 1. Click "View Details" on schedule with exceptions | D46: 1. Modal opens 2. All exception dates listed 3. Dates formatted correctly | E46: 1. Schedule with exceptions exists | F46: Passed | G46: 45928 | H46: HuyNLQ | I46: Passed | J46: 45960 | K46: TrungNVT | L46: Passed | M46: 45986 | N46: HuyNLQ
A47: SCHED-034 | B47: View schedule details with API error | C47: 1. Click "View Details" 2. Mock API to return 404 | D47: 1. Error message "Schedule not found" 2. Modal closes or shows error state | E47: 1. API returns 404 | F47: Passed | G47: 45928 | H47: HuyNLQ | I47: Passed | J47: 45960 | K47: TrungNVT | L47: Passed | M47: 45986 | N47: HuyNLQ
A48: SCHED-035 | B48: View schedule with time overrides | C48: 1. Click "View Details" on schedule with time overrides | D48: 1. Modal opens 2. Time overrides section shows all overrides 3. Override details displayed correctly | E48: 1. Schedule with time overrides exists | F48: Passed | G48: 45928 | H48: HuyNLQ | I48: Passed | J48: 45960 | K48: TrungNVT | L48: Passed | M48: 45986 | N48: HuyNLQ
A49: SCHED-036 | B49: View schedule with complex RRule | C49: 1. Click "View Details" on schedule with complex RRule | D49: 1. Modal opens 2. RRule displayed in readable format 3. Generated dates preview available | E49: 1. Schedule with complex RRule exists | F49: Passed | G49: 45928 | H49: HuyNLQ | I49: Passed | J49: 45960 | K49: TrungNVT | L49: Passed | M49: 45986 | N49: HuyNLQ
A50: SCHED-037 | B50: View schedule details modal close | C50: 1. Click "View Details" 2. Click "X" button to close modal | D50: 1. Modal closes 2. No data loss 3. Return to schedule list | E50: 1. Schedule details modal open | F50: Passed | G50: 45928 | H50: HuyNLQ | I50: Passed | J50: 45960 | K50: TrungNVT | L50: Passed | M50: 45986 | N50: HuyNLQ
A51: SCHED-038 | B51: View schedule with expired effective dates | C51: 1. Click "View Details" on expired schedule | D51: 1. Modal opens 2. Shows expired status 3. Effective dates highlighted as expired | E51: 1. Schedule with past effective dates | F51: Passed | G51: 45928 | H51: HuyNLQ | I51: Passed | J51: 45960 | K51: TrungNVT | L51: Passed | M51: 45986 | N51: HuyNLQ
A52: SCHED-039 | B52: View schedule with future effective dates | C52: 1. Click "View Details" on future schedule | D52: 1. Modal opens 2. Shows future status 3. Effective dates highlighted as future | E52: 1. Schedule with future effective dates | F52: Passed | G52: 45928 | H52: HuyNLQ | I52: Passed | J52: 45960 | K52: TrungNVT | L52: Passed | M52: 45986 | N52: HuyNLQ
A53: SCHED-040 | B53: View schedule details with slow loading | C53: 1. Click "View Details" 2. Simulate slow API response | D53: 1. Loading spinner shown 2. Details load when ready 3. No timeout errors | E53: 1. Slow API response simulated | F53: Passed | G53: 45928 | H53: HuyNLQ | I53: Passed | J53: 45960 | K53: TrungNVT | L53: Passed | M53: 45986 | N53: HuyNLQ
A54: SCHED-041 | B54: View schedule with malformed data | C54: 1. Click "View Details" 2. Mock API to return malformed data | D54: 1. Error message "Invalid data format" 2. Modal shows error state 3. Graceful error handling | E54: 1. API returns malformed data | F54: Failed | G54: 45928 | H54: HuyNLQ | I54: Passed | J54: 45960 | K54: TrungNVT | L54: Passed | M54: 45986 | N54: HuyNLQ
A55: SCHED-042 | B55: View schedule details accessibility | C55: 1. Click "View Details" 2. Navigate using keyboard only | D55: 1. All elements accessible via keyboard 2. Focus management works 3. Screen reader compatible | E55: 1. Keyboard navigation enabled | F55: Failed | G55: 45928 | H55: HuyNLQ | I55: Passed | J55: 45960 | K55: TrungNVT | L55: Passed | M55: 45986 | N55: HuyNLQ
... A58: SCHED-045 | B58: View schedule details copy data | C58: 1. Click "View Details" 2. Select and copy schedule information | D58: 1. Text selection works 2. Copy to clipboard successful 3. Data integrity maintained | E58: 1. Text selection enabled | F58: Passed | G58: 45928 | H58: HuyNLQ | I58: Passed | J58: 45960 | K58: TrungNVT | L58: Passed | M58: 45986 | N58: HuyNLQ
A59: View All Schedule
A60: SCHED-061 | B60: View all schedules successfully | C60: 1. Navigate to Schedule Management page 2. Ensure "Schedules" tab is active | D60: 1. All schedules displayed in list 2. Pagination works if >5 schedules 3. Each schedule shows name, type, times, status | E60: 1. Schedules exist in system | F60: Passed | G60: 45928 | H60: HuyNLQ | I60: Passed | J60: 45960 | K60: TrungNVT | L60: Passed | M60: 45986 | N60: HuyNLQ
A61: SCHED-062 | B61: Search schedules by name | C61: 1. Enter schedule name in search box 2. Press Enter or wait for auto-search | D61: 1. Only matching schedules displayed 2. Search is case-insensitive | E61: 1. Multiple schedules with different names exist | F61: Passed | G61: 45928 | H61: HuyNLQ | I61: Passed | J61: 45960 | K61: TrungNVT | L61: Passed | M61: 45986 | N61: HuyNLQ
A62: SCHED-063 | B62: Filter schedules by status | C62: 1. Select "Active Only" from filter dropdown | D62: 1. Only active schedules displayed 2. Inactive schedules hidden | E62: 1. Mix of active/inactive schedules exist | F62: Passed | G62: 45928 | H62: HuyNLQ | I62: Passed | J62: 45960 | K62: TrungNVT | L62: Passed | M62: 45986 | N62: HuyNLQ
A63: SCHED-064 | B63: Pagination with many schedules | C63: 1. Ensure >5 schedules exist 2. Navigate through pages | D63: 1. Shows 5 schedules per page 2. Pagination controls work correctly 3. Page numbers update correctly | E63: 1. >5 schedules exist | F63: Passed | G63: 45928 | H63: HuyNLQ | I63: Passed | J63: 45960 | K63: TrungNVT | L63: Passed | M63: 45986 | N63: HuyNLQ
A64: SCHED-065 | B64: View schedules with empty state | C64: 1. Navigate to Schedule Management 2. When no schedules exist | D64: 1. Shows "No schedules found" message 2. Create button still available | E64: 1. No schedules in system | F64: Passed | G64: 45928 | H64: HuyNLQ | I64: Passed | J64: 45960 | K64: TrungNVT | L64: Passed | M64: 45986 | N64: HuyNLQ
A65: SCHED-066 | B65: Search schedules with partial match | C65: 1. Enter partial schedule name 2. Wait for search results | D65: 1. All schedules containing search term displayed 2. Partial matches highlighted | E65: 1. Multiple schedules with similar names exist | F65: Passed | G65: 45928 | H65: HuyNLQ | I65: Passed | J65: 45960 | K65: TrungNVT | L65: Passed | M65: 45986 | N65: HuyNLQ
A66: SCHED-067 | B66: Filter schedules by type | C66: 1. Add schedule type filter 2. Select "School Day" type | D66: 1. Only school day schedules displayed 2. Other types hidden | E66: 1. Schedules with different types exist | F66: Failed | G66: 45928 | H66: HuyNLQ | I66: Passed | J66: 45960 | K66: TrungNVT | L66: Passed | M66: 45986 | N66: HuyNLQ
A67: SCHED-068 | B67: Sort schedules by name | C67: 1. Click on "Name" column header 2. Verify sorting order | D67: 1. Schedules sorted alphabetically 2. Sort direction indicated 3. Click again reverses order | E67: 1. Multiple schedules exist | F67: Failed | G67: 45928 | H67: HuyNLQ | I67: Passed | J67: 45960 | K67: TrungNVT | L67: Passed | M67: 45986 | N67: HuyNLQ
A68: SCHED-069 | B68: Sort schedules by effective date | C68: 1. Click on "Effective From" column header 2. Verify sorting order | D68: 1. Schedules sorted by effective date 2. Sort direction indicated 3. Click again reverses order | E68: 1. Multiple schedules with different effective dates exist | F68: Failed | G68: 45928 | H68: HuyNLQ | I68: Passed | J68: 45960 | K68: TrungNVT | L68: Passed | M68: 45986 | N68: HuyNLQ
A69: SCHED-070 | B69: View schedules with loading state | C69: 1. Navigate to Schedule Management 2. Simulate slow API response | D69: 1. Loading spinner displayed 2. Schedules load when ready 3. No timeout errors | E69: 1. Slow API response simulated | F69: Passed | G69: 45928 | H69: HuyNLQ | I69: Passed | J69: 45960 | K69: TrungNVT | L69: Passed | M69: 45986 | N69: HuyNLQ
A70: SCHED-071 | B70: View schedules with API error | C70: 1. Navigate to Schedule Management 2. Mock API to return 500 error | D70: 1. Error message "Failed to load schedules" 2. Empty state with error message 3. Retry button available | E70: 1. API returns 500 error | F70: Passed | G70: 45928 | H70: HuyNLQ | I70: Passed | J70: 45960 | K70: TrungNVT | L70: Passed | M70: 45986 | N70: HuyNLQ
A71: SCHED-072 | B71: View schedules responsive design | C71: 1. Navigate to Schedule Management 2. Resize browser window | D71: 1. Layout adapts to screen size 2. Content remains readable 3. No horizontal scroll | E71: 1. Responsive design enabled | F71: Passed | G71: 45928 | H71: HuyNLQ | I71: Passed | J71: 45960 | K71: TrungNVT | L71: Passed | M71: 45986 | N71: HuyNLQ
... A79: SCHED-080 | B79: View schedules with mixed languages | C79: 1. Navigate to Schedule Management 2. With schedules in different languages | D79: 1. All schedules displayed correctly 2. No encoding issues 3. Search works across languages | E79: 1. Schedules in multiple languages exist | F79: Passed | G79: 45928 | H79: HuyNLQ | I79: Passed | J79: 45960 | K79: TrungNVT | L79: Passed | M79: 45986 | N79: HuyNLQ
A80: Add Exception Date
A81: SCHED-081 | B81: Add valid exception date | C81: 1. Click "Manage Exceptions" on schedule 2. Select future date within effective range 3. Click "Add Exception" | D81: 1. Success message "Exception added successfully" 2. Date appears in exceptions list 3. Schedule updated | E81: 1. Existing schedule available | F81: Passed | G81: 45928 | H81: HuyNLQ | I81: Passed | J81: 45960 | K81: TrungNVT | L81: Passed | M81: 45986 | N81: HuyNLQ
A82: SCHED-082 | B82: Add exception date in the past | C82: 1. Click "Manage Exceptions" 2. Select yesterday's date 3. Click "Add Exception" | D82: 1. Validation message "Exception date cannot be in the past" 2. Exception not added | E82: 1. Schedule with effective date range | F82: Passed | G82: 45928 | H82: HuyNLQ | I82: Passed | J82: 45960 | K82: TrungNVT | L82: Passed | M82: 45986 | N82: HuyNLQ
A83: SCHED-083 | B83: Add exception date outside effective range | C83: 1. Click "Manage Exceptions" 2. Select date before effective from 3. Click "Add Exception" | D83: 1. Validation message "Date must be on or after Effective From" 2. Exception not added | E83: 1. Schedule with existing exceptions | F83: Passed | G83: 45928 | H83: HuyNLQ | I83: Passed | J83: 45960 | K83: TrungNVT | L83: Passed | M83: 45986 | N83: HuyNLQ
A84: SCHED-084 | B84: Add duplicate exception date | C84: 1. Click "Manage Exceptions" 2. Select date that already exists in exceptions 3. Click "Add Exception" | D84: 1. Validation message "This date is already an exception" 2. Exception not added | E84: 1. Schedule with existing exceptions | F84: Passed | G84: 45928 | H84: HuyNLQ | I84: Passed | J84: 45960 | K84: TrungNVT | L84: Passed | M84: 45986 | N84: HuyNLQ
A85: SCHED-085 | B85: Remove exception date | C85: 1. Click "Manage Exceptions" 2. Click "Remove" button next to existing exception 3. Confirm removal | D85: 1. Success message "Exception removed successfully" 2. Date removed from list | E85: 1. Schedule with existing exceptions | F85: Passed | G85: 45928 | H85: HuyNLQ | I85: Passed | J85: 45960 | K85: TrungNVT | L85: Passed | M85: 45986 | N85: HuyNLQ
A86: SCHED-086 | B86: Add exception date with API error | C86: 1. Click "Manage Exceptions" 2. Select valid date 3. Mock API to return 500 4. Click "Add Exception" | D86: 1. Error message "Failed to add exception" 2. Exception not added 3. Modal remains open | E86: 1. API returns 500 error | F86: Passed | G86: 45928 | H86: HuyNLQ | I86: Passed | J86: 45960 | K86: TrungNVT | L86: Passed | M86: 45986 | N86: HuyNLQ
A87: SCHED-087 | B87: Add multiple exception dates | C87: 1. Click "Manage Exceptions" 2. Add first exception date 3. Add second exception date 4. Verify both added | D87: 1. Both dates appear in list 2. Success messages for each 3. Schedule updated correctly | E87: 1. Existing schedule available | F87: Passed | G87: 45928 | H87: HuyNLQ | I87: Passed | J87: 45960 | K87: TrungNVT | L87: Passed | M87: 45986 | N87: HuyNLQ
A88: SCHED-088 | B88: Add exception date with network timeout | C88: 1. Click "Manage Exceptions" 2. Select valid date 3. Simulate network timeout 4. Click "Add Exception" | D88: 1. Error message "Request timeout" 2. Exception not added 3. Retry option available | E88: 1. Network timeout simulated | F88: Passed | G88: 45928 | H88: HuyNLQ | I88: Passed | J88: 45960 | K88: TrungNVT | L88: Passed | M88: 45986 | N88: HuyNLQ
A89: SCHED-089 | B89: Add exception date with expired session | C89: 1. Click "Manage Exceptions" 2. Select valid date 3. Session expires 4. Click "Add Exception" | D89: 1. User redirected to login 2. Message "Session expired" 3. No data loss | E89: 1. Session timeout configured | F89: Passed | G89: 45928 | H89: HuyNLQ | I89: Passed | J89: 45960 | K89: TrungNVT | L89: Passed | M89: 45986 | N89: HuyNLQ
A90: SCHED-090 | B90: Add exception date with invalid format | C90: 1. Click "Manage Exceptions" 2. Manually enter invalid date format 3. Click "Add Exception" | D90: 1. Validation message "Invalid date format" 2. Exception not added 3. Date picker resets | E90: 1. Existing schedule available | F90: Passed | G90: 45928 | H90: HuyNLQ | I90: Passed | J90: 45960 | K90: TrungNVT | L90: Passed | M90: 45986 | N90: HuyNLQ
A91: SCHED-091 | B91: Add exception date on weekend | C91: 1. Click "Manage Exceptions" 2. Select Saturday date 3. Click "Add Exception" | D91: 1. Success message "Exception added successfully" 2. Weekend date added correctly 3. No special restrictions | E91: 1. Existing schedule available | F91: Passed | G91: 45928 | H91: HuyNLQ | I91: Passed | J91: 45960 | K91: TrungNVT | L91: Passed | M91: 45986 | N91: HuyNLQ
A92: SCHED-092 | B92: Add exception date on holiday | C92: 1. Click "Manage Exceptions" 2. Select holiday date 3. Click "Add Exception" | D92: 1. Success message "Exception added successfully" 2. Holiday date added correctly 3. No special restrictions | E92: 1. Existing schedule available | F92: Passed | G92: 45928 | H92: HuyNLQ | I92: Passed | J92: 45960 | K92: TrungNVT | L92: Passed | M92: 45986 | N92: HuyNLQ
... A100: SCHED-100 | B100: Add exception date with undo functionality | C100: 1. Click "Manage Exceptions" 2. Add exception date 3. Click "Undo" button | D100: 1. Exception removed from list 2. Success message "Exception removed" 3. Undo functionality works | E100: 1. Existing schedule available | F100: Failed | G100: 45928 | H100: HuyNLQ | I100: Passed | J100: 45960 | K100: TrungNVT | L100: Passed | M100: 45986 | N100: HuyNLQ
A101: Add Time Overrides
A102: SCHED-101 | B102: Add valid time override | C102: 1. Click "Time Overrides" on schedule 2. Click "Add Time Override" 3. Fill date, start/end time, reason 4. Click "Save" | D102: 1. Success message "Time override added successfully" 2. Override appears in list 3. Modal closes | E102: Existing schedule available | F102: Passed | G102: 45928 | H102: HuyNLQ | I102: Passed | J102: 45960 | K102: TrungNVT | L102: Passed | M102: 45986 | N102: HuyNLQ
A103: SCHED-102 | B103: Add time override with invalid time | C103: 1. Click "Add Time Override" 2. Set end time before start time 3. Fill other fields 4. Click "Save" | D103: 1. Validation message "End time must be after start time" 2. Override not added | E103: None | F103: Passed | G103: 45928 | H103: HuyNLQ | I103: Passed | J103: 45960 | K103: TrungNVT | L103: Passed | M103: 45986 | N103: HuyNLQ
A104: SCHED-103 | B104: Add time override with missing reason | C104: 1. Click "Add Time Override" 2. Fill date and times 3. Leave reason field empty 4. Click "Save" | D104: 1. Validation message "Reason is required" 2. Override not added | E104: None | F104: Passed | G104: 45928 | H104: HuyNLQ | I104: Passed | J104: 45960 | K104: TrungNVT | L104: Passed | M104: 45986 | N104: HuyNLQ
A105: SCHED-104 | B105: Add time override for exception date | C105: 1. Click "Add Time Override" 2. Select "Exception Override" type 3. Choose existing exception date 4. Fill times and reason 5. Click "Save" | D105: 1. Success message "Time override added successfully" 2. Override linked to exception date | E105: 1. Schedule with existing exceptions | F105: Passed | G105: 45928 | H105: HuyNLQ | I105: Passed | J105: 45960 | K105: TrungNVT | L105: Passed | M105: 45986 | N105: HuyNLQ
A106: SCHED-105 | B106: Edit existing time override | C106: 1. Click "Time Overrides" 2. Click "Edit" on existing override 3. Modify times and reason 4. Click "Save" | D106: 1. Success message "Time override updated successfully" 2. Changes reflected in list | E106: 1. Schedule with existing time overrides | F106: Passed | G106: 45928 | H106: HuyNLQ | I106: Passed | J106: 45960 | K106: TrungNVT | L106: Passed | M106: 45986 | N106: HuyNLQ
A107: SCHED-106 | B107: Delete time override | C107: 1. Click "Time Overrides" 2. Click "Delete" on existing override 3. Confirm deletion | D107: 1. Success message "Time override deleted successfully" 2. Override removed from list | E107: 1. Schedule with existing time overrides | F107: Passed | G107: 45928 | H107: HuyNLQ | I107: Passed | J107: 45960 | K107: TrungNVT | L107: Passed | M107: 45986 | N107: HuyNLQ
A108: SCHED-107 | B108: Add time override with backend error | C108: 1. Click "Add Time Override" 2. Fill valid data 3. Mock API to return 500 4. Click "Save" | D108: 1. Error message "Failed to save time override" 2. Modal remains open | E108: 1. Backend returns 500 error | F108: Passed | G108: 45928 | H108: HuyNLQ | I108: Passed | J108: 45960 | K108: TrungNVT | L108: Passed | M108: 45986 | N108: HuyNLQ
A109: SCHED-108 | B109: Add time override with same start/end time | C109: 1. Click "Add Time Override" 2. Set start time: 08:00 3. Set end time: 08:00 4. Fill other fields 5. Click "Save" | D109: 1. Validation message "End time must be after start time" 2. Override not added | E109: None | F109: Passed | G109: 45928 | H109: HuyNLQ | I109: Passed | J109: 45960 | K109: TrungNVT | L109: Passed | M109: 45986 | N109: HuyNLQ
A110: SCHED-109 | B110: Add time override with very long reason | C110: 1. Click "Add Time Override" 2. Enter reason with 500+ characters 3. Fill other fields 4. Click "Save" | D110: 1. Success message "Time override added successfully" 2. Long reason saved correctly | E110: None | F110: Passed | G110: 45928 | H110: HuyNLQ | I110: Passed | J110: 45960 | K110: TrungNVT | L110: Passed | M110: 45986 | N110: HuyNLQ
A111: SCHED-110 | B111: Add time override with special characters | C111: 1. Click "Add Time Override" 2. Enter reason with special characters 3. Fill other fields 4. Click "Save" | D111: 1. Success message "Time override added successfully" 2. Special characters handled correctly | E111: None | F111: Passed | G111: 45928 | H111: HuyNLQ | I111: Passed | J111: 45960 | K111: TrungNVT | L111: Passed | M111: 45986 | N111: HuyNLQ
A112: SCHED-111 | B112: Add time override with past date | C112: 1. Click "Add Time Override" 2. Select yesterday's date 3. Fill other fields 4. Click "Save" | D112: 1. Validation message "Override date cannot be in the past" 2. Override not added | E112: None | F112: Passed | G112: 45928 | H112: HuyNLQ | I112: Passed | J112: 45960 | K112: TrungNVT | L112: Passed | M112: 45986 | N112: HuyNLQ
A113: SCHED-112 | B113: Add time override with future date | C113: 1. Click "Add Time Override" 2. Select date 1 year in future 3. Fill other fields 4. Click "Save" | D113: 1. Success message "Time override added successfully" 2. Future date handled correctly | E113: None | F113: Passed | G113: 45928 | H113: HuyNLQ | I113: Passed | J113: 45960 | K113: TrungNVT | L113: Passed | M113: 45986 | N113: HuyNLQ
... A126: SCHED-125 | B126: Add time override with export functionality | C126: 1. Click "Time Overrides" 2. Add several overrides 3. Click "Export" button | D126: 1. Export file generated 2. All overrides included 3. File format correct | E126: 1. Schedule with time overrides exists | F126: Failed | G126: 45928 | H126: HuyNLQ | I126: Passed | J126: 45960 | K126: TrungNVT | L126: Passed | M126: 45986 | N126: HuyNLQ
A127: Intergration Test
A128: SCHED-126 | B128: Complete schedule workflow | C128: 1. Create new schedule 2. Add exception dates 3. Add time overrides 4. Edit schedule details 5. View final result | D128: 1. All operations successful 2. Final schedule shows all modifications 3. Data consistency maintained | E128: 1. User logged in as admin | F128: Passed | G128: 45928 | H128: HuyNLQ | I128: Passed | J128: 45960 | K128: TrungNVT | L128: Passed | M128: 45986 | N128: HuyNLQ
A129: SCHED-127 | B129: Schedule with complex RRule | C129: 1. Create schedule with custom RRule 2. Set complex recurrence pattern 3. Preview generated dates 4. Save schedule | D129: 1. RRule validation passes 2. Preview shows correct dates 3. Schedule created successfully | E129: None | F129: Passed | G129: 45928 | H129: HuyNLQ | I129: Passed | J129: 45960 | K129: TrungNVT | L129: Passed | M129: 45986 | N129: HuyNLQ
A130: SCHED-128 | B130: Multiple users editing same schedule | C130: 1. User A opens schedule for editing 2. User B opens same schedule for editing 3. User A saves changes 4. User B tries to save | D130: 1. User B gets conflict warning 2. Option to refresh and re-edit 3. Data integrity maintained | E130: 1. Two admin users logged in | F130: Passed | G130: 45928 | H130: HuyNLQ | I130: Failed | J130: 45960 | K130: TrungNVT | L130: Passed | M130: 45986 | N130: HuyNLQ
A131: SCHED-129 | B131: Schedule with all features combined | C131: 1. Create schedule with RRule 2. Add multiple exception dates 3. Add multiple time overrides 4. Edit schedule details 5. View complete schedule | D131: 1. All features work together 2. Data consistency maintained 3. Performance remains good | E131: 1. User logged in as admin | F131: Passed | G131: 45928 | H131: HuyNLQ | I131: Passed | J131: 45960 | K131: TrungNVT | L131: Passed | M131: 45986 | N131: HuyNLQ
A132: SCHED-130 | B132: Schedule with data migration | C132: 1. Create schedule in old format 2. Migrate to new format 3. Verify all data preserved 4. Test all functions | D132: 1. Migration successful 2. All data preserved 3. All functions work correctly | E132: 1. Old format schedule exists | F132: Failed | G132: 45928 | H132: HuyNLQ | I132: Passed | J132: 45960 | K132: TrungNVT | L132: Passed | M132: 45986 | N132: HuyNLQ
A133: SCHED-131 | B133: Schedule with backup and restore | C133: 1. Create schedule with data 2. Backup schedule data 3. Delete schedule 4. Restore from backup 5. Verify data integrity | D133: 1. Backup successful 2. Restore successful 3. All data preserved 4. Functions work correctly | E133: 1. User logged in as admin | F133: Failed | G133: 45928 | H133: HuyNLQ | I133: Failed | J133: 45960 | K133: TrungNVT | L133: Passed | M133: 45986 | N133: HuyNLQ
A134: SCHED-132 | B134: Schedule with performance testing | C134: 1. Create 1000+ schedules 2. Add exceptions and overrides 3. Test all CRUD operations 4. Measure performance | D134: 1. All operations complete within acceptable time 2. No memory leaks 3. UI remains responsive | E134: 1. Large dataset available | F134: Passed | G134: 45928 | H134: HuyNLQ | I134: Passed | J134: 45960 | K134: TrungNVT | L134: Passed | M134: 45986 | N134: HuyNLQ
...

Sheet Vehicle Management
A2: Feature | B2: Verifies the complete vehicle management flow—including registering, editing, assigning, monitoring, and deactivating vehicles—covering input validation, operational constraints, assignment consistency, safety parameters, and role-based permissions. | R2: Passed
A3: Test requirement | B3: Tracks and maintains vehicle details, capacity, documents, and operational status. | R3: Failed
A4: Number of TCs | B4: =COUNTA(A12:A897)-6 -> 27 | R4: Pending
A5: Testing Round | B5: Passed | C5: Failed | D5: Pending | E5: N/A | R5: N/A
A6: Round 1 | B6: =COUNTIF($F10:$F895,B5) -> 23 | C6: =COUNTIF($F10:$F895,C5) -> 2 | D6: =COUNTIF($F10:$F895,D5) -> 2 | E6: =COUNTIF($F10:$F895,E5) -> 0
A7: Round 2 | B7: =COUNTIF($I10:$I895,B5) -> 25 | C7: =COUNTIF($I10:$FI895,C5) -> 3 | D7: =COUNTIF($F10:$F895,D5) -> 2 | E7: =COUNTIF($F10:$F895,E5) -> 0
A8: Round 3 | B8: =COUNTIF($L10:$L895,B5) -> 22 | C8: =COUNTIF($L10:$L895,C5) -> 3 | D8: =COUNTIF($F10:$F895,D5) -> 2 | E8: =COUNTIF($F10:$F895,E5) -> 0
A10: Test Case ID | B10: Test Case Description | C10: Test Case Procedure | D10: Expected Results | E10: Pre-conditions | F10: Round 1 | G10: Test date | H10: Tester | I10: Round 2 | J10: Test date | K10: Tester | L10: Round 3 | M10: Test date | N10: Tester | O10: Note
A11: Create vehicle
A12: VEH-001 | B12: Test creating a new vehicle with all valid information | C12: 1.Login as admin 2.Navigate to Vehicle Management 3.Click "Create Vehicle" 4. Fill license plate "30H-12345" 5.Select capacity "16 seats" 6.Select status "Active" 7.Click "Create Vehicle" | D12: 1.Success message appears 2.Vehicle created successfully 3.Redirected to vehicle list | E12: 1. Admin session active | F12: Passed | G12: 45928 | H12: NguyetNTT | I12: Passed | J12: 45960 | K12: NhiPTK | L12: Failed | M12: 45986 | N12: NguyetNTT
A13: VEH-002 | B13: Test validation for incorrect license plate format | C13: 1.Login as admin 2.Navigate to Vehicle Management 3.Enter license plate "ABC123" 4.Fill other valid fields. 5.Click "Create Vehicle" | D13: 1. Validation message "Invalid Vietnam license plate format" | E13: None | F13: Passed | G13: 45928 | H13: NguyetNTT | I13: Passed | J13: 45960 | K13: NhiPTK | L13: Passed | M13: 45986 | N13: NguyetNTT
A14: VEH-003 | B14: Test creating vehicle with existing license plate | C14: 1.Login as admin 2.Create vehicle with license plate "30H-12345" 3.Try to create another vehicle with same license plate | D14: 1.API responds with error 2.Error message displayed | E14: 1. Vehicle with license plate "30H-12345" exists | F14: Failed | G14: 45928 | H14: NguyetNTT | I14: Passed | J14: 45960 | K14: NhiPTK | L14: Passed | M14: 45986 | N14: NguyetNTT
A15: VEH-004 | B15: Test validation for required license plate field | C15: 1.Login as admin 2.Navigate to Create Vehicle 3.Leave license plate empty 4.Fill other fields 5.Click "Create Vehicle" | D15: 1. Validation message "License plate is required" | E15: None | F15: Passed | G15: 45928 | H15: NguyetNTT | I15: Passed | J15: 45960 | K15: NhiPTK | L15: Passed | M15: 45986 | N15: NguyetNTT
A16: VEH-005 | B16: Test validation for capacity field | C16: 1.Login as admin 2.Navigate to Create Vehicle 3. Enter capacity 0 4.Fill other valid fields 5.Click "Create Vehicle" | D16: 1. Validation message "Capacity must be greater than 0" | E16: None | F16: Passed | G16: 45928 | H16: NguyetNTT | I16: Passed | J16: 45960 | K16: NhiPTK | L16: Passed | M16: 45986 | N16: NguyetNTT
A17: VEH-006 | B17: Test creating vehicle with expired admin session | C17: 1.Login as admin 2.Clear auth token manually 3. Try to create vehicle | D17: 1.User redirected to login page 2.Message "Session expired" | E17: 1. Token removed/expired | F17: Passed | G17: 45928 | H17: NguyetNTT | I17: Passed | J17: 45960 | K17: NhiPTK | L17: Passed | M17: 45986 | N17: NguyetNTT
A18: VEH-007 | B18: Test creating vehicle when API is down | C18: 1.Login as admin 2.Stop API server 3. Try to create vehicle | D18: 1. Error toast "Service unavailable, try later" | E18: 1. Backend offline | F18: Failed | G18: 45928 | H18: NguyetNTT | I18: Passed | J18: 45960 | K18: NhiPTK | L18: Passed | M18: 45986 | N18: NguyetNTT
A19: Update vehicle
A20: VEH-008 | B20: Test updating existing vehicle information | C20: 1.Login as admin 2.Navigate to Vehicle Management 3.Click edit on existing vehicle 4.Change capacity to "24 seats" 5.Click "Update Vehicle" | D20: 1.Success message appears 2.Vehicle updated successfully | E20: 1. Active session 2.Existing vehicle | F20: Passed | G20: 45928 | H20: NguyetNTT | I20: Passed | J20: 45960 | K20: NhiPTK | L20: Passed | M20: 45986 | N20: NguyetNTT
A21: VEH-009 | B21: Test updating vehicle with invalid license plate format | C21: 1.Login as admin 2.Edit existing vehicle 3.Change license plate to "INVALID123" 4.Click "Update Vehicle" | D21: 1. Validation message "Invalid Vietnam license plate format" | E21: 1. Existing vehicle | F21: Passed | G21: 45928 | H21: NguyetNTT | I21: Passed | J21: 45960 | K21: NhiPTK | L21: Passed | M21: 45986 | N21: NguyetNTT
A22: VEH-010 | B22: Test updating vehicle that doesn't exist | C22: 1.Login as admin 2.Navigate to update URL with invalid vehicle ID | D22: 1.API returns 404 2.Error message "Vehicle not found" | E22: 1. Invalid vehicle ID | F22: Passed | G22: 45928 | H22: NguyetNTT | I22: Passed | J22: 45960 | K22: NhiPTK | L22: Passed | M22: 45986 | N22: NguyetNTT
A23: VEH-011 | B23: Test updating vehicle with expired session | C23: 1.Login as admin 2.Clear auth token 3.Try to update vehicle | D23: 1. User redirected to login page | E23: 1. Token removed/expired | F23: Passed | G23: 45928 | H23: NguyetNTT | I23: Passed | J23: 45960 | K23: NhiPTK | L23: Passed | M23: 45986 | N23: NguyetNTT
A24: Delete Vehicle
A25: VEH-012 | B25: Test deleting an existing vehicle | C25: 1.Login as admin 2.Navigate to Vehicle Management 3.Click delete on vehicle 4.Confirm deletion | D25: 1.Confirmation modal appears 2.Vehicle deleted successfully 3.Removed from list | E25: 1. Active session 2.Existing vehicle | F25: Passed | G25: 45928 | H25: NguyetNTT | I25: Passed | J25: 45960 | K25: NhiPTK | L25: Passed | M25: 45986 | N25: NguyetNTT
A26: VEH-013 | B26: Test deleting vehicle that doesn't exist | C26: 1.Login as admin 2.Try to delete with invalid vehicle ID | D26: 1.API returns 404 2.Error message "Vehicle not found" | E26: 1. Invalid vehicle ID | F26: Passed | G26: 45928 | H26: NguyetNTT | I26: Passed | J26: 45960 | K26: NhiPTK | L26: Passed | M26: 45986 | N26: NguyetNTT
A27: VEH-014 | B27: Test deleting vehicle with expired session | C27: 1.Login as admin 2.Clear auth token 3.Try to delete vehicle | D27: 1. User redirected to login page | E27: 1. Token removed/expired | F27: Passed | G27: 45928 | H27: NguyetNTT | I27: Passed | J27: 45960 | K27: NhiPTK | L27: Passed | M27: 45986 | N27: NguyetNTT
A28: View vehicle list
A29: VEH-015 | B29: Test viewing vehicle list with pagination | C29: 1.Login as admin 2.Navigate to Vehicle Management 3.Check pagination controls | D29: 1.Vehicle list displays 2.Pagination works correctly | E29: 1.Active session 2.Multiple vehicles exist | F29: Passed | G29: 45928 | H29: NguyetNTT | I29: Passed | J29: 45960 | K29: NhiPTK | L29: Failed | M29: 45986 | N29: NguyetNTT
A30: VEH-016 | B30: Test filtering vehicles by status | C30: 1.Login as admin 2.Navigate to Vehicle Management 3.Select "Active" from status filter | D30: 1. Only active vehicles displayed | E30: 1. Vehicles with different statuses exist | F30: Passed | G30: 45928 | H30: NguyetNTT | I30: Passed | J30: 45960 | K30: NhiPTK | L30: Passed | M30: 45986 | N30: NguyetNTT
A31: VEH-017 | B31: Test searching vehicles by license plate | C31: 1.Login as admin 2.Navigate to Vehicle Management 3.Enter license plate in search box | D31: 1. Matching vehicles displayed | E31: 1. Vehicles with known license plates exist | F31: Passed | G31: 45928 | H31: NguyetNTT | I31: Passed | J31: 45960 | K31: NhiPTK | L31: Passed | M31: 45986 | N31: NguyetNTT
A32: VEH-018 | B32: Test searching vehicles with no results | C32: 1.Login as admin 2.Navigate to Vehicle Management 3.Enter "ZZZ-99999" in search box | D32: 1. "No vehicles found" message displayed | E32: 1. No vehicle with "ZZZ-99999" exists | F32: Passed | G32: 45928 | H32: NguyetNTT | I32: Passed | J32: 45960 | K32: NhiPTK | L32: Passed | M32: 45986 | N32: NguyetNTT
A33: VEH-019 | B33: Test combining status filter with search | C33: 1.Login as admin 2.Navigate to Vehicle Management 3.Select "Maintenance" status and search "30H" | D33: 1. Only maintenance vehicles with "30H" displayed | E33: 1. Maintenance vehicles with "30H" exist | F33: Passed | G33: 45928 | H33: NguyetNTT | I33: Passed | J33: 45960 | K33: NhiPTK | L33: Passed | M33: 45986 | N33: NguyetNTT
A34: VEH-020 | B34: Test searching vehicles with spaces in search term | C34: 1.Login as admin 2.Navigate to Vehicle Management 3.Enter " 30H-12345 " in search box | D34: 1. Vehicle with "30H-12345" displayed (spaces ignored) | E34: 1. Vehicle with "30H-12345" exists | F34: Passed | G34: 45928 | H34: NguyetNTT | I34: Passed | J34: 45960 | K34: NhiPTK | L34: Passed | M34: 45986 | N34: NguyetNTT
A35: VEH-021 | B35: Test searching vehicles with special characters only | C35: 1.Login as admin 2.Navigate to Vehicle Management 3.Enter "@#$%" in search box | D35: 1. "No vehicles found" message displayed | E35: 1. No vehicles with special characters exist | F35: Passed | G35: 45928 | H35: NguyetNTT | I35: Passed | J35: 45960 | K35: NhiPTK | L35: Passed | M35: 45986 | N35: NguyetNTT
A36: View vehicle detail
A37: VEH-022 | B37: Test filtering vehicles by status | C37: 1.Login as admin 2.Navigate to Vehicle Management 3.Click on vehicle row | D37: 1.Vehicle details displayed 2.All information shown correctly | E37: 1.Active session 2.Existing vehicle | F37: Passed | G37: 45928 | H37: NguyetNTT | I37: Passed | J37: 45960 | K37: NhiPTK | L37: Passed | M37: 45986 | N37: NguyetNTT
A38: Assign driver
A39: VEH-023 | B39: Test assigning a driver to vehicle | C39: 1.Login as admin 2.Navigate to Vehicle Management 3.Click assign driver button 4.Select available driver 5.Click "Assign Driver" | D39: 1.Driver assignment modal opens 2.Available drivers listed 3.Assignment successful | E39: 1.Available drivers exist | F39: Pending | G39: 45928 | H39: NguyetNTT | I39: Pending | J39: 45960 | K39: NhiPTK | L39: Pending | M39: 45986 | N39: NguyetNTT
A40: VEH-024 | B40: Test assigning driver with scheduling conflicts | C40: 1.Login as admin 2.Try to assign driver already assigned to another vehicle | D40: 1.Conflict detection 2.Error message about conflicts | E40: 1. Driver already assigned to another vehicle | F40: Passed | G40: 45928 | H40: NguyetNTT | I40: Passed | J40: 45960 | K40: NhiPTK | L40: Passed | M40: 45986 | N40: NguyetNTT
A41: Partial Update Vehicle
A42: VEH-025 | B42: Test partial update of vehicle license plate only | C42: 1.Login as admin 2.Navigate to Vehicle Management 3.Click edit on existing vehicle 4.Change only license plate to "43A-54321" 5.Click "Update Vehicle" | D42: 1.Success message appears 2.Only license plate updated 3.Other fields remain unchanged | E42: 1. Existing vehicle | F42: Passed | G42: 45928 | H42: NguyetNTT | I42: Passed | J42: 45960 | K42: NhiPTK | L42: Passed | M42: 45986 | N42: NguyetNTT
A43: VEH-026 | B43: Test partial update of vehicle capacity only | C43: 1.Login as admin 2.Navigate to Vehicle Management 3.Click edit on existing vehicle 4.Change only capacity to "32 seats" 5.Click "Update Vehicle" | D43: 1.Success message appears 2.Only capacity updated 3.Other fields remain unchanged | E43: 1. Existing vehicle | F43: Passed | G43: 45928 | H43: NguyetNTT | I43: Passed | J43: 45960 | K43: NhiPTK | L43: Failed | M43: 45986 | N43: NguyetNTT
A44: VEH-027 | B44: Test partial update of vehicle status only | C44: 1.Login as admin 2.Navigate to Vehicle Management 3.Click edit on existing vehicle 4.Change only status to "Maintenance" 5.Click "Update Vehicle" | D44: 1.Success message appears 2.Only status updated 3.Other fields remain unchanged | E44: 1. Existing vehicle | F44: Pending | G44: 45928 | H44: NguyetNTT | I44: Pending | J44: 45960 | K44: NhiPTK | L44: Pending | M44: 45986 | N44: NguyetNTT

Sheet Route Management
A2: Feature | B2: Route Management | R2: Passed
A3: Test requirement | B3: Verifies the complete route management flow—including creating, editing, sequencing, and deactivating bus routes—covering input validation, geolocation logic, stop ordering, dependency checks, and role-based permissions. | R3: Failed
A4: Number of TCs | B4: =COUNTA(A12:A923)-6 -> 54 | R4: Pending
A5: Testing Round | B5: Passed | C5: Failed | D5: Pending | E5: N/A | R5: N/A
A6: Round 1 | B6: =COUNTIF($F10:$F921,B5) -> 50 | C6: =COUNTIF($F10:$F921,C5) -> 4 | D6: =COUNTIF($F10:$F921,D5) -> 0 | E6: =COUNTIF($F10:$F921,E5) -> 0
A7: Round 2 | B7: =COUNTIF($I10:$I895,B5) -> 53 | C7: =COUNTIF($I10:$FI895,C5) -> 1 | D7: =COUNTIF($F10:$F921,D5) -> 0 | E7: =COUNTIF($F10:$F921,E5) -> 0
A8: Round 3 | B8: =COUNTIF($L10:$L895,B5) -> 54 | C8: =COUNTIF($L10:$L895,C5) -> 0 | D8: =COUNTIF($F10:$F921,D5) -> 0 | E8: =COUNTIF($F10:$F921,E5) -> 0
A10: Test Case ID | B10: Test Case Description | C10: Test Case Procedure | D10: Expected Results | E10: Pre-conditions | F10: Round 1 | G10: Test date | H10: Tester | I10: Round 2 | J10: Test date | K10: Tester | L10: Round 3 | M10: Test date | N10: Tester | O10: Note
A11: CREATE_ROUTE
A12: RT-002 | B12: Test validation for empty route name | C12: 1. Login as admin 2. Navigate to Route Management 3. Click "Create Route" 4. Leave route name empty 5. Select vehicle 6. Add pickup points 7. Click "Create Route" | D12: 1. Validation message "Route name is required" 2. Route not created 3. Form stays on create page | E12: None | F12: Failed | G12: 45928 | H12: HuyNLQ | I12: Passed | J12: 45960 | K12: NhiPTK | L12: Passed | M12: 45986 | N12: NhiPTK
A13: RT-003 | B13: Test validation for route name exceeding 200 characters | C13: 1. Login as admin 2. Navigate to Route Management 3. Click "Create Route" 4. Fill route name with 201 characters 5. Select vehicle 6. Add pickup points 7. Click "Create Route" | D13: 1. Validation message "Route name cannot exceed 200 characters" 2. Route not created | E13: None | F13: Passed | G13: 45928 | H13: HuyNLQ | I13: Passed | J13: 45960 | K13: NhiPTK | L13: Passed | M13: 45986 | N13: NhiPTK
A14: RT-004 | B14: Test creating route without selecting vehicle | C14: 1. Login as admin 2. Navigate to Route Management 3. Click "Create Route" 4. Fill route name 5. Do not select vehicle 6. Add pickup points 7. Click "Create Route" | D14: 1. Validation message "Vehicle ID is required" 2. Route not created | E14: None | F14: Passed | G14: 45928 | H14: HuyNLQ | I14: Failed | J14: 45960 | K14: NhiPTK | L14: Passed | M14: 45986 | N14: NhiPTK
A15: RT-005 | B15: Test creating route with vehicle already assigned to another active route | C15: 1. Login as admin 2. Navigate to Route Management 3. Click "Create Route" 4. Fill route name "Route B" 5. Select vehicle "30H-12345" (already in use) 6. Add pickup points 7. Click "Create Route" | D15: 1. Error message "Vehicle with license plate '30H-12345' is already used in other active routes" 2. Route not created | E15: 1. Vehicle "30H-12345" already assigned to active Route A | F15: Passed | G15: 45928 | H15: HuyNLQ | I15: Passed | J15: 45960 | K15: NhiPTK | L15: Passed | M15: 45986 | N15: NhiPTK
A16: RT-006 | B16: Test creating route with inactive vehicle | C16: 1. Login as admin 2. Navigate to Route Management 3. Click "Create Route" 4. Fill route name 5. Select inactive vehicle "30H-99999" 6. Add pickup points 7. Click "Create Route" | D16: 1. Error message "Vehicle with ID {id} does not exist or is not active" 2. Route not created | E16: 1. Vehicle "30H-99999" exists but inactive | F16: Failed | G16: 45928 | H16: HuyNLQ | I16: Passed | J16: 45960 | K16: NhiPTK | L16: Passed | M16: 45986 | N16: NhiPTK
A17: RT-007 | B17: Test creating route with pickup points not assigned to active students | C17: 1. Login as admin 2. Navigate to Route Management 3. Click "Create Route" 4. Fill route name 5. Select vehicle 6. Add pickup point without active students 7. Click "Create Route" | D17: 1. Error message "The following pickup points are not assigned to active students: {pickupPointId}" 2. Route not created | E17: 1. Pickup point exists but has no active students | F17: Passed | G17: 45928 | H17: HuyNLQ | I17: Passed | J17: 45960 | K17: NhiPTK | L17: Passed | M17: 45986 | N17: NhiPTK
A18: RT-008 | B18: Test creating route with pickup point already used in another active route | C18: 1. Login as admin 2. Navigate to Route Management 3. Click "Create Route" 4. Fill route name "Route C" 5. Select vehicle 6. Add pickup point already in Route A 7. Click "Create Route" | D18: 1. Error message "The following pickup points are already used in other active routes: Route '{route_name}' already uses pickup point {id}" 2. Route not created | E18: 1. Pickup point already assigned to active Route A | F18: Passed | G18: 45928 | H18: HuyNLQ | I18: Passed | J18: 45960 | K18: NhiPTK | L18: Passed | M18: 45986 | N18: NhiPTK
A19: RT-009 | B19: Test creating route with duplicate sequence orders | C19: 1. Login as admin 2. Navigate to Route Management 3. Click "Create Route" 4. Fill route name 5. Select vehicle 6. Add 3 pickup points with sequence orders: 1, 1, 2 7. Click "Create Route" | D19: 1. Error message "Duplicate sequence orders found: 1" 2. Route not created | E19: 1. At least 3 valid pickup points available | F19: Passed | G19: 45928 | H19: HuyNLQ | I19: Passed | J19: 45960 | K19: NhiPTK | L19: Passed | M19: 45986 | N19: NhiPTK
A20: RT-010 | B20: Test creating route with zero or negative sequence order | C20: 1. Login as admin 2. Navigate to Route Management 3. Click "Create Route" 4. Fill route name 5. Select vehicle 6. Add pickup point with sequence order 0 7. Click "Create Route" | D20: 1. Validation message "Sequence order must be a positive number" 2. Route not created | E20: None | F20: Passed | G20: 45928 | H20: HuyNLQ | I20: Passed | J20: 45960 | K20: NhiPTK | L20: Passed | M20: 45986 | N20: NhiPTK
A21: RT-011 | B21: Test creating route with schedule (valid dates) | C21: 1. Login as admin 2. Navigate to Route Management 3. Click "Create Route" 4. Fill route name, vehicle, pickup points 5. Add schedule with EffectiveFrom = tomorrow, EffectiveTo = next week 6. Click "Create Route" | D21: 1. Success message appears 2. Route and RouteSchedule created 3. Schedule properly linked to route | E21: 1. Valid schedule exists in system | F21: Passed | G21: 45928 | H21: HuyNLQ | I21: Passed | J21: 45960 | K21: NhiPTK | L21: Passed | M21: 45986 | N21: NhiPTK
A22: RT-012 | B22: Test creating route with past EffectiveFrom date | C22: 1. Login as admin 2. Navigate to Route Management 3. Click "Create Route" 4. Fill route name, vehicle, pickup points 5. Set EffectiveFrom = yesterday 6. Click "Create Route" | D22: 1. Error message "EffectiveFrom date cannot be in the past" 2. Route not created | E22: None | F22: Passed | G22: 45928 | H22: HuyNLQ | I22: Passed | J22: 45960 | K22: NhiPTK | L22: Passed | M22: 45986 | N22: NhiPTK
A23: RT-013 | B23: Test creating route with EffectiveTo before EffectiveFrom | C23: 1. Login as admin 2. Navigate to Route Management 3. Click "Create Route" 4. Fill route name, vehicle, pickup points 5. Set EffectiveFrom = tomorrow, EffectiveTo = today 6. Click "Create Route" | D23: 1. Error message "EffectiveTo date cannot be before EffectiveFrom date" 2. Route not created | E23: None | F23: Failed | G23: 45928 | H23: HuyNLQ | I23: Passed | J23: 45960 | K23: NhiPTK | L23: Passed | M23: 45986 | N23: NhiPTK
... A30: RT-020 | B30: Test bulk create with shared schedule | C30: 1. Login as admin 2. Navigate to Route Management 3. Add 3 routes 4. Set shared schedule for all routes 5. Click "Create All" | D30: 1. Success message "3 routes created successfully" 2. All routes have same schedule assigned 3. 3 RouteSchedule records created | E30: 1. Valid schedule exists | F30: Passed | G30: 45928 | H30: HuyNLQ | I30: Passed | J30: 45960 | K30: NhiPTK | L30: Passed | M30: 45986 | N30: NhiPTK
A31: VIEW_ALL_ROUTES
A32: RT-021 | B32: Test viewing all routes as admin | C32: 1. Login as admin 2. Navigate to Route Management 3. View routes list | D32: 1. All routes displayed (including active and inactive) 2. Each route shows: name, vehicle, pickup points, status 3. Pickup points sorted by sequence order 4. Student count displayed for each pickup point | E32: 1. At least 3 routes exist in system | F32: Passed | G32: 45928 | H32: HuyNLQ | I32: Passed | J32: 45960 | K32: NhiPTK | L32: Passed | M32: 45986 | N32: NhiPTK
A33: RT-022 | B33: Test route list shows vehicle information | C33: 1. Login as admin 2. Navigate to Route Management 3. View routes list | D33: 1. Each route displays vehicle number plate 2. Vehicle capacity shown 3. Vehicle info correctly populated | E33: 1. Routes with assigned vehicles exist | F33: Passed | G33: 45928 | H33: HuyNLQ | I33: Passed | J33: 45960 | K33: NhiPTK | L33: Passed | M33: 45986 | N33: NhiPTK
A34: RT-023 | B34: Test updating vehicle that doesn't exist | C34: 1.Login as admin 2.Navigate to update URL with invalid vehicle ID | D34: 1.API returns 404 2.Error message "Vehicle not found" | E34: 1. Invalid vehicle ID | F34: Passed | G34: 45928 | H34: HuyNLQ | I34: Passed | J34: 45960 | K34: NhiPTK | L34: Passed | M34: 45986 | N34: NhiPTK
A35: RT-024 | B35: Test route list shows student count per pickup point | C35: 1. Login as admin 2. Navigate to Route Management 3. View routes list 4. Expand pickup points for a route | D35: 1. Each pickup point shows number of active students 2. Student count is accurate 3. Only active students counted | E35: 1. Routes with pickup points having students | F35: Passed | G35: 45928 | H35: HuyNLQ | I35: Passed | J35: 45960 | K35: NhiPTK | L35: Passed | M35: 45986 | N35: NhiPTK
A36: RT-025 | B36: Test empty route list | C36: 1. Login as admin 2. Navigate to Route Management 3. View routes list (when no routes exist) | D36: 1. Message "No routes found" displayed 2. Option to create new route shown | E36: 1. No routes in system | F36: Passed | G36: 45928 | H36: HuyNLQ | I36: Passed | J36: 45960 | K36: NhiPTK | L36: Passed | M36: 45986 | N36: NhiPTK
A37: RT-026 | B37: Test deleted routes are not shown | C37: 1. Login as admin 2. Navigate to Route Management 3. View routes list | D37: 1. Deleted routes (IsDeleted=true) not displayed 2. Only non-deleted routes shown | E37: 1. Some routes are soft-deleted | F37: Passed | G37: 45928 | H37: HuyNLQ | I37: Passed | J37: 45960 | K37: NhiPTK | L37: Passed | M37: 45986 | N37: NhiPTK
A38: RT-027 | B38: Test route list sorting by sequence order | C38: 1. Login as admin 2. Navigate to Route Management 3. View a route's pickup points | D38: 1. Pickup points displayed in sequence order 2. Order: 1, 2, 3, ... (ascending) | E38: 1. Route with multiple pickup points | F38: Passed | G38: 45928 | H38: HuyNLQ | I38: Passed | J38: 45960 | K38: NhiPTK | L38: Passed | M38: 45986 | N38: NhiPTK
A39: VIEW ROUTE DETAIL
A40: RT-028 | B40: Test viewing route detail with valid route ID | C40: 1. Login as admin 2. Navigate to Route Management 3. Click on route "Route A - District 1" 4. View route details | D40: 1. Route details displayed: name, vehicle, pickup points, timestamps 2. Vehicle info shown: capacity, number plate 3. Pickup points with locations and student counts 4. IsActive status displayed | E40: 1. Route "Route A - District 1" exists | F40: Passed | G40: 45928 | H40: HuyNLQ | I40: Passed | J40: 45960 | K40: NhiPTK | L40: Passed | M40: 45986 | N40: NhiPTK
A41: RT-029 | B41: Test viewing non-existent route | C41: 1. Login as admin 2. Navigate to URL /api/routes/{invalid-guid} 3. Try to view route | D41: 1. HTTP 404 Not Found 2. Error message "Route not found" | E41: None | F41: Passed | G41: 45928 | H41: HuyNLQ | I41: Passed | J41: 45960 | K41: NhiPTK | L41: Passed | M41: 45986 | N41: NhiPTK
A42: RT-030 | B42: Test viewing deleted route | C42: 1. Login as admin 2. Try to view route with IsDeleted=true 3. Access route by ID | D42: 1. HTTP 404 Not Found 2. Error message "Route not found" 3. Deleted route treated as not found | E42: 1. Route exists with IsDeleted=true | F42: Passed | G42: 45928 | H42: HuyNLQ | I42: Passed | J42: 45960 | K42: NhiPTK | L42: Passed | M42: 45986 | N42: NhiPTK
A43: RT-031 | B43: Test viewing route with empty GUID | C43: 1. Login as admin 2. Navigate to /api/routes/00000000-0000-0000-0000-000000000000 | D43: 1. HTTP 400 Bad Request 2. Error message "Invalid route ID" | E43: None | F43: Passed | G43: 45928 | H43: HuyNLQ | I43: Passed | J43: 45960 | K43: NhiPTK | L43: Passed | M43: 45986 | N43: NhiPTK
A44: RT-032 | B44: Test route detail shows complete location information | C44: 1. Login as admin 2. Navigate to Route Management 3. View route detail 4. Check pickup point locations | D44: 1. Each pickup point shows latitude, longitude, address 2. Location data is accurate 3. Map can be rendered with coordinates | E44: 1. Route with pickup points exists | F44: Passed | G44: 45928 | H44: HuyNLQ | I44: Passed | J44: 45960 | K44: NhiPTK | L44: Passed | M44: 45986 | N44: NhiPTK
A45: RT-033 | B45: Test route detail shows timestamps | C45: 1. Login as admin 2. Navigate to Route Management 3. View route detail | D45: 1. CreatedAt timestamp displayed 2. UpdatedAt timestamp displayed (if route was updated) 3. Timestamps in correct format | E45: 1. Route exists | F45: Passed | G45: 45928 | H45: HuyNLQ | I45: Passed | J45: 45960 | K45: NhiPTK | L45: Passed | M45: 45986 | N45: NhiPTK
A46: UPDATE_ROUTE
A47: RT-034 | B47: Test updating route name with valid data | C47: 1. Login as admin 2. Navigate to Route Management 3. Click "Edit" on route "Route A" 4. Change name to "Route A - Updated" 5. Click "Update Route" | D47: 1. Success message "Route updated successfully" 2. Route name changed to "Route A - Updated" 3. UpdatedAt timestamp updated | E47: 1. Route "Route A" exists | F47: Passed | G47: 45928 | H47: HuyNLQ | I47: Passed | J47: 45960 | K47: NhiPTK | L47: Passed | M47: 45986 | N47: NhiPTK
A48: RT-035 | B48: Test updating route name to duplicate name | C48: 1. Login as admin 2. Navigate to Route Management 3. Edit route "Route A" 4. Change name to "Route B" (already exists) 5. Click "Update Route" | D48: 1. Error message "Route name already exists" 2. Route not updated 3. Name remains unchanged | E48: 1. Routes "Route A" and "Route B" both exist | F48: Passed | G48: 45928 | H48: HuyNLQ | I48: Passed | J48: 45960 | K48: NhiPTK | L48: Passed | M48: 45986 | N48: NhiPTK
A49: RT-036 | B49: Test updating route vehicle to new valid vehicle | C49: 1. Login as admin 2. Navigate to Route Management 3. Edit route "Route A" 4. Change vehicle from "30H-12345" to "30H-67890" 5. Click "Update Route" | D49: 1. Success message appears 2. Route now assigned to vehicle "30H-67890" 3. Old vehicle "30H-12345" is released | E49: 1. Route A with vehicle "30H-12345" 2. Vehicle "30H-67890" is available | F49: Passed | G49: 45928 | H49: HuyNLQ | I49: Passed | J49: 45960 | K49: NhiPTK | L49: Passed | M49: 45986 | N49: NhiPTK
A50: RT-037 | B50: Test updating route vehicle to one already in use | C50: 1. Login as admin 2. Navigate to Route Management 3. Edit route "Route A" 4. Try to assign vehicle "30H-99999" (used by Route B) 5. Click "Update Route" | D50: 1. Error message "Vehicle with license plate '30H-99999' is already used in other active routes" 2. Route not updated | E50: 1. Route B using vehicle "30H-99999" | F50: Passed | G50: 45928 | H50: HuyNLQ | I50: Passed | J50: 45960 | K50: NhiPTK | L50: Passed | M50: 45986 | N50: NhiPTK
A51: RT-038 | B51: Test updating route pickup points | C51: 1. Login as admin 2. Navigate to Route Management 3. Edit route "Route A" 4. Remove pickup point #1, add new pickup point #4 5. Click "Update Route" | D51: 1. Success message appears 2. Pickup points updated 3. New pickup point added with correct sequence order 4. Location info populated automatically | E51: 1. Route A with 3 pickup points 2. Valid pickup point available to add | F51: Passed | G51: 45928 | H51: HuyNLQ | I51: Passed | J51: 45960 | K51: NhiPTK | L51: Passed | M51: 45986 | N51: NhiPTK
A52: RT-039 | B52: Test updating pickup points with duplicate sequence orders | C52: 1. Login as admin 2. Navigate to Route Management 3. Edit route "Route A" 4. Set two pickup points to same sequence order 2 5. Click "Update | D52: 1. Error message "Duplicate sequence orders found: 2" 2. Route not updated | E52: 1. Route A exists | F52: Passed | G52: 45928 | H52: HuyNLQ | I52: Passed | J52: 45960 | K52: NhiPTK | L52: Passed | M52: 45986 | N52: NhiPTK
A53: RT-040 | B53: Test updating route with invalid route ID | C53: 1. Login as admin 2. Send PUT request to /api/routes/{invalid-guid} 3. Provide update | D53: 1. HTTP 400 Bad Request 2. Error message "Invalid route ID" | E53: None | F53: Passed | G53: 45928 | H53: HuyNLQ | I53: Passed | J53: 45960 | K53: NhiPTK | L53: Passed | M53: 45986 | N53: NhiPTK
A54: RT-041 | B54: Test updating non-existent route | C54: 1. Login as admin 2. Send PUT request to /api/routes/{valid-but-nonexistent-guid} 3. Provide update data | D54: 1. HTTP 404 Not Found 2. Error message "Route not found" | E54: None | F54: Passed | G54: 45928 | H54: HuyNLQ | I54: Passed | J54: 45960 | K54: NhiPTK | L54: Passed | M54: 45986 | N54: NhiPTK
A55: RT-042 | B55: Test updating deleted route | C55: 1. Login as admin 2. Try to update route with IsDeleted=true 3. Send update request | D55: 1. HTTP 404 Not Found 2. Error message "Route not found" 3. Route not updated | E55: 1. Deleted route exists | F55: Passed | G55: 45928 | H55: HuyNLQ | I55: Passed | J55: 45960 | K55: NhiPTK | L55: Passed | M55: 45986 | N55: NhiPTK
A56: DELETE ROUTE
A57: RT-051 | B57: Test soft deleting a route | C57: 1. Login as admin 2. Navigate to Route Management 3. Click "Delete" on route "Route A" 4. Confirm deletion | D57: 1. Success message "Route deleted successfully" 2. Route marked as IsDeleted=true 3. Route marked as IsActive=false 4. HTTP 204 No Content returned | E57: 1. Route "Route A" exists and is active | F57: Passed | G57: 45928 | H57: HuyNLQ | I57: Passed | J57: 45960 | K57: NhiPTK | L57: Passed | M57: 45986 | N57: NhiPTK
A58: RT-052 | B58: Test deleted route disappears from list | C58: 1. Login as admin 2. Delete a route 3. View route list | D58: 1. Deleted route not shown in list 2. Route count decreased by 1 | E58: 1. Route exists | F58: Passed | G58: 45928 | H58: HuyNLQ | I58: Passed | J58: 45960 | K58: NhiPTK | L58: Passed | M58: 45986 | N58: NhiPTK
A59: RT-053 | B59: Test deleting route deactivates associated RouteSchedules | C59: 1. Login as admin 2. Delete route that has RouteSchedules 3. Check RouteSchedules | D59: 1. All RouteSchedules for this route deactivated 2. RouteSchedules IsActive=false | E59: 1. Route with active RouteSchedules | F59: Passed | G59: 45928 | H59: HuyNLQ | I59: Passed | J59: 45960 | K59: NhiPTK | L59: Passed | M59: 45986 | N59: NhiPTK
A60: RT-054 | B60: Test deleting route cascades to deactivate Trips | C60: 1. Login as admin 2. Delete route that has Trips 3. Check Trips | D60: 1. All Trips for this route deactivated 2. Trips IsActive=false 3. Cascade deactivation successful | E60: 1. Route with active Trips | F60: Passed | G60: 45928 | H60: HuyNLQ | I60: Passed | J60: 45960 | K60: NhiPTK | L60: Passed | M60: 45986 | N60: NhiPTK
A61: RT-055 | B61: Test deleting non-existent route | C61: 1. Login as admin 2. Try to delete route with non-existent ID 3. Send DELETE request | D61: 1. HTTP 404 Not Found 2. Error message "Route not found" | E61: None | F61: Passed | G61: 45928 | H61: HuyNLQ | I61: Passed | J61: 45960 | K61: NhiPTK | L61: Passed | M61: 45986 | N61: NhiPTK
A62: ACTIVATE/DEACTIVATE ROUTE
A63: RT-060 | B63: Test activating an inactive route | C63: 1. Login as admin 2. Navigate to Route Management 3. Click "Activate" on inactive route 4. Confirm activation | D63: 1. Success message "Route activated successfully" 2. Route IsActive=true 3. Route appears in active routes list | E63: 1. Inactive route exists (IsActive=false, IsDeleted=false) | F63: Passed | G63: 45928 | H63: HuyNLQ | I63: Passed | J63: 45960 | K63: NhiPTK | L63: Passed | M63: 45986 | N63: NhiPTK
A64: RT-061 | B64: Test activating already active route | C64: 1. Login as admin 2. Try to activate route that is already active | D64: 1. Success message (idempotent operation) 2. Route remains IsActive=true | E64: 1. Active route exists | F64: Passed | G64: 45928 | H64: HuyNLQ | I64: Passed | J64: 45960 | K64: NhiPTK | L64: Passed | M64: 45986 | N64: NhiPTK
A65: RT-062 | B65: Test activating deleted route | C65: 1. Login as admin 2. Try to activate route with IsDeleted=true | D65: 1. HTTP 404 Not Found 2. Error message "Route not found" | E65: 1. Deleted route exists | F65: Passed | G65: 45928 | H65: HuyNLQ | I65: Passed | J65: 45960 | K65: NhiPTK | L65: Passed | M65: 45986 | N65: NhiPTK
A66: ASSIGN DRIVER/SUPERVISOR TO ROUTE
A67: RT-078 | B67: Test assigning schedule to route (which includes driver/supervisor) | C67: 1. Login as admin 2. Navigate to Route Management 3. Select route "Route A" 4. Click "Assign Schedule" 5. Select schedule "Morning Shift" (has driver and supervisor) 6. Set EffectiveFrom = tomorrow 7. Click "Assign" | D67: 1. Success message "Schedule assigned successfully" 2. RouteSchedule created 3. Route linked to schedule 4. Driver and supervisor info accessible via schedule | E67: 1. Route "Route A" exists 2. Schedule "Morning Shift" with assigned driver/supervisor | F67: Passed | G67: 45928 | H67: HuyNLQ | I67: Passed | J67: 45960 | K67: NhiPTK | L67: Passed | M67: 45986 | N67: NhiPTK
A68: RT-079 | B68: Test assigning schedule when creating route | C68: 1. Login as admin 2. Create new route 3. In creation form, add RouteSchedule section 4. Select schedule, set dates 5. Create route | D68: 1. Route created successfully 2. RouteSchedule created automatically 3. Both entities linked | E68: 1. Valid schedule exists | F68: Passed | G68: 45928 | H68: HuyNLQ | I68: Passed | J68: 45960 | K68: NhiPTK | L68: Passed | M68: 45986 | N68: NhiPTK
A69: RT-080 | B69: Test viewing route schedules for a route | C69: 1. Login as admin 2. Navigate to Route Management 3. View route "Route A" 4. Click "View Schedules" | D69: 1. All RouteSchedules for route displayed 2. Schedule details shown: EffectiveFrom, EffectiveTo, Priority 3. Associated driver/supervisor info visible | E69: 1. Route A with assigned schedules | F69: Passed | G69: 45928 | H69: HuyNLQ | I69: Passed | J69: 45960 | K69: NhiPTK | L69: Passed | M69: 45986 | N69: NhiPTK
A70: RT-081 | B70: Test creating RouteSchedule with invalid schedule ID | C70: 1. Login as admin 2. Navigate to RouteSchedule Management 3. Try to create RouteSchedule 4. Use non-existent ScheduleId 5. Submit | D70: 1. Error message "Schedule with ID {id} does not exist or is not active" 2. RouteSchedule not created | E70: None | F70: Passed | G70: 45928 | H70: HuyNLQ | I70: Passed | J70: 45960 | K70: NhiPTK | L70: Passed | M70: 45986 | N70: NhiPTK
A71: RT-082 | B71: Test creating RouteSchedule with inactive schedule | C71: 1. Login as admin 2. Try to assign inactive schedule to route 3. Submit | D71: 1. Error message "Schedule does not exist or is not active" 2. Assignment rejected | E71: 1. Inactive schedule exists | F71: Passed | G71: 45928 | H71: HuyNLQ | I71: Passed | J71: 45960 | K71: NhiPTK | L71: Passed | M71: 45986 | N71: NhiPTK

Sheet Trip Management
A2: Feature | B2: Trip Management | R2: Passed
A3: Test requirement | B3: Verifies the complete trip management flow—including creating, starting, monitoring, and completing trips—covering real-time tracking, attendance integration, route/time validation, conflict detection, and proper role-based access. | R3: Failed
A4: Number of TCs | B4: =COUNTA(A12:A880)-10 -> 52 | R4: Pending
A5: Testing Round | B5: Passed | C5: Failed | D5: Pending | E5: N/A | R5: N/A
A6: Round 1 | B6: =COUNTIF($F10:$F878,B5) -> 49 | C6: =COUNTIF($F10:$F878,C5) -> 3 | D6: =COUNTIF($F10:$F878,D5) -> 0 | E6: =COUNTIF($F10:$F878,E5) -> 0
A7: Round 2 | B7: =COUNTIF($I10:$I895,B5) -> 50 | C7: =COUNTIF($I10:$FI895,C5) -> 2 | D7: =COUNTIF($F10:$F878,D5) -> 0 | E7: =COUNTIF($F10:$F878,E5) -> 0
A8: Round 3 | B8: =COUNTIF($L10:$L895,B5) -> 52 | C8: =COUNTIF($L10:$L895,C5) -> 0 | D8: =COUNTIF($F10:$F878,D5) -> 0 | E8: =COUNTIF($F10:$F878,E5) -> 0
A10: Test Case ID | B10: Test Case Description | C10: Test Case Procedure | D10: Expected Results | E10: Pre-conditions | F10: Round 1 | G10: Test date | H10: Tester | I10: Round 2 | J10: Test date | K10: Tester | L10: Round 3 | M10: Test date | N10: Tester | O10: Note
A11: CREATE_TRIP
A12: TR-001 | B12: Test creating a new trip with all valid information | C12: 1. Login as admin 2. Navigate to Trip Management 3. Click "Create Trip" 4. Fill route ID, service date (tomorrow) 5. Set planned start time "07:00", planned end time "08:30" 6. Click "Create Trip" | D12: 1. Success message appears 2. Trip created successfully 3. Redirected to trip list 4. New trip appears with status "Scheduled" 5. Stops automatically populated from route | E12: 1. Admin session active 2. At least 1 active route exists 3. Service date is in the future | F12: Passed | G12: 45935 | H12: TrungNVT | I12: Passed | J12: 45971 | K12: KhoiVN | L12: Passed | M12: 46004 | N12: NguyetNTT
A13: TR-002 | B13: Test validation for invalid route ID | C13: 1. Login as admin 2. Navigate to Trip Management 3. Click "Create Trip" 4. Use non-existent route ID 5. Fill other valid fields 6. Click "Create Trip" | D13: 1. Error message "Route not found" 2. Trip not created | E13: None | F13: Passed | G13: 45935 | H13: TrungNVT | I13: Passed | J13: 45971 | K13: KhoiVN | L13: Passed | M13: 46004 | N13: NguyetNTT
A14: TR-003 | B14: Test creating trip with past service date | C14: 1. Login as admin 2. Navigate to Trip Management 3. Click "Create Trip" 4. Set service date = yesterday 5. Fill other fields 6. Click "Create Trip" | D14: 1. Validation error or warning about past date 2. Trip creation may be blocked or flagged | E14: None | F14: Passed | G14: 45935 | H14: TrungNVT | I14: Passed | J14: 45971 | K14: KhoiVN | L14: Passed | M14: 46004 | N14: NguyetNTT
A15: TR-004 | B15: Test creating duplicate trip (same route, same date) | C15: 1. Login as admin 2. Create trip for Route A, date = tomorrow 3. Try to create another trip with same route, same date 4. Submit | D15: 1. Warning or error about duplicate trip 2. System may allow or block based on business rules | E15: 1. Trip already exists for Route A tomorrow | F15: Passed | G15: 45935 | H15: TrungNVT | I15: Passed | J15: 45971 | K15: KhoiVN | L15: Passed | M15: 46004 | N15: NguyetNTT
A16: TR-005 | B16: Test validating planned start/end times | C16: 1. Login as admin 2. Create trip 3. Set planned end time before planned start time 4. Submit | D16: 1. Validation error "End time must be after start time" 2. Trip not created | E16: None | F16: Passed | G16: 45935 | H16: TrungNVT | I16: Passed | J16: 45971 | K16: KhoiVN | L16: Passed | M16: 46004 | N16: NguyetNTT
A17: VIEW ALL TRIPS
A18: TR-006 | B18: Test viewing all trips with pagination | C18: 1. Login as admin 2. Navigate to Trip Management 3. View trips list 4. Set page=1, perPage=20 | D18: 1. List of trips displayed (max 20) 2. Pagination info shown: page, perPage, totalPages, hasNextPage 3. Each trip shows: route name, service date, status, vehicle plate | E18: 1. At least 25 trips exist | F18: Passed | G18: 45935 | H18: TrungNVT | I18: Passed | J18: 45971 | K18: KhoiVN | L18: Passed | M18: 46004 | N18: NguyetNTT
A19: TR-007 | B19: Test filtering trips by route | C19: 1. Login as admin 2. Navigate to Trip Management 3. Apply filter: routeId = {specific route} 4. View results | D19: 1. Only trips for specified route displayed 2. Filter applied correctly | E19: 1. Trips for multiple routes exist | F19: Passed | G19: 45935 | H19: TrungNVT | I19: Passed | J19: 45971 | K19: KhoiVN | L19: Passed | M19: 46004 | N19: NguyetNTT
A20: TR-008 | B20: Test filtering trips by service date | C20: 1. Login as admin 2. Navigate to Trip Management 3. Apply filter: serviceDate = "2025-12-05" 4. View results | D20: 1. Only trips for December 5, 2025 displayed 2. Date filter working correctly | E20: 1. Trips for multiple dates exist | F20: Passed | G20: 45935 | H20: TrungNVT | I20: Passed | J20: 45971 | K20: KhoiVN | L20: Passed | M20: 46004 | N20: NguyetNTT
A21: TR-009 | B21: Test filtering trips by status | C21: 1. Login as admin 2. Navigate to Trip Management 3. Apply filter: status = "InProgress" 4. View results | D21: 1. Only trips with "InProgress" status shown 2. Status filter | E21: 1. Trips with various statuses exist | F21: Passed | G21: 45935 | H21: TrungNVT | I21: Passed | J21: 45971 | K21: KhoiVN | L21: Passed | M21: 46004 | N21: NguyetNTT
A22: TR-010 | B22: Test filtering trips by date range | C22: 1. Login as admin 2. Navigate to Trip Management 3. Set startDate = "2025-12-01", endDate = "2025-12-10" 4. View results | D22: 1. Trips within date range displayed 2. Trips outside range excluded | E22: 1. Trips across multiple months exist | F22: Passed | G22: 45935 | H22: TrungNVT | I22: Passed | J22: 45971 | K22: KhoiVN | L22: Passed | M22: 46004 | N22: NguyetNTT
A23: TR-011 | B23: Test viewing upcoming trips (next 7 days) | C23: 1. Login as admin 2. Navigate to Trip Management 3. Set sortBy="serviceDate", sortOrder="desc" 4. View results | D23: 1. Trips sorted newest to oldest 2. Most recent trips appear first | E23: 1. Multiple trips exist | F23: Passed | G23: 45935 | H23: TrungNVT | I23: Passed | J23: 45971 | K23: KhoiVN | L23: Passed | M23: 46004 | N23: NguyetNTT
A24: TR-012 | B24: Test viewing upcoming trips (next 7 days) | C24: 1. Login as admin 2. Call GET /api/trip with upcomingDays=7 3. View results | D24: 1. Only trips in next 7 days returned 2. No pagination applied (all results) 3. Past trips excluded | E24: 1. Mix of past and future trips | F24: Passed | G24: 45935 | H24: TrungNVT | I24: Passed | J24: 45971 | K24: KhoiVN | L24: Passed | M24: 46004 | N24: NguyetNTT
A25: VIEW TRIP DETAIL
A26: TR-014 | B26: Test viewing trip detail with valid trip ID (Admin) | C26: 1. Login as admin 2. Navigate to Trip Management 3. Click on specific trip 4. View trip details | D26: 1. Complete trip information displayed 2. Route name, service date, planned/actual times 3. All stops with attendance 4. Vehicle, driver, supervisor info 5. Current location if trip in progress | E26: 1. Trip exists | F26: Passed | G26: 45935 | H26: TrungNVT | I26: Passed | J26: 45971 | K26: KhoiVN | L26: Passed | M26: 46004 | N26: NguyetNTT
A27: TR-015 | B27: Test viewing non-existent trip | C27: 1. Login as admin 2. Navigate to /api/trip/{invalid-guid} 3. Try to view | D27: 1. HTTP 404 Not Found 2. Error message "Trip not found" | E27: None | F27: Passed | G27: 45935 | H27: TrungNVT | I27: Passed | J27: 45971 | K27: KhoiVN | L27: Passed | M27: 46004 | N27: NguyetNTT
A28: TR-016 | B28: Test viewing deleted trip | C28: 1. Login as admin 2. Try to view trip with IsDeleted=true 3. Access by ID | D28: 1. HTTP 404 Not Found 2. Error message "Trip not found" | E28: 1. Deleted trip exists | F28: Passed | G28: 45935 | H28: TrungNVT | I28: Passed | J28: 45971 | K28: KhoiVN | L28: Passed | M28: 46004 | N28: NguyetNTT
A29: TR-017 | B29: Test trip detail shows all stops with proper sequence | C29: 1. Login as admin 2. View trip detail 3. Check stops section | D29: 1. All stops displayed 2. Stops sorted by sequence order 3. Each stop shows: planned time, actual arrival/departure, location, attendance | E29: 1. Trip with multiple stops | F29: Passed | G29: 45935 | H29: TrungNVT | I29: Passed | J29: 45971 | K29: KhoiVN | L29: Passed | M29: 46004 | N29: NguyetNTT
A30: UPDATE TRIP
A31: TR-018 | B31: Test updating trip planned times | C31: 1. Login as admin 2. Navigate to Trip Management 3. Edit trip 4. Change planned start from "07:00" to "07:30" 5. Change planned end from "08:30" to "09:00" 6. Save changes | D31: 1. Success message 2. Trip updated successfully 3. New times reflected 4. HTTP 204 No Content | E31: 1. Trip exists with Scheduled status | F31: Passed | G31: 45935 | H31: TrungNVT | I31: Passed | J31: 45971 | K31: KhoiVN | L31: Passed | M31: 46004 | N31: NguyetNTT
A32: TR-019 | B32: Test updating trip status | C32: 1. Login as admin 2. Call PUT /api/trip/{id}/status 3. Change status from "Scheduled" to "InProgress" 4. Provide reason "Started early" | D32: 1. Success message 2. Trip status updated 3. Reason stored 4. Timestamp recorded | E32: 1. Trip in Scheduled status | F32: Passed | G32: 45935 | H32: TrungNVT | I32: Passed | J32: 45971 | K32: KhoiVN | L32: Passed | M32: 46004 | N32: NguyetNTT
A33: TR-020 | B33: Test updating trip with ID mismatch | C33: 1. Login as admin 2. Send PUT /api/trip/{id1} 3. Body contains different ID {id2} 4. Submit | D33: 1. HTTP 400 Bad Request 2. Error message "ID mismatch" | E33: None | F33: Passed | G33: 45935 | H33: TrungNVT | I33: Passed | J33: 45971 | K33: KhoiVN | L33: Passed | M33: 46004 | N33: NguyetNTT
A34: TR-021 | B34: Test updating non-existent trip | C34: 1. Login as admin 2. Send PUT request to non-existent trip ID 3. Provide update data | D34: 1. HTTP 404 Not Found 2. Error message "Trip not found" | E34: None | F34: Passed | G34: 45935 | H34: TrungNVT | I34: Passed | J34: 45971 | K34: KhoiVN | L34: Passed | M34: 46004 | N34: NguyetNTT
A35: TR-022 | B35: Test updating attendance for a stop | C35: 1. Login as admin 2. Call PUT /api/trip/{id}/attendance 3. Update student attendance: studentId, stopId, state="CheckedIn" 4. Submit | D35: 1. Success message 2. Attendance updated 3. BoardedAt timestamp set | E35: 1. Trip with stops and students | F35: Passed | G35: 45935 | H35: TrungNVT | I35: Passed | J35: 45971 | K35: KhoiVN | L35: Passed | M35: 46004 | N35: NguyetNTT
A36: DELETE TRIP
A37: TR-023 | B37: Test soft deleting a trip (Admin) | C37: 1. Login as admin 2. Navigate to Trip Management 3. Click "Delete" on trip 4. Confirm deletion | D37: 1. Success message 2. Trip marked as IsDeleted=true 3. Trip removed from list 4. HTTP 204 No Content | E37: 1. Trip exists | F37: Passed | G37: 45935 | H37: TrungNVT | I37: Passed | J37: 45971 | K37: KhoiVN | L37: Passed | M37: 46004 | N37: NguyetNTT
A38: TR-024 | B38: Test deleting trip that is InProgress | C38: 1. Login as admin 2. Try to delete trip with status "InProgress" 3. Confirm | D38: 1. Warning message or confirmation required 2. Trip deleted if confirmed 3. Status change recorded | E38: 1. Trip in InProgress status | F38: Passed | G38: 45935 | H38: TrungNVT | I38: Passed | J38: 45971 | K38: KhoiVN | L38: Passed | M38: 46004 | N38: NguyetNTT
A39: TR-025 | B39: Test deleting non-existent trip | C39: 1. Login as admin 2. Send DELETE to non-existent trip ID | D39: 1. HTTP 404 Not Found 2. Error message "Trip not found" | E39: None | F39: Passed | G39: 45935 | H39: TrungNVT | I39: Passed | J39: 45971 | K39: KhoiVN | L39: Passed | M39: 46004 | N39: NguyetNTT
A40: TR-026 | B40: Test deleting already deleted trip | C40: 1. Login as admin 2. Try to delete trip already marked IsDeleted=true | D40: 1. HTTP 404 Not Found 2. Error message "Trip not found" | E40: 1. Deleted trip exists | F40: Passed | G40: 45935 | H40: TrungNVT | I40: Passed | J40: 45971 | K40: KhoiVN | L40: Passed | M40: 46004 | N40: NguyetNTT
A41: TR-027 | B41: Test deleted trip disappears from active list | C41: 1. Login as admin 2. Delete a trip 3. View trip list | D41: 1. Deleted trip not shown 2. Trip count decreased | E41: 1. Trip exists | F41: Passed | G41: 45935 | H41: TrungNVT | I41: Passed | J41: 45971 | K41: KhoiVN | L41: Passed | M41: 46004 | N41: NguyetNTT
A42: START TRIP
A43: TR-028 | B43: Test driver starting a scheduled trip | C43: 1. Login as driver 2. Navigate to My Trips 3. Select today's scheduled trip 4. Click "Start Trip" | D43: 1. Success message "Trip started successfully" 2. Trip status changed to "InProgress" 3. StartTime timestamp set to current time 4. Driver can now update location and attendance | E43: 1. Driver assigned to trip 2. Trip status = "Scheduled" 3. Service date = today | F43: Passed | G43: 45935 | H43: TrungNVT | I43: Passed | J43: 45971 | K43: KhoiVN | L43: Passed | M43: 46004 | N43: NguyetNTT
A44: TR-029 | B44: Test starting trip by unauthorized driver | C44: 1. Login as driver A 2. Try to start trip assigned to driver B 3. Call POST /api/trip/{tripId}/start | D44: 1. HTTP 400 Bad Request or 403 Forbidden 2. Error "You don't have access to this trip" 3. Trip not started | E44: 1. Trip assigned to different driver | F44: Passed | G44: 45935 | H44: TrungNVT | I44: Passed | J44: 45971 | K44: KhoiVN | L44: Passed | M44: 46004 | N44: NguyetNTT
A45: TR-030 | B45: Test starting trip not in Scheduled status | C45: 1. Login as driver 2. Try to start trip already InProgress 3. Call POST /api/trip/{id}/start | D45: 1. HTTP 400 Bad Request 2. Error "Trip is not in Scheduled status" 3. No changes made | E45: 1. Trip status = "InProgress" or "Completed" | F45: Passed | G45: 45935 | H45: TrungNVT | I45: Passed | J45: 45971 | K45: KhoiVN | L45: Passed | M45: 46004 | N45: NguyetNTT
A46: TR-031 | B46: Test starting non-existent trip | C46: 1. Login as driver 2. Call POST /api/trip/{invalid-id}/start | D46: 1. HTTP 400 Bad Request or 404 2. Error message "Trip not found" | E46: None | F46: Passed | G46: 45935 | H46: TrungNVT | I46: Passed | J46: 45971 | K46: KhoiVN | L46: Passed | M46: 46004 | N46: NguyetNTT
A47: TR-032 | B47: Test unauthorized user (non-driver) starting trip | C47: 1. Login as parent or admin (not driver role) 2. Try to call start trip endpoint | D47: 1. HTTP 403 Forbidden 2. Role authorization error | E47: 1. User without Driver role | F47: Passed | G47: 45935 | H47: TrungNVT | I47: Passed | J47: 45971 | K47: KhoiVN | L47: Passed | M47: 46004 | N47: NguyetNTT
A48: END_TRIP
A49: TR-033 | B49: Test driver ending an in-progress trip | C49: 1. Login as driver 2. Navigate to active trip 3. Click "End Trip" | D49: 1. Success message "Trip ended successfully" 2. Trip status changed to "Completed" 3. EndTime timestamp set 4. Trip summary may be calculated | E49: 1. Driver assigned to trip 2. Trip status = "InProgress" | F49: Passed | G49: 45935 | H49: TrungNVT | I49: Passed | J49: 45971 | K49: KhoiVN | L49: Passed | M49: 46004 | N49: NguyetNTT
A50: TR-034 | B50: Test ending trip by unauthorized driver | C50: 1. Login as driver A 2. Try to end trip assigned to driver B 3. Call POST /api/trip/{tripId}/end | D50: 1. HTTP 400 Bad Request or 403 2. Error "You don't have access" 3. Trip not ended | E50: 1. Trip assigned to different driver | F50: Passed | G50: 45935 | H50: TrungNVT | I50: Passed | J50: 45971 | K50: KhoiVN | L50: Passed | M50: 46004 | N50: NguyetNTT
A51: TR-035 | B51: Test ending trip not in InProgress status | C51: 1. Login as driver 2. Try to end trip with status "Scheduled" 3. Call POST /api/trip/{id}/end | D51: 1. HTTP 400 Bad Request 2. Error "Trip is not in InProgress status" 3. No changes made | E51: 1. Trip status = "Scheduled" | F51: Passed | G51: 45935 | H51: TrungNVT | I51: Passed | J51: 45971 | K51: KhoiVN | L51: Passed | M51: 46004 | N51: NguyetNTT
A52: TR-036 | B52: Test ending trip without completing all stops | C52: 1. Login as driver 2. Trip has 5 stops, only 3 completed 3. Click "End Trip" | D52: 1. Warning or confirmation dialog 2. If confirmed, trip ends 3. Incomplete stops flagged | E52: 1. Trip InProgress with incomplete stops | F52: Passed | G52: 45935 | H52: TrungNVT | I52: Passed | J52: 45971 | K52: KhoiVN | L52: Passed | M52: 46004 | N52: NguyetNTT
A53: VIEW_HISTORY
A54: TR-058 | B54: Test driver viewing trips by date | C54: 1. Login as driver 2. Call GET /api/trip/by-date?date=2025-12-01 3. View results | D54: 1. List of trips for December 1, 2025 2. Only trips assigned to this driver 3. Each trip shows: id, name, plannedStart, plannedEnd, vehicle plate, status, totalStops, completedStops 4. Date filter working | E54: 1. Driver has trips on specified date | F54: Passed | G54: 45935 | H54: TrungNVT | I54: Passed | J54: 45971 | K54: KhoiVN | L54: Passed | M54: 46004 | N54: NguyetNTT
A55: TR-059 | B55: Test viewing today's trips | C55: 1. Login as driver 2. Call GET /api/trip/by-date (no date param, defaults to today) 3. View results | D55: 1. List of today's trips returned 2. Only driver's trips shown 3. Trips sorted by planned start time | E55: 1. Driver has trips today | F55: Passed | G55: 45935 | H55: TrungNVT | I55: Passed | J55: 45971 | K55: KhoiVN | L55: Passed | M55: 46004 | N55: NguyetNTT
A56: TR-060 | B56: Test viewing trip history shows completion status | C56: 1. Login as driver 2. View trips for past week 3. Check each trip | D56: 1. Completed trips show all stops completed 2. Incomplete trips show partial completion 3. totalStops and completedStops accurate | E56: 1. Driver has mix of completed/incomplete trips | F56: Passed | G56: 45935 | H56: TrungNVT | I56: Passed | J56: 45971 | K56: KhoiVN | L56: Passed | M56: 46004 | N56: NguyetNTT
A57: TR-061 | B57: Test driver viewing trip detail history | C57: 1. Login as driver 2. Trip has 5 stops, only 3 completed 3. Click "End Trip" | D57: 1. Warning or confirmation dialog 2. If confirmed, trip ends 3. Incomplete stops flagged | E57: 1. Trip InProgress with incomplete stops | F57: Passed | G57: 45935 | H57: TrungNVT | I57: Passed | J57: 45971 | K57: KhoiVN | L57: Passed | M57: 46004 | N57: NguyetNTT
A58: TR-062 | B58: Test viewing history for unauthorized trip | C58: 1. Login as driver A 2. Try to view detail for trip assigned to driver B | D58: 1. HTTP 404 Not Found 2. Error "Trip not found or you don't have access" 3. No data returned | E58: 1. Trip assigned to different driver | F58: Passed | G58: 45935 | H58: TrungNVT | I58: Passed | J58: 45971 | K58: KhoiVN | L58: Passed | M58: 46004 | N58: NguyetNTT
A59: HANDLE_ABSENT
A60: TR-063 | B60: Test supervisor marking student as absent | C60: 1. Login as supervisor 2. Navigate to today's trips 3. Select trip 4. Find student "Mike Johnson" at stop #2 5. Mark as "Absent" | D60: 1. Success message 2. Student attendance state = "Absent" 3. Timestamp recorded 4. Parent notified of absence | E60: 1. Supervisor assigned to trip 2. Trip status = InProgress or Scheduled 3. Student registered for trip | F60: Passed | G60: 45935 | H60: TrungNVT | I60: Passed | J60: 45971 | K60: KhoiVN | L60: Passed | M60: 46004 | N60: NguyetNTT
A61: TR-064 | B61: Test marking student absent after boarding | C61: 1. Login as supervisor 2. Student already checked in (BoardedAt set) 3. Try to mark as absent 4. Submit | D61: 1. Warning "Student already boarded" 2. Absent marking may be blocked or require override 3. Reason required | E61: 1. Student checked in on bus | F61: Failed | G61: 45935 | H61: TrungNVT | I61: Passed | J61: 45971 | K61: KhoiVN | L61: Passed | M61: 46004 | N61: NguyetNTT
A62: TR-065 | B62: Test supervisor viewing trip with attendance details | C62: 1. Login as supervisor 2. Call GET /api/supervisor/trips/{tripId} 3. View trip detail | D62: 1. Trip details displayed 2. All stops with students listed 3. Attendance status shown for each student 4. Absent students highlighted | E62: 1. Supervisor assigned to trip | F62: Passed | G62: 45935 | H62: TrungNVT | I62: Passed | J62: 45971 | K62: KhoiVN | L62: Passed | M62: 46004 | N62: NguyetNTT
A63: TR-066 | B63: Test unauthorized supervisor accessing trip | C63: 1. Login as supervisor A 2. Try to access trip assigned to supervisor B 3. Call GET /api/supervisor/trips/{tripId} | D63: 1. HTTP 403 Forbidden 2. Error or empty response 3. No access granted | E63: 1. Trip assigned to different supervisor | F63: Passed | G63: 45935 | H63: TrungNVT | I63: Passed | J63: 45971 | K63: KhoiVN | L63: Passed | M63: 46004 | N63: NguyetNTT
A64: GENERATE_TRIPS
A65: TR-070 | B65: Test generating trips from schedule for date range | C65: 1. Login as admin 2. Call POST /api/trip/generate-from-schedule 3. Params: scheduleId, startDate=2025-12-01, endDate=2025-12-31 4. Submit | D65: 1. Success message 2. Trips generated for all applicable days in range 3. Each trip has route, times, schedule snapshot 4. RRule evaluated correctly | E65: 1. Schedule with RRule exists 2. Schedule has active route assignments | F65: Passed | G65: 45935 | H65: TrungNVT | I65: Passed | J65: 45971 | K65: KhoiVN | L65: Passed | M65: 46004 | N65: NguyetNTT
A66: TR-071 | B66: Test generating trips for non-existent schedule | C66: 1. Login as admin 2. Call generate with invalid scheduleId 3. Submit | D66: 1. HTTP 400 or 404 error 2. Error "Schedule not found" 3. No trips created | E66: None | F66: Passed | G66: 45935 | H66: TrungNVT | I66: Failed | J66: 45971 | K66: KhoiVN | L66: Passed | M66: 46004 | N66: NguyetNTT
A67: TR-072 | B67: Test automatic trip generation (7 days ahead) | C67: 1. Login as admin 2. Call POST /api/trip/generate-all-automatic?daysAhead=7 3. Submit | D67: 1. Success response 2. Trips auto-generated for next 7 days 3. All active schedules processed 4. Result summary: total trips created, schedules processed | E67: 1. Multiple active schedules exist | F67: Passed | G67: 45935 | H67: TrungNVT | I67: Passed | J67: 45971 | K67: KhoiVN | L67: Passed | M67: 46004 | N67: NguyetNTT
A68: TR-073 | B68: Test trip generation respects schedule recurrence rule | C68: 1. Login as admin 2. Schedule with RRule "FREQ=WEEKLY;BYDAY=MO,WE,FR" 3. Generate trips for 2 weeks 4. Check results | D68: 1. Trips only generated for Mon, Wed, Fri 2. No trips on Tue, Thu, Sat, Sun 3. RRule correctly interpreted | E68: 1. Schedule with specific RRule | F68: Failed | G68: 45935 | H68: TrungNVT | I68: Passed | J68: 45971 | K68: KhoiVN | L68: Passed | M68: 46004 | N68: NguyetNTT
A69: PARENT_VIEW_TRIPS
A70: TR-075 | B70: Test parent viewing upcoming trips for their child | C70: 1. Login as parent 2. Call GET /api/trip/parent/upcoming?days=7 3. View results | D70: 1. List of trips for next 7 days 2. Only trips where child is registered 3. Each trip shows: route, date, times, status 4. Stops with child's pickup point highlighted | E70: 1. Parent has child registered for trips | F70: Passed | G70: 45935 | H70: TrungNVT | I70: Passed | J70: 45971 | K70: KhoiVN | L70: Passed | M70: 46004 | N70: NguyetNTT
A71: TR-076 | B71: Test parent viewing trips by date | C71: 1. Login as parent 2. Call GET /api/trip/parent/date?date=2025-12-05 3. View results | D71: 1. Trips for December 5, 2025 returned 2. Only trips with parent's child 3. Date filter working | E71: 1. Child has trips on specified date | F71: Passed | G71: 45935 | H71: TrungNVT | I71: Passed | J71: 45971 | K71: KhoiVN | L71: Passed | M71: 46004 | N71: NguyetNTT
A72: TR-077 | B72: Test parent viewing trip detail for unauthorized trip | C72: 1. Login as parent 2. Call GET /api/trip/parent/{tripId} 3. View trip detail | D72: 1. Full trip details shown 2. Child's stop and attendance visible 3. Vehicle and driver info shown 4. Real-time status if InProgress | E72: 1. Parent's child registered for trip | F72: Failed | G72: 45935 | H72: TrungNVT | I72: Failed | J72: 45971 | K72: KhoiVN | L72: Passed | M72: 46004 | N72: NguyetNTT
A73: TR-078 | B73: Test parent viewing trip detail for unauthorized trip | C73: 1. Login as parent A 2. Try to view trip for child of parent B 3. Call GET /api/trip/parent/{tripId} | D73: 1. HTTP 404 Not Found 2. Error "Trip not found or you don't have access" 3. No data returned | E73: 1. Trip doesn't include parent A's child | F73: Passed | G73: 45935 | H73: TrungNVT | I73: Passed | J73: 45971 | K73: KhoiVN | L73: Passed | M73: 46004 | N73: NguyetNTT

Sheet Atendance Management
A2: Feature | B2: Attendance Management | R2: Passed
A3: Test requirement | B3: Verifies the complete attendance management flow—including recording, updating, and reviewing student attendance across trips—covering check-in/out logic, validation against schedules, role permissions, real-time synchronization, and error handling. | R3: Failed
A4: Number of TCs | B4: =COUNTA(A12:A909)-7 -> 38 | R4: Pending
A5: Testing Round | B5: Passed | C5: Failed | D5: Pending | E5: N/A | R5: N/A
A6: Round 1 | B6: =COUNTIF($F10:$F907,B5) -> 32 | C6: =COUNTIF($F10:$F907,C5) -> 6 | D6: =COUNTIF($F10:$F907,D5) -> 0 | E6: =COUNTIF($F10:$F907,E5) -> 0
A7: Round 2 | B7: =COUNTIF($I10:$I895,B5) -> 35 | C7: =COUNTIF($I10:$FI895,C5) -> 3 | D7: =COUNTIF($F10:$F907,D5) -> 0 | E7: =COUNTIF($F10:$F907,E5) -> 0
A8: Round 3 | B8: =COUNTIF($L10:$L895,B5) -> 38 | C8: =COUNTIF($L10:$L895,C5) -> 0 | D8: =COUNTIF($F10:$F907,D5) -> 0 | E8: =COUNTIF($F10:$F907,E5) -> 0
A10: Test Case ID | B10: Test Case Description | C10: Test Case Procedure | D10: Expected Results | E10: Pre-conditions | F10: Round 1 | G10: Test date | H10: Tester | I10: Round 2 | J10: Test date | K10: Tester | L10: Round 3 | M10: Test date | N10: Tester | O10: Note
A11: AUTOMATED_ATTENDANCE
A12: ATT-001 | B12: Test automatic attendance recording when student checks in | C12: 1. Login as driver 2. Trip InProgress 3. At stop #2 4. Check in student "John Doe" manually 5. View attendance record | D12: 1. Attendance record created automatically 2. StudentId and StudentName populated 3. BoardedAt timestamp set to current time 4. State = "Present" 5. Record saved in trip stop attendance list | E12: 1. Trip InProgress 2. Driver at stop 3. Student assigned to this stop | F12: Failed | G12: 45935 | H12: NguyetNTT | I12: Passed | J12: 45971 | K12: NguyetNTT | L12: Passed | M12: 46004 | N12: HuyNLQ
A13: ATT-002 | B13: Test attendance state validation with valid states | C13: 1. Login as admin 2. Call PUT /api/trip/{tripId}/attendance 3. Try each valid state: "Present", "Absent", "Late", "Excused", "Pending" 4. Submit each one | D13: 1. All valid states accepted 2. Attendance updated successfully 3. No validation errors | E13: 1. Trip exists with students | F13: Passed | G13: 45935 | H13: NguyetNTT | I13: Passed | J13: 45971 | K13: NguyetNTT | L13: Passed | M13: 46004 | N13: HuyNLQ
A14: ATT-003 | B14: Test attendance state validation with invalid state | C14: 1. Login as admin 2. Call PUT /api/trip/{tripId}/attendance 3. Set state = "InvalidState" 4. Submit | D14: 1. HTTP 400 Bad Request 2. Error message "Invalid attendance state 'InvalidState'. Valid states are: Present, Absent, Late, Excused, Pending" 3. Attendance not updated | E14: None | F14: Passed | G14: 45935 | H14: NguyetNTT | I14: Passed | J14: 45971 | K14: NguyetNTT | L14: Passed | M14: 46004 | N14: HuyNLQ
A15: ATT-004 | B15: Test attendance state validation with empty/null state | C15: 1. Login as admin 2. Call PUT /api/trip/{tripId}/attendance 3. Set state = "" or null 4. Submit | D15: 1. HTTP 400 Bad Request 2. Error "Attendance state cannot be null or empty" 3. Attendance not updated | E15: None | F15: Passed | G15: 45935 | H15: NguyetNTT | I15: Passed | J15: 45971 | K15: NguyetNTT | L15: Passed | M15: 46004 | N15: HuyNLQ
A16: ATT-005 | B16: Test attendance recording for multiple students at same stop | C16: 1. Login as driver 2. At stop #2 with 5 students 3. Check in all 5 students one by one 4. View stop attendance | D16: 1. 5 attendance records created 2. Each has unique StudentId 3. All have BoardedAt timestamps 4. All have State = "Present" 5. Records in correct sequence | E16: 1. Stop with 5 assigned students | F16: Passed | G16: 45935 | H16: NguyetNTT | I16: Passed | J16: 45971 | K16: NguyetNTT | L16: Passed | M16: 46004 | N16: HuyNLQ
